Workbook

Sheet Timeline
A2: WBS ID | B2: Phase / Activity | C2: Duration (Working Days) | D2: Mode | E2: Fixed Start (optional) | F2: Start Date | G2: End Date | H2: Comments
A3: 1 | B3: 1. Project Kick-off | C3: 1 | D3: Offshore | E3: 46238 | F3: =IF(D3="Offshore",INDEX('Calendar_Dont Use this'!$A$5:$A$424,MATCH(INDEX('Calendar_Dont Use this'!$J$5:$J$424,MATCH(E3-1,'Calendar_Dont Use this'!$A$5:$A$424,0))+1,'Calendar_Dont Use this'!$J$5:$J$424,0)),INDEX('Calendar_Dont Use this'!$A$5:$A$424,MATCH(INDEX('Calendar_Dont Use this'!$I$5:$I$424,MATCH(E3-1,'Calendar_Dont Use this'!$A$5:$A$424,0))+1,'Calendar_Dont Use this'!$I$5:$I$424,0))) -> 46238 | G3: =IF(D3="Offshore",INDEX('Calendar_Dont Use this'!$A$5:$A$424,MATCH(INDEX('Calendar_Dont Use this'!$J$5:$J$424,MATCH(F3,'Calendar_Dont Use this'!$A$5:$A$424,0))+C3-1,'Calendar_Dont Use this'!$J$5:$J$424,0)),INDEX('Calendar_Dont Use this'!$A$5:$A$424,MATCH(INDEX('Calendar_Dont Use this'!$I$5:$I$424,MATCH(F3,'Calendar_Dont Use this'!$A$5:$A$424,0))+C3-1,'Calendar_Dont Use this'!$I$5:$I$424,0))) -> 46238 | H3: Formal project launch; PMT and governance confirmed. Fixed date.
A4: 2 | B4: 2. Business Process Study | C4: 12 | D4: Mix-Mode | E4: 46249 | F4: =IF(D4="Offshore",INDEX('Calendar_Dont Use this'!$A$5:$A$424,MATCH(INDEX('Calendar_Dont Use this'!$J$5:$J$424,MATCH(IF(E4<>"",E4-1,G3),'Calendar_Dont Use this'!$A$5:$A$424,0))+1,'Calendar_Dont Use this'!$J$5:$J$424,0)),INDEX('Calendar_Dont Use this'!$A$5:$A$424,MATCH(INDEX('Calendar_Dont Use this'!$I$5:$I$424,MATCH(IF(E4<>"",E4-1,G3),'Calendar_Dont Use this'!$A$5:$A$424,0))+1,'Calendar_Dont Use this'!$I$5:$I$424,0))) -> 46249 | G4: =IF(D4="Offshore",INDEX('Calendar_Dont Use this'!$A$5:$A$424,MATCH(INDEX('Calendar_Dont Use this'!$J$5:$J$424,MATCH(F4,'Calendar_Dont Use this'!$A$5:$A$424,0))+C4-1,'Calendar_Dont Use this'!$J$5:$J$424,0)),INDEX('Calendar_Dont Use this'!$A$5:$A$424,MATCH(INDEX('Calendar_Dont Use this'!$I$5:$I$424,MATCH(F4,'Calendar_Dont Use this'!$A$5:$A$424,0))+C4-1,'Calendar_Dont Use this'!$I$5:$I$424,0))) -> 46262 | H4: On-site and remote study of current farm & finance processes (7 onshore days within this window). Fixed start date, gap after kick-off for mobilisation.
A5: 3 | B5: 3. Business Blueprint | C5: 7 | D5: Offshore | F5: =IF(D5="Offshore",INDEX('Calendar_Dont Use this'!$A$5:$A$424,MATCH(INDEX('Calendar_Dont Use this'!$J$5:$J$424,MATCH(IF(E5<>"",E5-1,G4),'Calendar_Dont Use this'!$A$5:$A$424,0))+1,'Calendar_Dont Use this'!$J$5:$J$424,0)),INDEX('Calendar_Dont Use this'!$A$5:$A$424,MATCH(INDEX('Calendar_Dont Use this'!$I$5:$I$424,MATCH(IF(E5<>"",E5-1,G4),'Calendar_Dont Use this'!$A$5:$A$424,0))+1,'Calendar_Dont Use this'!$I$5:$I$424,0))) -> 46265 | G5: =IF(D5="Offshore",INDEX('Calendar_Dont Use this'!$A$5:$A$424,MATCH(INDEX('Calendar_Dont Use this'!$J$5:$J$424,MATCH(F5,'Calendar_Dont Use this'!$A$5:$A$424,0))+C5-1,'Calendar_Dont Use this'!$J$5:$J$424,0)),INDEX('Calendar_Dont Use this'!$A$5:$A$424,MATCH(INDEX('Calendar_Dont Use this'!$I$5:$I$424,MATCH(F5,'Calendar_Dont Use this'!$A$5:$A$424,0))+C5-1,'Calendar_Dont Use this'!$I$5:$I$424,0))) -> 46273 | H5: Business Blueprint Document (BBP) prepared and signed off.
A6: 4 | B6: 4. System Configuration & Customization (P1) | C6: 20 | D6: Offshore | F6: =IF(D6="Offshore",INDEX('Calendar_Dont Use this'!$A$5:$A$424,MATCH(INDEX('Calendar_Dont Use this'!$J$5:$J$424,MATCH(IF(E6<>"",E6-1,G5),'Calendar_Dont Use this'!$A$5:$A$424,0))+1,'Calendar_Dont Use this'!$J$5:$J$424,0)),INDEX('Calendar_Dont Use this'!$A$5:$A$424,MATCH(INDEX('Calendar_Dont Use this'!$I$5:$I$424,MATCH(IF(E6<>"",E6-1,G5),'Calendar_Dont Use this'!$A$5:$A$424,0))+1,'Calendar_Dont Use this'!$I$5:$I$424,0))) -> 46274 | G6: =IF(D6="Offshore",INDEX('Calendar_Dont Use this'!$A$5:$A$424,MATCH(INDEX('Calendar_Dont Use this'!$J$5:$J$424,MATCH(F6,'Calendar_Dont Use this'!$A$5:$A$424,0))+C6-1,'Calendar_Dont Use this'!$J$5:$J$424,0)),INDEX('Calendar_Dont Use this'!$A$5:$A$424,MATCH(INDEX('Calendar_Dont Use this'!$I$5:$I$424,MATCH(F6,'Calendar_Dont Use this'!$A$5:$A$424,0))+C6-1,'Calendar_Dont Use this'!$I$5:$I$424,0))) -> 46302 | H6: Core NAVFarm configuration per signed-off BBP.
A7: 5 | B7: 5. Conference Room Pilot (CRP) | C7: 3 | D7: Offshore | F7: =IF(D7="Offshore",INDEX('Calendar_Dont Use this'!$A$5:$A$424,MATCH(INDEX('Calendar_Dont Use this'!$J$5:$J$424,MATCH(IF(E7<>"",E7-1,G6),'Calendar_Dont Use this'!$A$5:$A$424,0))+1,'Calendar_Dont Use this'!$J$5:$J$424,0)),INDEX('Calendar_Dont Use this'!$A$5:$A$424,MATCH(INDEX('Calendar_Dont Use this'!$I$5:$I$424,MATCH(IF(E7<>"",E7-1,G6),'Calendar_Dont Use this'!$A$5:$A$424,0))+1,'Calendar_Dont Use this'!$I$5:$I$424,0))) -> 46303 | G7: =IF(D7="Offshore",INDEX('Calendar_Dont Use this'!$A$5:$A$424,MATCH(INDEX('Calendar_Dont Use this'!$J$5:$J$424,MATCH(F7,'Calendar_Dont Use this'!$A$5:$A$424,0))+C7-1,'Calendar_Dont Use this'!$J$5:$J$424,0)),INDEX('Calendar_Dont Use this'!$A$5:$A$424,MATCH(INDEX('Calendar_Dont Use this'!$I$5:$I$424,MATCH(F7,'Calendar_Dont Use this'!$A$5:$A$424,0))+C7-1,'Calendar_Dont Use this'!$I$5:$I$424,0))) -> 46307 | H7: Configured solution walked through with client stakeholders.
A8: 6 | B8: 6. Integration & Customization (P2) | C8: 20 | D8: Offshore | F8: =IF(D8="Offshore",INDEX('Calendar_Dont Use this'!$A$5:$A$424,MATCH(INDEX('Calendar_Dont Use this'!$J$5:$J$424,MATCH(IF(E8<>"",E8-1,G7),'Calendar_Dont Use this'!$A$5:$A$424,0))+1,'Calendar_Dont Use this'!$J$5:$J$424,0)),INDEX('Calendar_Dont Use this'!$A$5:$A$424,MATCH(INDEX('Calendar_Dont Use this'!$I$5:$I$424,MATCH(IF(E8<>"",E8-1,G7),'Calendar_Dont Use this'!$A$5:$A$424,0))+1,'Calendar_Dont Use this'!$I$5:$I$424,0))) -> 46308 | G8: =IF(D8="Offshore",INDEX('Calendar_Dont Use this'!$A$5:$A$424,MATCH(INDEX('Calendar_Dont Use this'!$J$5:$J$424,MATCH(F8,'Calendar_Dont Use this'!$A$5:$A$424,0))+C8-1,'Calendar_Dont Use this'!$J$5:$J$424,0)),INDEX('Calendar_Dont Use this'!$A$5:$A$424,MATCH(INDEX('Calendar_Dont Use this'!$I$5:$I$424,MATCH(F8,'Calendar_Dont Use this'!$A$5:$A$424,0))+C8-1,'Calendar_Dont Use this'!$I$5:$I$424,0))) -> 46338 | H8: D365BC and Pig Vision integration build.
A9: 7 | B9: 7. Key User Training | C9: 7 | D9: Onshore | F9: =IF(D9="Offshore",INDEX('Calendar_Dont Use this'!$A$5:$A$424,MATCH(INDEX('Calendar_Dont Use this'!$J$5:$J$424,MATCH(IF(E9<>"",E9-1,G8),'Calendar_Dont Use this'!$A$5:$A$424,0))+1,'Calendar_Dont Use this'!$J$5:$J$424,0)),INDEX('Calendar_Dont Use this'!$A$5:$A$424,MATCH(INDEX('Calendar_Dont Use this'!$I$5:$I$424,MATCH(IF(E9<>"",E9-1,G8),'Calendar_Dont Use this'!$A$5:$A$424,0))+1,'Calendar_Dont Use this'!$I$5:$I$424,0))) -> 46339 | G9: =IF(D9="Offshore",INDEX('Calendar_Dont Use this'!$A$5:$A$424,MATCH(INDEX('Calendar_Dont Use this'!$J$5:$J$424,MATCH(F9,'Calendar_Dont Use this'!$A$5:$A$424,0))+C9-1,'Calendar_Dont Use this'!$J$5:$J$424,0)),INDEX('Calendar_Dont Use this'!$A$5:$A$424,MATCH(INDEX('Calendar_Dont Use this'!$I$5:$I$424,MATCH(F9,'Calendar_Dont Use this'!$A$5:$A$424,0))+C9-1,'Calendar_Dont Use this'!$I$5:$I$424,0))) -> 46346 | H9: May extend up to 5 additional days with joint management approval.
A10: 8 | B10: 8. User Testing | C10: 8 | D10: Onshore | F10: =IF(D10="Offshore",INDEX('Calendar_Dont Use this'!$A$5:$A$424,MATCH(INDEX('Calendar_Dont Use this'!$J$5:$J$424,MATCH(IF(E10<>"",E10-1,G9),'Calendar_Dont Use this'!$A$5:$A$424,0))+1,'Calendar_Dont Use this'!$J$5:$J$424,0)),INDEX('Calendar_Dont Use this'!$A$5:$A$424,MATCH(INDEX('Calendar_Dont Use this'!$I$5:$I$424,MATCH(IF(E10<>"",E10-1,G9),'Calendar_Dont Use this'!$A$5:$A$424,0))+1,'Calendar_Dont Use this'!$I$5:$I$424,0))) -> 46347 | G10: =IF(D10="Offshore",INDEX('Calendar_Dont Use this'!$A$5:$A$424,MATCH(INDEX('Calendar_Dont Use this'!$J$5:$J$424,MATCH(F10,'Calendar_Dont Use this'!$A$5:$A$424,0))+C10-1,'Calendar_Dont Use this'!$J$5:$J$424,0)),INDEX('Calendar_Dont Use this'!$A$5:$A$424,MATCH(INDEX('Calendar_Dont Use this'!$I$5:$I$424,MATCH(F10,'Calendar_Dont Use this'!$A$5:$A$424,0))+C10-1,'Calendar_Dont Use this'!$I$5:$I$424,0))) -> 46356 | H10: May extend up to 5 additional days (combined with training) with joint management approval.
A11: 9 | B11: 9. Data Migration & Go-Live Preparation | C11: 7 | D11: Onshore | F11: =IF(D11="Offshore",INDEX('Calendar_Dont Use this'!$A$5:$A$424,MATCH(INDEX('Calendar_Dont Use this'!$J$5:$J$424,MATCH(IF(E11<>"",E11-1,G10),'Calendar_Dont Use this'!$A$5:$A$424,0))+1,'Calendar_Dont Use this'!$J$5:$J$424,0)),INDEX('Calendar_Dont Use this'!$A$5:$A$424,MATCH(INDEX('Calendar_Dont Use this'!$I$5:$I$424,MATCH(IF(E11<>"",E11-1,G10),'Calendar_Dont Use this'!$A$5:$A$424,0))+1,'Calendar_Dont Use this'!$I$5:$I$424,0))) -> 46357 | G11: =IF(D11="Offshore",INDEX('Calendar_Dont Use this'!$A$5:$A$424,MATCH(INDEX('Calendar_Dont Use this'!$J$5:$J$424,MATCH(F11,'Calendar_Dont Use this'!$A$5:$A$424,0))+C11-1,'Calendar_Dont Use this'!$J$5:$J$424,0)),INDEX('Calendar_Dont Use this'!$A$5:$A$424,MATCH(INDEX('Calendar_Dont Use this'!$I$5:$I$424,MATCH(F11,'Calendar_Dont Use this'!$A$5:$A$424,0))+C11-1,'Calendar_Dont Use this'!$I$5:$I$424,0))) -> 46364 | H11: 4 years of historical data migrated (client-provided in NAVFarm template format).
A12: 10 | B12: 10. Go-Live | C12: 5 | D12: Onshore | F12: =IF(D12="Offshore",INDEX('Calendar_Dont Use this'!$A$5:$A$424,MATCH(INDEX('Calendar_Dont Use this'!$J$5:$J$424,MATCH(IF(E12<>"",E12-1,G11),'Calendar_Dont Use this'!$A$5:$A$424,0))+1,'Calendar_Dont Use this'!$J$5:$J$424,0)),INDEX('Calendar_Dont Use this'!$A$5:$A$424,MATCH(INDEX('Calendar_Dont Use this'!$I$5:$I$424,MATCH(IF(E12<>"",E12-1,G11),'Calendar_Dont Use this'!$A$5:$A$424,0))+1,'Calendar_Dont Use this'!$I$5:$I$424,0))) -> 46365 | G12: =IF(D12="Offshore",INDEX('Calendar_Dont Use this'!$A$5:$A$424,MATCH(INDEX('Calendar_Dont Use this'!$J$5:$J$424,MATCH(F12,'Calendar_Dont Use this'!$A$5:$A$424,0))+C12-1,'Calendar_Dont Use this'!$J$5:$J$424,0)),INDEX('Calendar_Dont Use this'!$A$5:$A$424,MATCH(INDEX('Calendar_Dont Use this'!$I$5:$I$424,MATCH(F12,'Calendar_Dont Use this'!$A$5:$A$424,0))+C12-1,'Calendar_Dont Use this'!$I$5:$I$424,0))) -> 46370 | H12: Production cutover.
A13: 11 | B13: 11. Post Go-Live Support | C13: 30 | D13: Offshore | F13: =IF(D13="Offshore",INDEX('Calendar_Dont Use this'!$A$5:$A$424,MATCH(INDEX('Calendar_Dont Use this'!$J$5:$J$424,MATCH(IF(E13<>"",E13-1,G12),'Calendar_Dont Use this'!$A$5:$A$424,0))+1,'Calendar_Dont Use this'!$J$5:$J$424,0)),INDEX('Calendar_Dont Use this'!$A$5:$A$424,MATCH(INDEX('Calendar_Dont Use this'!$I$5:$I$424,MATCH(IF(E13<>"",E13-1,G12),'Calendar_Dont Use this'!$A$5:$A$424,0))+1,'Calendar_Dont Use this'!$I$5:$I$424,0))) -> 46371 | G13: =IF(D13="Offshore",INDEX('Calendar_Dont Use this'!$A$5:$A$424,MATCH(INDEX('Calendar_Dont Use this'!$J$5:$J$424,MATCH(F13,'Calendar_Dont Use this'!$A$5:$A$424,0))+C13-1,'Calendar_Dont Use this'!$J$5:$J$424,0)),INDEX('Calendar_Dont Use this'!$A$5:$A$424,MATCH(INDEX('Calendar_Dont Use this'!$I$5:$I$424,MATCH(F13,'Calendar_Dont Use this'!$A$5:$A$424,0))+C13-1,'Calendar_Dont Use this'!$I$5:$I$424,0))) -> 46413 | H13: Stabilization support, performance tuning, issue resolution, user enablement.
A14: 12 | B14: 12. Phase 2 - System Enhancement & Integration | C14: TBD | D14: Offshore | F14: TBD | G14: TBD | H14: Scope and timeline to be finalized separately per proposal.
B16: Total Phase 1 Duration (Working Days) | C16: =SUM(C3:C13) -> 120
B17: Go-Live Date | C17: =G12 -> 46370
B18: Project Closure (Post Go-Live Support End) | C18: =G13 -> 46413
B19: Total Calendar Span (Kick-off to Closure, days) | C19: =G13-F3+1 -> 176

Sheet Milestones
A1: Project Milestones
A2: No. | B2: Milestone | C2: Target Date | D2: Description / Exit Criteria
A3: M1 | B3: Project Kick-off Complete | C3: =Timeline!G3 -> 46238 | D3: Project charter confirmed, PMT, governance model and communication plan agreed.
A4: M2 | B4: Business Blueprint Sign-off | C4: =Timeline!G5 -> 46273 | D4: Business Blueprint Document reviewed and signed off by both parties.
A5: M3 | B5: Conference Room Pilot (CRP) Sign-off | C5: =Timeline!G7 -> 46307 | D5: Configured solution demonstrated and accepted by client stakeholders.
A6: M4 | B6: Integration & Customization Complete | C6: =Timeline!G8 -> 46338 | D6: NAVFarm-D365BC and NAVFarm-Pig Vision integrations built and unit tested.
A7: M5 | B7: Key User Training Complete | C7: =Timeline!G9 -> 46346 | D7: Key users trained at the centralized location (Head Office).
A8: M6 | B8: User Testing (UAT) Complete | C8: =Timeline!G10 -> 46356 | D8: User acceptance testing completed and signed off.
A9: M7 | B9: Data Migration Complete | C9: =Timeline!G11 -> 46364 | D9: 4 years of historical pig farm data migrated and validated in NAVFarm.
A10: M8 | B10: Go-Live | C10: =Timeline!G12 -> 46370 | D10: Production cutover, NAVFarm live across all farms.
A11: M9 | B11: Project Closure (Post Go-Live Support End) | C11: =Timeline!G13 -> 46413 | D11: 1-month stabilization support complete, project handed to AMC/support agreement.

Sheet Detailed WBS
A1: Detailed Work Breakdown Structure - Phase 1
A2: WBS ID | B2: Phase / Activity | C2: Work Package | D2: Deliverable / Task | E2: Start Date | F2: End Date | G2: Mode | H2: Owner
A3: 1.1.1 | B3: 1. Project Kick-off | C3: Project Launch | D3: Project charter and governance model confirmed | E3: =INDEX(Timeline!$F$3:$F$13,MATCH($B3,Timeline!$B$3:$B$13,0)) -> 46238 | F3: =INDEX(Timeline!$G$3:$G$13,MATCH($B3,Timeline!$B$3:$B$13,0)) -> 46238 | G3: Offshore | H3: Joint (Client & Prudence)
A4: 1.1.2 | B4: 1. Project Kick-off | C4: Project Launch | D4: Project Management Team (PMT) introduced and roles agreed | E4: =INDEX(Timeline!$F$3:$F$13,MATCH($B4,Timeline!$B$3:$B$13,0)) -> 46238 | F4: =INDEX(Timeline!$G$3:$G$13,MATCH($B4,Timeline!$B$3:$B$13,0)) -> 46238 | G4: Offshore | H4: Joint (Client & Prudence)
A5: 1.1.3 | B5: 1. Project Kick-off | C5: Project Launch | D5: Communication plan and meeting cadence agreed | E5: =INDEX(Timeline!$F$3:$F$13,MATCH($B5,Timeline!$B$3:$B$13,0)) -> 46238 | F5: =INDEX(Timeline!$G$3:$G$13,MATCH($B5,Timeline!$B$3:$B$13,0)) -> 46238 | G5: Offshore | H5: Joint (Client & Prudence)
A6: 2.1.1 | B6: 2. Business Process Study | C6: Farm Process Walkthroughs | D6: Feed, health, breeding and mortality workflows reviewed, farm by farm | E6: =INDEX(Timeline!$F$3:$F$13,MATCH($B6,Timeline!$B$3:$B$13,0)) -> 46249 | F6: =INDEX(Timeline!$G$3:$G$13,MATCH($B6,Timeline!$B$3:$B$13,0)) -> 46262 | G6: Mix-Mode | H6: Joint (Client & Prudence)
A7: 2.1.2 | B7: 2. Business Process Study | C7: Farm Process Walkthroughs | D7: Current reporting structure and MIS reviewed | E7: =INDEX(Timeline!$F$3:$F$13,MATCH($B7,Timeline!$B$3:$B$13,0)) -> 46249 | F7: =INDEX(Timeline!$G$3:$G$13,MATCH($B7,Timeline!$B$3:$B$13,0)) -> 46262 | G7: Mix-Mode | H7: Joint (Client & Prudence)
A8: 2.1.3 | B8: 2. Business Process Study | C8: Farm Process Walkthroughs | D8: Roles and responsibilities of farm and finance staff reviewed | E8: =INDEX(Timeline!$F$3:$F$13,MATCH($B8,Timeline!$B$3:$B$13,0)) -> 46249 | F8: =INDEX(Timeline!$G$3:$G$13,MATCH($B8,Timeline!$B$3:$B$13,0)) -> 46262 | G8: Mix-Mode | H8: Joint (Client & Prudence)
A9: 2.2.1 | B9: 2. Business Process Study | C9: Documentation | D9: Current-state process documentation | E9: =INDEX(Timeline!$F$3:$F$13,MATCH($B9,Timeline!$B$3:$B$13,0)) -> 46249 | F9: =INDEX(Timeline!$G$3:$G$13,MATCH($B9,Timeline!$B$3:$B$13,0)) -> 46262 | G9: Mix-Mode | H9: Prudence Consulting
A10: 2.2.2 | B10: 2. Business Process Study | C10: Documentation | D10: Gap analysis against NAVFarm standard functionality | E10: =INDEX(Timeline!$F$3:$F$13,MATCH($B10,Timeline!$B$3:$B$13,0)) -> 46249 | F10: =INDEX(Timeline!$G$3:$G$13,MATCH($B10,Timeline!$B$3:$B$13,0)) -> 46262 | G10: Mix-Mode | H10: Prudence Consulting
A11: 3.1.1 | B11: 3. Business Blueprint | C11: Business Blueprint | D11: Business Blueprint Document (BBP) prepared | E11: =INDEX(Timeline!$F$3:$F$13,MATCH($B11,Timeline!$B$3:$B$13,0)) -> 46265 | F11: =INDEX(Timeline!$G$3:$G$13,MATCH($B11,Timeline!$B$3:$B$13,0)) -> 46273 | G11: Offshore | H11: Joint (Client & Prudence)
A12: 3.1.2 | B12: 3. Business Blueprint | C12: Business Blueprint | D12: Blueprint review workshops with Triple-C stakeholders | E12: =INDEX(Timeline!$F$3:$F$13,MATCH($B12,Timeline!$B$3:$B$13,0)) -> 46265 | F12: =INDEX(Timeline!$G$3:$G$13,MATCH($B12,Timeline!$B$3:$B$13,0)) -> 46273 | G12: Offshore | H12: Joint (Client & Prudence)
A13: 3.1.3 | B13: 3. Business Blueprint | C13: Business Blueprint | D13: Blueprint sign-off by both parties | E13: =INDEX(Timeline!$F$3:$F$13,MATCH($B13,Timeline!$B$3:$B$13,0)) -> 46265 | F13: =INDEX(Timeline!$G$3:$G$13,MATCH($B13,Timeline!$B$3:$B$13,0)) -> 46273 | G13: Offshore | H13: Joint (Client & Prudence)
A14: 4.1.1 | B14: 4. System Configuration & Customization (P1) | C14: Master Data & Farm Setup | D14: Breed Master | E14: =INDEX(Timeline!$F$3:$F$13,MATCH($B14,Timeline!$B$3:$B$13,0)) -> 46274 | F14: =INDEX(Timeline!$G$3:$G$13,MATCH($B14,Timeline!$B$3:$B$13,0)) -> 46302 | G14: Offshore | H14: Prudence Consulting
... A68: 11.1.4 | B68: 11. Post Go-Live Support | C68: Post Go-Live Stabilization | D68: User enablement | E68: =INDEX(Timeline!$F$3:$F$13,MATCH($B68,Timeline!$B$3:$B$13,0)) -> 46371 | F68: =INDEX(Timeline!$G$3:$G$13,MATCH($B68,Timeline!$B$3:$B$13,0)) -> 46413 | G68: Offshore | H68: Prudence Consulting
A70: P2 | B70: Phase 2 - System Enhancement & Integration (scope & timeline TBD)
A71: P2.1 | B71: 12. Phase 2 - System Enhancement & Integration | C71: Process Enhancement | D71: Process enhancement on the NAVFarm platform | E71: TBD | F71: TBD | G71: Offshore | H71: Prudence Consulting
A72: P2.2 | B72: 12. Phase 2 - System Enhancement & Integration | C72: Reporting | D72: New report / MIS development on NAVFarm or D365BC | E72: TBD | F72: TBD | G72: Offshore | H72: Prudence Consulting
A73: P2.3 | B73: 12. Phase 2 - System Enhancement & Integration | C73: IoT Integration | D73: NAVFarm integration with water meters | E73: TBD | F73: TBD | G73: Offshore | H73: Prudence Consulting
A74: P2.4 | B74: 12. Phase 2 - System Enhancement & Integration | C74: IoT Integration | D74: NAVFarm integration with silo weight scales | E74: TBD | F74: TBD | G74: Offshore | H74: Prudence Consulting
A75: P2.5 | B75: 12. Phase 2 - System Enhancement & Integration | C75: IoT Integration | D75: Any other device/equipment integrations, as required | E75: TBD | F75: TBD | G75: Offshore | H75: Prudence Consulting

Sheet holidays
A1: Holidays / Non-Working Days - Customer (Triple-C)
A3: Date | B3: Holiday / Closure Name
A4: 46244 | B4: Heroes Holiday - Zimbabwe
A5: 46245 | B5: Zimbabwe Defence Forces day
A6: 46378 | B6: Zimbabwe Unity Day
A7: 46381 | B7: Christmas Day
A8: 46382 | B8: Boxing Day

Sheet Prudence Holidays
A1: Holidays / Non-Working Days- Prudence Consulting
A2: Date | B2: Holiday / Closure Name
A3: 46262 | B3: Raksha Bandhan
A4: 46297 | B4: Mahatma Gandhi Jayanti
A5: 46315 | B5: Dussehra
A6: 46335 | B6: Govardhan Puja
A7: 46337 | B7: Bhai Dooj
A8: 46350 | B8: Gurpurab
A9: 46381 | B9: Christmas

Sheet About wbs
B2: Triple-C - NAVFARM Implementation
B3: Project Plan: Working-Day Timeline, Milestones & Detailed WBS
B5: Two working calendars are used, based on each activity's Mode
B6: - Mode = Mix-Mode or Onshore -> follows the CUSTOMER (Triple-C) calendar: Monday to Saturday, Sunday off, plus any date on the 'holidays' sheet.
B7: - Mode = Offshore -> follows the PRUDENCE calendar: Monday to Friday only (Saturday and Sunday off), plus any date on the 'Prudence Holidays' sheet.
B8: - Every date on the Timeline, Milestones and Detailed WBS sheets is calculated automatically using whichever calendar applies to that activity's Mode.
B9: - Add or change a holiday on either holiday sheet and the whole plan recalculates and shifts automatically.
B11: Fixed (anchor) dates
B12: - Project Kick-off is fixed to 04-Aug-2026 (Timeline sheet, cell E7).
B13: - Business Process Study is fixed to start 15-Aug-2026 (Timeline sheet, cell E8) - there is a deliberate gap after kick-off for mobilisation.
B14: - Every other activity is chained automatically: it starts on the next working day (per its own Mode's calendar) after the previous activity ends.
B15: - To fix any other activity to a specific start date, type that date into its 'Fixed Start' cell (column E) on the Timeline sheet. Leave it blank to let the plan auto-chain.
... B26: Durations, phases and deliverables are taken from the Prudence Consulting Business Proposal (Enterprise Pig Farming Transformation Proposal, v0.4). Working-day durations use the same day-counts as the proposal's implementation plan.

Sheet Calendar_Dont Use this
A1: Working-Day Calendar (helper sheet - drives all date calculations)
A2: We shouldn't need to edit this sheet.
A4: Date | B4: Day | C4: Is Saturday? | D4: Is Sunday? | E4: Is Customer Holiday? | F4: Is Prudence Holiday? | G4: Working Day - Customer (Mon-Sat) | H4: Working Day - Prudence (Mon-Fri) | I4: Cumulative Working Days - Customer | J4: Cumulative Working Days - Prudence
A5: 46218 | B5: =TEXT(A5,"ddd") -> Wed | C5: =IF(WEEKDAY(A5,2)=6,1,0) -> 0 | D5: =IF(WEEKDAY(A5,2)=7,1,0) -> 0 | E5: =IF(COUNTIF(holidays!$A:$A,A5)>0,1,0) -> 0 | F5: =IF(COUNTIF('Prudence Holidays'!$A:$A,A5)>0,1,0) -> 0 | G5: =IF(OR(D5=1,E5=1),0,1) -> 1 | H5: =IF(OR(C5=1,D5=1,F5=1),0,1) -> 1 | I5: =G5 -> 1 | J5: =H5 -> 1
A6: =A5+1 -> 46219 | B6: =TEXT(A6,"ddd") -> Thu | C6: =IF(WEEKDAY(A6,2)=6,1,0) -> 0 | D6: =IF(WEEKDAY(A6,2)=7,1,0) -> 0 | E6: =IF(COUNTIF(holidays!$A:$A,A6)>0,1,0) -> 0 | F6: =IF(COUNTIF('Prudence Holidays'!$A:$A,A6)>0,1,0) -> 0 | G6: =IF(OR(D6=1,E6=1),0,1) -> 1 | H6: =IF(OR(C6=1,D6=1,F6=1),0,1) -> 1 | I6: =I5+G6 -> 2 | J6: =J5+H6 -> 2
A7: =A6+1 -> 46220 | B7: =TEXT(A7,"ddd") -> Fri | C7: =IF(WEEKDAY(A7,2)=6,1,0) -> 0 | D7: =IF(WEEKDAY(A7,2)=7,1,0) -> 0 | E7: =IF(COUNTIF(holidays!$A:$A,A7)>0,1,0) -> 0 | F7: =IF(COUNTIF('Prudence Holidays'!$A:$A,A7)>0,1,0) -> 0 | G7: =IF(OR(D7=1,E7=1),0,1) -> 1 | H7: =IF(OR(C7=1,D7=1,F7=1),0,1) -> 1 | I7: =I6+G7 -> 3 | J7: =J6+H7 -> 3
A8: =A7+1 -> 46221 | B8: =TEXT(A8,"ddd") -> Sat | C8: =IF(WEEKDAY(A8,2)=6,1,0) -> 1 | D8: =IF(WEEKDAY(A8,2)=7,1,0) -> 0 | E8: =IF(COUNTIF(holidays!$A:$A,A8)>0,1,0) -> 0 | F8: =IF(COUNTIF('Prudence Holidays'!$A:$A,A8)>0,1,0) -> 0 | G8: =IF(OR(D8=1,E8=1),0,1) -> 1 | H8: =IF(OR(C8=1,D8=1,F8=1),0,1) -> 0 | I8: =I7+G8 -> 4 | J8: =J7+H8 -> 3
A9: =A8+1 -> 46222 | B9: =TEXT(A9,"ddd") -> Sun | C9: =IF(WEEKDAY(A9,2)=6,1,0) -> 0 | D9: =IF(WEEKDAY(A9,2)=7,1,0) -> 1 | E9: =IF(COUNTIF(holidays!$A:$A,A9)>0,1,0) -> 0 | F9: =IF(COUNTIF('Prudence Holidays'!$A:$A,A9)>0,1,0) -> 0 | G9: =IF(OR(D9=1,E9=1),0,1) -> 0 | H9: =IF(OR(C9=1,D9=1,F9=1),0,1) -> 0 | I9: =I8+G9 -> 4 | J9: =J8+H9 -> 3
A10: =A9+1 -> 46223 | B10: =TEXT(A10,"ddd") -> Mon | C10: =IF(WEEKDAY(A10,2)=6,1,0) -> 0 | D10: =IF(WEEKDAY(A10,2)=7,1,0) -> 0 | E10: =IF(COUNTIF(holidays!$A:$A,A10)>0,1,0) -> 0 | F10: =IF(COUNTIF('Prudence Holidays'!$A:$A,A10)>0,1,0) -> 0 | G10: =IF(OR(D10=1,E10=1),0,1) -> 1 | H10: =IF(OR(C10=1,D10=1,F10=1),0,1) -> 1 | I10: =I9+G10 -> 5 | J10: =J9+H10 -> 4
A11: =A10+1 -> 46224 | B11: =TEXT(A11,"ddd") -> Tue | C11: =IF(WEEKDAY(A11,2)=6,1,0) -> 0 | D11: =IF(WEEKDAY(A11,2)=7,1,0) -> 0 | E11: =IF(COUNTIF(holidays!$A:$A,A11)>0,1,0) -> 0 | F11: =IF(COUNTIF('Prudence Holidays'!$A:$A,A11)>0,1,0) -> 0 | G11: =IF(OR(D11=1,E11=1),0,1) -> 1 | H11: =IF(OR(C11=1,D11=1,F11=1),0,1) -> 1 | I11: =I10+G11 -> 6 | J11: =J10+H11 -> 5
A12: =A11+1 -> 46225 | B12: =TEXT(A12,"ddd") -> Wed | C12: =IF(WEEKDAY(A12,2)=6,1,0) -> 0 | D12: =IF(WEEKDAY(A12,2)=7,1,0) -> 0 | E12: =IF(COUNTIF(holidays!$A:$A,A12)>0,1,0) -> 0 | F12: =IF(COUNTIF('Prudence Holidays'!$A:$A,A12)>0,1,0) -> 0 | G12: =IF(OR(D12=1,E12=1),0,1) -> 1 | H12: =IF(OR(C12=1,D12=1,F12=1),0,1) -> 1 | I12: =I11+G12 -> 7 | J12: =J11+H12 -> 6
A13: =A12+1 -> 46226 | B13: =TEXT(A13,"ddd") -> Thu | C13: =IF(WEEKDAY(A13,2)=6,1,0) -> 0 | D13: =IF(WEEKDAY(A13,2)=7,1,0) -> 0 | E13: =IF(COUNTIF(holidays!$A:$A,A13)>0,1,0) -> 0 | F13: =IF(COUNTIF('Prudence Holidays'!$A:$A,A13)>0,1,0) -> 0 | G13: =IF(OR(D13=1,E13=1),0,1) -> 1 | H13: =IF(OR(C13=1,D13=1,F13=1),0,1) -> 1 | I13: =I12+G13 -> 8 | J13: =J12+H13 -> 7
A14: =A13+1 -> 46227 | B14: =TEXT(A14,"ddd") -> Fri | C14: =IF(WEEKDAY(A14,2)=6,1,0) -> 0 | D14: =IF(WEEKDAY(A14,2)=7,1,0) -> 0 | E14: =IF(COUNTIF(holidays!$A:$A,A14)>0,1,0) -> 0 | F14: =IF(COUNTIF('Prudence Holidays'!$A:$A,A14)>0,1,0) -> 0 | G14: =IF(OR(D14=1,E14=1),0,1) -> 1 | H14: =IF(OR(C14=1,D14=1,F14=1),0,1) -> 1 | I14: =I13+G14 -> 9 | J14: =J13+H14 -> 8
A15: =A14+1 -> 46228 | B15: =TEXT(A15,"ddd") -> Sat | C15: =IF(WEEKDAY(A15,2)=6,1,0) -> 1 | D15: =IF(WEEKDAY(A15,2)=7,1,0) -> 0 | E15: =IF(COUNTIF(holidays!$A:$A,A15)>0,1,0) -> 0 | F15: =IF(COUNTIF('Prudence Holidays'!$A:$A,A15)>0,1,0) -> 0 | G15: =IF(OR(D15=1,E15=1),0,1) -> 1 | H15: =IF(OR(C15=1,D15=1,F15=1),0,1) -> 0 | I15: =I14+G15 -> 10 | J15: =J14+H15 -> 8
A16: =A15+1 -> 46229 | B16: =TEXT(A16,"ddd") -> Sun | C16: =IF(WEEKDAY(A16,2)=6,1,0) -> 0 | D16: =IF(WEEKDAY(A16,2)=7,1,0) -> 1 | E16: =IF(COUNTIF(holidays!$A:$A,A16)>0,1,0) -> 0 | F16: =IF(COUNTIF('Prudence Holidays'!$A:$A,A16)>0,1,0) -> 0 | G16: =IF(OR(D16=1,E16=1),0,1) -> 0 | H16: =IF(OR(C16=1,D16=1,F16=1),0,1) -> 0 | I16: =I15+G16 -> 10 | J16: =J15+H16 -> 8
A17: =A16+1 -> 46230 | B17: =TEXT(A17,"ddd") -> Mon | C17: =IF(WEEKDAY(A17,2)=6,1,0) -> 0 | D17: =IF(WEEKDAY(A17,2)=7,1,0) -> 0 | E17: =IF(COUNTIF(holidays!$A:$A,A17)>0,1,0) -> 0 | F17: =IF(COUNTIF('Prudence Holidays'!$A:$A,A17)>0,1,0) -> 0 | G17: =IF(OR(D17=1,E17=1),0,1) -> 1 | H17: =IF(OR(C17=1,D17=1,F17=1),0,1) -> 1 | I17: =I16+G17 -> 11 | J17: =J16+H17 -> 9
... A424: =A423+1 -> 46637 | B424: =TEXT(A424,"ddd") -> Tue | C424: =IF(WEEKDAY(A424,2)=6,1,0) -> 0 | D424: =IF(WEEKDAY(A424,2)=7,1,0) -> 0 | E424: =IF(COUNTIF(holidays!$A:$A,A424)>0,1,0) -> 0 | F424: =IF(COUNTIF('Prudence Holidays'!$A:$A,A424)>0,1,0) -> 0 | G424: =IF(OR(D424=1,E424=1),0,1) -> 1 | H424: =IF(OR(C424=1,D424=1,F424=1),0,1) -> 1 | I424: =I423+G424 -> 355 | J424: =J423+H424 -> 293
