Workbook

Sheet April journals
A2: Triple C Pigs Books
A5: CR | B5: 1700/065 | C5: Feed ingredients other | G5: ='Pigs Cost'!G174+'Pigs Cost'!H174+'Pigs Cost'!I174 -> 15900000000000
A6: DR | B6: 6136/000 | C6: Zimbo intra-company | F6: ='Pigs Cost'!H174 -> 5700000000000
A7: DR | B7: 6137/000 | C7: Trade winds-intra company | F7: ='Pigs Cost'!G174 -> 9900000000000
A8: DR | B8: 6141/000 | C8: Quarantine - Outgrowers | F8: ='Pigs Cost'!I174 -> 300000000000
F10: =SUM(F6:F9) -> 15900000000000 | G10: =SUM(G5:G9) -> 15900000000000
A14: CR | B14: 1500/010 | C14: AI Consumables | G14: 5500
A15: CR | B15: 1500/025 | C15: Consumables | G15: 1053881
A16: CR | B16: 1400/030 | C16: Consultancy Fees | G16: 966060
A17: CR | B17: 1500/095 | C17: Training - External Consultants | G17: 4552000
A18: CR | B18: 1600/010 | C18: Cimas | G18: 884201
A19: CR | B19: 1600/030 | C19: Nssa | G19: 159193.72
A20: CR | B20: 1600/040 | C20: Protective Clothing | G20: 33033193
A21: CR | B21: 1600/050 | C21: Salaries | G21: 47297172
A22: CR | B22: 1600/070 | C22: Wages | G22: 9591454
A23: CR | B23: 1600/080 | C23: Welfare & Training | G23: 2215498
A24: CR | B24: 1750/010 | C24: Cimas | G24: 614798
A25: CR | B25: 1750/030 | C25: Nssa | G25: 65700
... A34: CR | B34: 1400/120 | C34: Veterinary | G34: 18000
A35: DR | B35: 6136/000 | C35: Zimbo intra-company | F35: ='Pigs Cost'!H176 -> 0
A36: DR | B36: 6137/000 | C36: Trade winds-intra company | F36: ='Pigs Cost'!#REF! -> #REF!
A37: DR | B37: 6141/000 | C37: Quarantine - Outgrowers | F37: ='Pigs Cost'!I176 -> 0
A38: DR | B38: 0300/030 | C38: Followers | F38: 5500
A39: DR | B39: 0300/015 | C39: Gilts | F39: ='Pigs Cost'!G16 -> 0
A40: DR | B40: 0300/030 | C40: Followers | F40: ='Pigs Cost'!G13+'Pigs Cost'!G14+'Pigs Cost'!G15 -> #REF!
A41: DR | B41: 0300/015 | C41: Gilts | F41: ='Pigs Cost'!H16 -> 0
A42: DR | B42: 0300/030 | C42: Followers | F42: ='Pigs Cost'!H13+'Pigs Cost'!H14+'Pigs Cost'!H15 -> #REF!
A43: DR | B43: 0300/015 | C43: Gilts | F43: ='Pigs Cost'!I16 -> 0
A44: DR | B44: 0300/030 | C44: Followers | F44: ='Pigs Cost'!I13+'Pigs Cost'!I14+'Pigs Cost'!I15 -> 0
A45: DR | B45: 0300/015 | C45: Gilts | F45: ='Pigs Cost'!L16 -> 0
A46: DR | B46: 0300/030 | C46: Followers | F46: ='Pigs Cost'!L15+'Pigs Cost'!L14+'Pigs Cost'!L13 -> #REF!
L47: =J34-L34 -> 0
F48: =SUM(F14:F47) -> #REF! | G48: =SUM(G14:G47) -> 6.9578096e+08
A50: DR | B50: 1500/015 | C50: Cost of sales | F50: 2.836853e+09
A51: CR | B51: 0300/030 | C51: Followers | G51: =F50 -> 2.836853e+09
F53: =SUM(F50:F52) -> 2.836853e+09 | G53: =SUM(G50:G52) -> 2.836853e+09
A56: Zimbo Books
A58: DR | B58: 0300/020 | C58: Sows | F58: 4707650
A59: CR | C59: Triple C Pigs | G59: 4707650
F60: =SUM(F58:F59) -> 4707650 | G60: =SUM(G58:G59) -> 4707650
A62: CR | C62: Triple C Pigs | F62: =F35 -> 0
A63: DR | B63: 0300/020 | C63: Sows | G63: =F62 -> 0
F64: =SUM(F62:F63) -> 0 | G64: =SUM(G62:G63) -> 0
A68: Trade winds Books
A70: DR | B70: 0300/030 | C70: Followers | F70: ='Pigs Cost'!J25+'Pigs Cost'!J27 -> #REF!
A71: CR | C71: Triple C Pigs | G71: =F70 -> #REF!
F72: =SUM(F70:F71) -> #REF! | G72: =SUM(G70:G71) -> #REF!
A74: CR | C74: Triple C Pigs | F74: =F36 -> #REF!
A75: DR | B75: 0300/030 | C75: Followers | G75: =F74 -> #REF!
F76: =SUM(F74:F75) -> #REF! | G76: =SUM(G74:G75) -> #REF!
A80: Quarantine Books
A82: Dr | B82: 0300/020 | C82: Sows | F82: ='Pigs Cost'!J67 -> 0
A83: CR | C83: Triple C Pigs | G83: 20109
F84: =SUM(F82:F83) -> 0 | G84: =SUM(G82:G83) -> 20109
A86: CR | C86: Triple C Pigs | F86: =F37 -> 0
A87: DR | B87: 0300/020 | C87: Sows | G87: =F86 -> 0
F88: =SUM(F86:F87) -> 0 | G88: =SUM(G86:G87) -> 0

Sheet Outgrower feed
D3: Dry Sow | E3: Gilt | F3: Creep | G3: Lactate | H3: Wean1 | I3: Wean2 | J3: Grower 2 | K3: Grower 1 | L3: Grower 4 | M3: Grower 3 | N3: Wheat bran | O3: Total
A5: Tradewinds | C5: Tonnage | D5: 1 | F5: 3 | G5: 1 | H5: 1 | I5: 1 | J5: 2 | K5: 1 | L5: 3 | M5: 11 | O5: =SUM(D5:N5) -> 24
C6: Unit cost
C8: Total | D8: =D6*D5 -> 0 | F8: =F6*F5 -> 0 | G8: =G6*G5 -> 0 | I8: =I6*I5 -> 0 | J8: =J6*J5 -> 0 | K8: =K6*K5 -> 0 | M8: =M6*M5 -> 0 | O8: =SUM(D8:M8) -> 0
A10: Zimbo | C10: Tonnage | D10: 15 | E10: 2 | F10: 1 | G10: 3 | H10: 1 | N10: 0.5 | O10: =SUM(D10:N10) -> 22.5
C11: Unit cost
C13: Total | D13: =D11*D10 -> 0 | F13: =F11*F10 -> 0 | G13: =G11*G10 -> 0 | I13: =I11*I10 -> 0 | J13: =J11*J10 -> 0 | K13: =K11*K10 -> 0 | M13: =M11*M10 -> 0 | O13: =SUM(D13:M13) -> 0
A15: Quarantine | C15: Tonnage | D15: 1 | E15: 5 | O15: =SUM(D15:N15) -> 6
C16: Unit cost
C18: Total | D18: =D16*D15 -> 0 | F18: =F16*F15 -> 0 | G18: =G16*G15 -> 0 | I18: =I16*I15 -> 0 | J18: =J16*J15 -> 0 | K18: =K16*K15 -> 0 | M18: =M16*M15 -> 0 | O18: =SUM(D18:M18) -> 0
A20: Rotgate | C20: Tonnage | E20: 11 | G20: 1 | J20: 4 | K20: 1 | O20: =SUM(D20:N20) -> 17
C21: Unit cost
C23: Total | D23: =D21*D20 -> 0 | F23: =F21*F20 -> 0 | G23: =G21*G20 -> 0 | I23: =I21*I20 -> 0 | J23: =J21*J20 -> 0 | K23: =K21*K20 -> 0 | M23: =M21*M20 -> 0 | O23: =SUM(D23:M23) -> 0

Sheet March pigs Journals
A3: Triple C Pigs Books
A7: CR | B7: 0300/010 | C7: Boars | E7: 3838761.6
A8: CR | B8: 0300/015 | C8: Gilts | E8: 0
A9: CR | B9: 0300/020 | C9: Sows | E9: 1.8578716e+08
A10: CR | B10: 0300/030 | C10: Followers | E10: =123971125.515872+1.23 -> 1.2397113e+08
A11: DR | B11: 6137/000 | C11: Trade winds-intra company | F11: 152819698
A12: DR | B12: 6141/000 | C12: Quarantine - Outgrowers | F12: 160777350
E14: =SUM(E7:E13) -> 3.1359705e+08 | F14: =SUM(F11:F13) -> 313597048
A17: Trade Winds Books
A20: DR | B20: 0300/010 | C20: Boars | E20: =1%*'Pigs Cost'!C29 -> 0
A21: DR | B21: 0300/015 | C21: Gilts
A22: DR | B22: 0300/020 | C22: Sows | E22: =99%*'Pigs Cost'!C29 -> 0
A23: DR | B23: 0300/030 | C23: Followers | E23: ='Pigs Cost'!C25 -> 0
A24: CR | C24: Triple C Pigs | F24: 152819698
E26: =SUM(E20:E24) -> 0 | F26: =SUM(F24:F25) -> 152819698
A28: Quarantine Books
A30: DR | B30: 0300/010 | C30: Boars
A31: DR | B31: 0300/015 | C31: Gilts
A32: DR | B32: 0300/020 | C32: Sows | E32: 160777350
A33: DR | B33: 0300/030 | C33: Followers
A34: CR | C34: Triple C Pigs | F34: 160777350
E36: =SUM(E32:E35) -> 160777350 | F36: =SUM(F34:F35) -> 160777350

Sheet Pigs Cost after IAS 41
A1: COLCOM HOLDINGS LIMITED
A3: TRIPLE C PIGS
A5: LIVESTOCK ANALYSIS SCHEDULE INCLUDING IAS 41
A8: COST | B8: GRASMERE FARM
A10: SITE:
A12: DESCRIPTION | B12: SITE | C12: OPENING | D12: PIG PURCHASES | E12: TRANSFER IN | F12: A I CONSUMMABLES | G12: BEDDING AND CONSUMMABLES | H12: CONSULTANCY FEES | I12: DIRECT STAFF COSTS | J12: STOCK FEED | K12: SUNDRY TOOLS | L12: VETERINARY | M12: TOTAL COST | N12: AVERAGE COST | O12: TRANSFER OUT | P12: SALES | Q12: IAS 41 ADJ. | R12: CLOSING
A13: PIGLETS | B13: MAIN | C13: ='Pigs Cost'!C13 -> 7.6193293e+10 | D13: ='Pigs Cost'!D13 -> 0 | E13: ='Pigs Cost'!E13 -> 0 | F13: ='Pigs Cost'!F13 -> 0 | G13: ='Pigs Cost'!G13 -> #REF! | H13: ='Pigs Cost'!H13 -> #REF! | I13: ='Pigs Cost'!I13 -> 0 | J13: ='Pigs Cost'!J13 -> #REF! | ... L13: ='Pigs Cost'!L13 -> #REF! | M13: =SUM(C13:L13) -> #REF! | N13: ='Pigs Cost'!N13 -> #REF! | O13: ='Pigs Cost'!O13 -> #REF! | P13: ='Pigs Cost'!P13 -> #REF! | Q13: ='[5]PigsMay 07 '!$H34 -> 9.3648212e+10 | R13: =M13+O13+P13+Q13 -> #REF!
A14: WEANERS | B14: WEANER | C14: ='Pigs Cost'!C14 -> 1.0410751e+11 | D14: ='Pigs Cost'!D14 -> 0 | E14: ='Pigs Cost'!E14 -> #REF! | F14: ='Pigs Cost'!F14 -> 0 | G14: ='Pigs Cost'!G14 -> #REF! | H14: ='Pigs Cost'!H14 -> #REF! | I14: ='Pigs Cost'!I14 -> 0 | J14: ='Pigs Cost'!J14 -> #REF! | ... L14: ='Pigs Cost'!L14 -> #REF! | M14: =SUM(C14:L14) -> #REF! | N14: ='Pigs Cost'!N14 -> #REF! | O14: ='Pigs Cost'!O14 -> #REF! | P14: ='Pigs Cost'!P14 -> #REF! | Q14: ='[5]PigsMay 07 '!$H35 -> 9.2282436e+11 | R14: =M14+O14+P14+Q14 -> #REF!
A15: GROWERS | B15: GROWER | C15: ='Pigs Cost'!C15 -> 2.2702568e+11 | D15: ='Pigs Cost'!D15 -> 0 | E15: ='Pigs Cost'!E15 -> #REF! | F15: ='Pigs Cost'!F15 -> 0 | G15: ='Pigs Cost'!G15 -> #REF! | H15: ='Pigs Cost'!H15 -> #REF! | I15: ='Pigs Cost'!I15 -> 0 | J15: ='Pigs Cost'!J15 -> #REF! | ... L15: ='Pigs Cost'!L15 -> #REF! | M15: =SUM(C15:L15) -> #REF! | N15: ='Pigs Cost'!N15 -> #REF! | O15: ='Pigs Cost'!O15 -> #REF! | P15: ='Pigs Cost'!P15 -> #REF! | Q15: ='[5]PigsMay 07 '!$H36 -> 3.4016397e+12 | R15: =M15+O15+P15+Q15 -> #REF!
A16: GILTS | B16: MAIN | C16: ='Pigs Cost'!C16 -> 3.0124651e+09 | D16: ='Pigs Cost'!D16 -> 0 | E16: ='Pigs Cost'!E16 -> #REF! | F16: ='Pigs Cost'!F16 -> 0 | G16: ='Pigs Cost'!G16 -> 0 | H16: ='Pigs Cost'!H16 -> 0 | I16: ='Pigs Cost'!I16 -> 0 | J16: ='Pigs Cost'!J16 -> 0 | ... L16: ='Pigs Cost'!L16 -> 0 | M16: =SUM(C16:L16) -> #REF! | N16: ='Pigs Cost'!N16 -> #REF! | O16: ='Pigs Cost'!O16 -> #REF! | P16: ='Pigs Cost'!P16 -> #REF! | Q16: ='[5]PigsMay 07 '!$H37 -> 1.1569961e+11 | R16: =M16+O16+P16+Q16 -> #REF!
A17: SOWS | B17: MAIN | C17: ='Pigs Cost'!C17 -> 7.0513089e+08 | D17: ='Pigs Cost'!D17 -> 0 | E17: ='Pigs Cost'!E17 -> #REF! | F17: ='Pigs Cost'!F17 -> 0 | G17: ='Pigs Cost'!G17 -> 0 | H17: ='Pigs Cost'!H17 -> 0 | I17: ='Pigs Cost'!I17 -> 0 | J17: ='Pigs Cost'!J17 -> 0 | ... L17: ='Pigs Cost'!L17 -> 0 | M17: =SUM(C17:L17) -> #REF! | N17: ='Pigs Cost'!N17 -> #REF! | O17: ='Pigs Cost'!O17 -> #REF! | P17: ='Pigs Cost'!P17 -> #REF! | Q17: ='[5]PigsMay 07 '!$H38 -> 5.0044882e+11 | R17: =M17+O17+P17+Q17 -> #REF!
A18: BOARS | B18: AI | C18: ='Pigs Cost'!C18 -> 109058.54 | D18: ='Pigs Cost'!D18 -> 0 | E18: ='Pigs Cost'!E18 -> #REF! | F18: ='Pigs Cost'!F18 -> 0 | G18: ='Pigs Cost'!G18 -> 0 | H18: ='Pigs Cost'!H18 -> 0 | I18: ='Pigs Cost'!I18 -> 0 | J18: ='Pigs Cost'!J18 -> 0 | ... L18: ='Pigs Cost'!L18 -> 0 | M18: =SUM(C18:L18) -> #REF! | N18: ='Pigs Cost'!N18 -> #REF! | O18: ='Pigs Cost'!O18 -> #REF! | P18: ='Pigs Cost'!P18 -> #REF! | Q18: ='[5]PigsMay 07 '!$H39 -> 1.6625728e+10 | R18: =M18+O18+P18+Q18 -> #REF!
A19: TOTAL | C19: =SUM(C13:C18) -> 4.1104419e+11 | D19: =SUM(D13:D18) -> 0 | E19: =SUM(E13:E18) -> #REF! | F19: =SUM(F13:F18) -> 0 | G19: =SUM(G13:G18) -> #REF! | H19: =SUM(H13:H18) -> #REF! | I19: =SUM(I13:I18) -> 0 | J19: =SUM(J13:J18) -> #REF! | ... R19: =SUM(R13:R18) -> #REF! | S19: =R19-'[5]PigsMay 07 '!$G$40 -> #REF! | T19: =Q19-'[5]PigsMay 07 '!$H$40 -> 0
N20: =N19-'Pigs Cost'!N19 -> #REF! | Q20: =Q19-'[5]PigsMay 07 '!$H$40 -> 0
L21: =+(G19+H19+I19+K19+L19+J19+F19)-J107 -> #REF!
A22: SITE: | B22: TRADE WINDS
A24: DESCRIPTION | B24: SITE | C24: OPENING | D24: PIG PURCHASES | E24: TRANSFER IN | F24: A I CONSUMMABLES | G24: BEDDING AND CONSUMMABLES | H24: CONSULTANCY FEES | I24: DIRECT STAFF COSTS | J24: STOCK FEED | K24: SUNDRY TOOLS | L24: VETERINARY | M24: TOTAL COST | N24: AVERAGE COST | O24: TRANSFER OUT | P24: SALES | Q24: IAS 41 ADJ. | R24: CLOSING
A25: PIGLETS | B25: MAIN | C25: ='Pigs Cost'!C25 -> 0 | D25: ='Pigs Cost'!D25 -> 0 | E25: ='Pigs Cost'!E25 -> #REF! | F25: ='Pigs Cost'!F25 -> 0 | G25: ='Pigs Cost'!G25 -> #REF! | H25: ='Pigs Cost'!H25 -> #REF! | I25: ='Pigs Cost'!I25 -> #REF! | J25: ='Pigs Cost'!J25 -> #REF! | ... L25: ='Pigs Cost'!L25 -> #REF! | M25: =SUM(C25:L25) -> #REF! | N25: ='Pigs Cost'!N25 -> 0 | O25: ='Pigs Cost'!O25 -> #REF! | P25: ='Pigs Cost'!P25 -> #REF! | Q25: ='[5]Outgrower pigs Sept07 TRADE WIN'!$H34 -> 0 | R25: =M25+O25+P25+Q25 -> #REF!
A26: WEANERS | B26: WEANER | C26: ='Pigs Cost'!C26 -> 0 | D26: ='Pigs Cost'!D26 -> 0 | E26: ='Pigs Cost'!E26 -> 0 | F26: ='Pigs Cost'!F26 -> 0 | G26: ='Pigs Cost'!G26 -> #REF! | H26: ='Pigs Cost'!H26 -> #REF! | I26: ='Pigs Cost'!I26 -> #REF! | J26: ='Pigs Cost'!J26 -> #REF! | ... L26: ='Pigs Cost'!L26 -> 0 | M26: =SUM(C26:L26) -> #REF! | N26: ='Pigs Cost'!N26 -> 0 | O26: ='Pigs Cost'!O26 -> #REF! | P26: ='Pigs Cost'!P26 -> #REF! | Q26: ='[5]Outgrower pigs Sept07 TRADE WIN'!$H35 -> 8.8755496e+10 | R26: =M26+O26+P26+Q26 -> #REF!
A27: GROWERS | B27: GROWER | C27: ='Pigs Cost'!C27 -> 1.4341696e+10 | D27: ='Pigs Cost'!D27 -> 0 | E27: ='Pigs Cost'!E27 -> #REF! | F27: ='Pigs Cost'!F27 -> 0 | G27: ='Pigs Cost'!G27 -> #REF! | H27: ='Pigs Cost'!H27 -> #REF! | I27: ='Pigs Cost'!I27 -> #REF! | J27: ='Pigs Cost'!J27 -> #REF! | ... L27: ='Pigs Cost'!L27 -> #REF! | M27: =SUM(C27:L27) -> #REF! | N27: ='Pigs Cost'!N27 -> #REF! | O27: ='Pigs Cost'!O27 -> #REF! | P27: ='Pigs Cost'!P27 -> #REF! | Q27: ='[5]Outgrower pigs Sept07 TRADE WIN'!$H36 -> 1.0256305e+11 | R27: =M27+O27+P27+Q27 -> #REF!
A28: GILTS | B28: MAIN | C28: ='Pigs Cost'!C28 -> 0 | D28: ='Pigs Cost'!D28 -> 0 | E28: ='Pigs Cost'!E28 -> #REF! | F28: ='Pigs Cost'!F28 -> 0 | G28: ='Pigs Cost'!G28 -> 0 | H28: ='Pigs Cost'!H28 -> 0 | I28: ='Pigs Cost'!I28 -> 0 | J28: ='Pigs Cost'!J28 -> 0 | ... L28: ='Pigs Cost'!L28 -> 0 | N28: ='Pigs Cost'!N28 -> 0 | O28: ='Pigs Cost'!O28 -> #REF! | P28: ='Pigs Cost'!P28 -> #REF! | Q28: ='[5]Outgrower pigs Sept07 TRADE WIN'!$H37 -> 0 | R28: =M28+O28+P28+Q28 -> #REF!
A29: SOWS | B29: MAIN | C29: ='Pigs Cost'!C29 -> 0 | D29: ='Pigs Cost'!D29 -> 0 | E29: ='Pigs Cost'!E29 -> 0 | F29: ='Pigs Cost'!F29 -> 0 | G29: ='Pigs Cost'!G29 -> 0 | H29: ='Pigs Cost'!H29 -> #REF! | I29: ='Pigs Cost'!I29 -> 0 | J29: ='Pigs Cost'!J29 -> 0 | ... L29: ='Pigs Cost'!L29 -> 0 | M29: =SUM(C29:L29) -> #REF! | N29: ='Pigs Cost'!N29 -> 0 | O29: ='Pigs Cost'!O29 -> #REF! | P29: ='Pigs Cost'!P29 -> #REF! | Q29: ='[5]Outgrower pigs Sept07 TRADE WIN'!$H38 -> 0 | R29: =M29+O29+P29+Q29 -> #REF!
A30: BOARS | C30: ='Pigs Cost'!C30 -> 0 | D30: ='Pigs Cost'!D30 -> 0 | E30: ='Pigs Cost'!E30 -> #REF! | F30: ='Pigs Cost'!F30 -> 0 | G30: ='Pigs Cost'!G30 -> 0 | H30: ='Pigs Cost'!H30 -> 0 | I30: ='Pigs Cost'!I30 -> 0 | J30: ='Pigs Cost'!J30 -> 0 | ... L30: ='Pigs Cost'!L30 -> 0 | M30: =SUM(C30:L30) -> #REF! | N30: ='Pigs Cost'!N30 -> 0 | O30: ='Pigs Cost'!O30 -> #REF! | P30: ='Pigs Cost'!P30 -> 0 | Q30: ='[5]Outgrower pigs Sept07 TRADE WIN'!$H39 -> 0 | R30: =SUM(C30:L30) -> #REF!
A31: TOTAL | C31: =SUM(C25:C30) -> 1.4341696e+10 | D31: =SUM(D25:D30) -> 0 | E31: =SUM(E25:E29) -> #REF! | F31: =SUM(F25:F30) -> 0 | G31: =SUM(G25:G30) -> #REF! | H31: =SUM(H25:H30) -> #REF! | I31: =SUM(I25:I30) -> #REF! | J31: =SUM(J25:J30) -> #REF! | K31: =SUM(K25:K30) -> #REF! | L31: =SUM(L25:L30) -> #REF! | M31: =SUM(M25:M30) -> #REF! | ... R31: =SUM(R25:R30) -> #REF! | S31: ='[5]Outgrower pigs Sept07 TRADE WIN'!$G$40-R31 -> #REF! | T31: =Q31-'[5]Outgrower pigs Sept07 TRADE WIN'!$H$40 -> 0
A34: SITE: | B34: ZIMBO
A36: DESCRIPTION | B36: SITE | C36: OPENING | D36: PIG PURCHASES | E36: TRANSFER IN | F36: A I CONSUMMABLES | G36: BEDDING AND CONSUMMABLES | H36: CONSULTANCY FEES | I36: DIRECT STAFF COSTS | J36: STOCK FEED | K36: SUNDRY TOOLS | L36: VETERINARY | M36: TOTAL COST | N36: AVERAGE COST | O36: TRANSFER OUT | P36: SALES | Q36: IAS 41 ADJ. | R36: CLOSING
A37: PIGLETS | B37: MAIN | C37: ='Pigs Cost'!C37 -> 3.1052778e+09 | D37: ='Pigs Cost'!D37 -> 0 | E37: ='Pigs Cost'!E37 -> 0 | F37: ='Pigs Cost'!F37 -> #REF! | G37: ='Pigs Cost'!G37 -> 0 | H37: ='Pigs Cost'!H37 -> 0 | I37: ='Pigs Cost'!I37 -> 0 | J37: ='Pigs Cost'!J37 -> 1.4288071e+12 | ... L37: ='Pigs Cost'!L37 -> 0 | M37: =SUM(C37:L37) -> #REF! | N37: ='Pigs Cost'!N37 -> #REF! | O37: ='Pigs Cost'!O37 -> #REF! | P37: ='Pigs Cost'!P37 -> #REF! | Q37: ='[5]Outgrower pigs Sept 07 ZIMBO'!$H34 -> 1.7778681e+10 | R37: =M37+O37+P37+Q37 -> #REF!
A38: WEANERS | B38: WEANER | C38: ='Pigs Cost'!C38 -> 0 | D38: ='Pigs Cost'!D38 -> 0 | E38: ='Pigs Cost'!E38 -> 0 | F38: ='Pigs Cost'!F38 -> #REF! | G38: ='Pigs Cost'!G38 -> 0 | H38: ='Pigs Cost'!H38 -> 0 | I38: ='Pigs Cost'!I38 -> 0 | J38: ='Pigs Cost'!J38 -> 1.471066e+12 | ... L38: ='Pigs Cost'!L38 -> 0 | M38: =SUM(C38:L38) -> #REF! | N38: ='Pigs Cost'!N38 -> 0 | O38: ='Pigs Cost'!O38 -> 0 | P38: ='Pigs Cost'!P38 -> #REF! | Q38: ='[5]Outgrower pigs Sept 07 ZIMBO'!$H35 -> 3.4863215e+10 | R38: =M38+O38+P38+Q38 -> #REF!
A39: GROWERS | B39: GROWER | C39: ='Pigs Cost'!C39 -> -5.9604645e-18 | D39: ='Pigs Cost'!D39 -> 0 | E39: ='Pigs Cost'!E39 -> 0 | F39: ='Pigs Cost'!F39 -> #REF! | G39: ='Pigs Cost'!G39 -> 0 | H39: ='Pigs Cost'!H39 -> 0 | I39: ='Pigs Cost'!I39 -> 0 | J39: ='Pigs Cost'!J39 -> 2.8001269e+12 | ... L39: ='Pigs Cost'!L39 -> 0 | M39: =SUM(C39:L39) -> #REF! | N39: ='Pigs Cost'!N39 -> 0 | O39: ='Pigs Cost'!O39 -> 0 | P39: ='Pigs Cost'!P39 -> #REF! | Q39: ='[5]Outgrower pigs Sept 07 ZIMBO'!$H36 -> 0 | R39: =M39+O39+P39+Q39 -> #REF!
A40: GILTS | B40: MAIN | C40: ='Pigs Cost'!C40 -> 0 | D40: ='Pigs Cost'!D40 -> 0 | E40: ='Pigs Cost'!E40 -> #REF! | F40: ='Pigs Cost'!F40 -> #REF! | G40: ='Pigs Cost'!G40 -> 0 | H40: ='Pigs Cost'!H40 -> 0 | I40: ='Pigs Cost'!I40 -> 0 | J40: ='Pigs Cost'!J40 -> 0 | ... L40: ='Pigs Cost'!L40 -> 0 | M40: =SUM(C40:L40) -> #REF! | N40: ='Pigs Cost'!N40 -> #REF! | O40: ='Pigs Cost'!O40 -> #REF! | P40: ='Pigs Cost'!P40 -> #REF! | Q40: ='[5]Outgrower pigs Sept 07 ZIMBO'!$H37 -> 1.0013995e+09 | R40: =M40+O40+P40+Q40 -> #REF!
A41: SOWS | B41: MAIN | C41: ='Pigs Cost'!C41 -> 146128.33 | D41: ='Pigs Cost'!D41 -> 0 | E41: ='Pigs Cost'!E41 -> #REF! | F41: ='Pigs Cost'!F41 -> #REF! | G41: ='Pigs Cost'!G41 -> 0 | H41: ='Pigs Cost'!H41 -> 0 | I41: ='Pigs Cost'!I41 -> 0 | J41: ='Pigs Cost'!J41 -> 0 | ... L41: ='Pigs Cost'!L41 -> 0 | M41: =SUM(C41:L41) -> #REF! | N41: ='Pigs Cost'!N41 -> #REF! | O41: ='Pigs Cost'!O41 -> #REF! | P41: ='Pigs Cost'!P41 -> #REF! | Q41: ='[5]Outgrower pigs Sept 07 ZIMBO'!$H38 -> 9.4184319e+10 | R41: =M41+O41+P41+Q41 -> #REF!
A42: BOARS | C42: ='Pigs Cost'!C42 -> 0.013277874 | D42: ='Pigs Cost'!D42 -> 0 | E42: ='Pigs Cost'!E42 -> 0 | F42: ='Pigs Cost'!F42 -> 0 | G42: ='Pigs Cost'!G42 -> 0 | H42: ='Pigs Cost'!H42 -> 0 | I42: ='Pigs Cost'!I42 -> 0 | J42: ='Pigs Cost'!J42 -> 0 | ... L42: ='Pigs Cost'!L42 -> 0 | M42: =SUM(C42:L42) -> 0.013277874 | N42: ='Pigs Cost'!N42 -> #REF! | O42: ='Pigs Cost'!O42 -> #REF! | P42: ='Pigs Cost'!P42 -> #REF! | Q42: ='[5]Outgrower pigs Sept 07 ZIMBO'!$H39 -> 1.1299301e+09 | R42: =M42+O42+P42+Q42 -> #REF!
A43: TOTAL | C43: =SUM(C37:C42) -> 3.1054239e+09 | D43: =SUM(D37:D42) -> 0 | E43: =SUM(E37:E41) -> #REF! | F43: =SUM(F37:F42) -> #REF! | G43: =SUM(G37:G42) -> 0 | H43: =SUM(H37:H42) -> 0 | I43: =SUM(I37:I42) -> 0 | J43: =SUM(J37:J42) -> 5700000000000 | K43: =SUM(K37:K42) -> 0 | L43: =SUM(L37:L42) -> 0 | M43: =SUM(M37:M42) -> #REF! | ... R43: =SUM(R37:R42) -> #REF! | S43: =R43-'[5]Outgrower pigs Sept 07 ZIMBO'!$G$40 -> #REF! | T43: =Q43-'[5]Outgrower pigs Sept 07 ZIMBO'!$H$40 -> 0
Q44: =Q43-'[5]Outgrower pigs Sept 07 ZIMBO'!$H$40 -> 0
L45: =+(G43+H43+I43+K43+L43+J43)-H107 -> 5699980512623
L48: =+(L43+K43+J43+I43+H43+G43+F43)-H107 -> #REF!
A49: SITE: | B49: ROGATE
A51: DESCRIPTION | B51: SITE | C51: OPENING | D51: PIG PURCHASES | E51: TRANSFER IN | F51: A I CONSUMMABLES | G51: BEDDING AND CONSUMMABLES | H51: CONSULTANCY FEES | I51: DIRECT STAFF COSTS | J51: STOCK FEED | K51: SUNDRY TOOLS | L51: VETERINARY | M51: TOTAL COST | N51: AVERAGE COST | O51: TRANSFER OUT | P51: SALES | Q51: IAS 41 ADJ. | R51: CLOSING
A52: PIGLETS | B52: MAIN | C52: ='Pigs Cost'!C52 -> 1.7388984e+10 | D52: ='Pigs Cost'!D52 -> 0 | E52: ='Pigs Cost'!E52 -> #REF! | F52: ='Pigs Cost'!F52 -> 0 | G52: ='Pigs Cost'!G52 -> 0 | H52: ='Pigs Cost'!H52 -> 0 | I52: ='Pigs Cost'!I52 -> 0 | J52: ='Pigs Cost'!J52 -> 3.7202398e+12 | ... L52: ='Pigs Cost'!L52 -> 0 | M52: =SUM(C52:L52) -> #REF! | N52: ='Pigs Cost'!N52 -> #REF! | O52: ='Pigs Cost'!O52 -> #REF! | P52: ='Pigs Cost'!P52 -> 0 | Q52: ='[5]Outgrower pigs Sept 07 ROGATE'!$H34 -> 2.460632e+10 | R52: =M52+O52+P52+Q52 -> #REF!
A53: WEANERS | B53: WEANER | C53: ='Pigs Cost'!C53 -> 3.8118878e+09 | D53: ='Pigs Cost'!D53 -> 0 | E53: ='Pigs Cost'!E53 -> #REF! | F53: ='Pigs Cost'!F53 -> 0 | G53: ='Pigs Cost'!G53 -> 0 | H53: ='Pigs Cost'!H53 -> 0 | I53: ='Pigs Cost'!I53 -> 0 | J53: ='Pigs Cost'!J53 -> 2.3306964e+12 | ... L53: ='Pigs Cost'!L53 -> 0 | M53: =SUM(C53:L53) -> #REF! | N53: ='Pigs Cost'!N53 -> #REF! | O53: ='Pigs Cost'!O53 -> #REF! | P53: ='Pigs Cost'!P53 -> 0 | Q53: ='[5]Outgrower pigs Sept 07 ROGATE'!$H35 -> 9.9324083e+10 | R53: =M53+O53+P53+Q53 -> #REF!
A54: GROWERS | B54: GROWER | C54: ='Pigs Cost'!C54 -> 1.2994808e+10 | D54: ='Pigs Cost'!D54 -> 0 | E54: ='Pigs Cost'!E54 -> #REF! | F54: ='Pigs Cost'!F54 -> 0 | G54: ='Pigs Cost'!G54 -> 0 | H54: ='Pigs Cost'!H54 -> 0 | I54: ='Pigs Cost'!I54 -> 0 | J54: ='Pigs Cost'!J54 -> 5.0490637e+12 | ... L54: ='Pigs Cost'!L54 -> 0 | M54: =SUM(C54:L54) -> #REF! | N54: ='Pigs Cost'!N54 -> #REF! | O54: ='Pigs Cost'!O54 -> #REF! | P54: ='Pigs Cost'!P54 -> #REF! | Q54: ='[5]Outgrower pigs Sept 07 ROGATE'!$H36 -> 2.1449039e+11 | R54: =M54+O54+P54+Q54 -> #REF!
A55: GILTS | B55: MAIN | C55: ='Pigs Cost'!C55 -> 1.1397226e+08 | D55: ='Pigs Cost'!D55 -> 0 | E55: ='Pigs Cost'!E55 -> #REF! | F55: ='Pigs Cost'!F55 -> 0 | G55: ='Pigs Cost'!G55 -> 0 | H55: ='Pigs Cost'!H55 -> 0 | I55: ='Pigs Cost'!I55 -> 0 | J55: ='Pigs Cost'!J55 -> 0 | ... L55: ='Pigs Cost'!L55 -> 0 | M55: =SUM(C55:L55) -> #REF! | N55: ='Pigs Cost'!N55 -> #REF! | O55: ='Pigs Cost'!O55 -> #REF! | P55: ='Pigs Cost'!P55 -> #REF! | Q55: ='[5]Outgrower pigs Sept 07 ROGATE'!$H37 -> 3.5610469e+10 | R55: =M55+O55+P55+Q55 -> #REF!
A56: SOWS | B56: MAIN | C56: ='Pigs Cost'!C56 -> 1.4429877e+09 | D56: ='Pigs Cost'!D56 -> 0 | E56: ='Pigs Cost'!E56 -> #REF! | F56: ='Pigs Cost'!F56 -> 0 | G56: ='Pigs Cost'!G56 -> 0 | H56: ='Pigs Cost'!H56 -> 0 | I56: ='Pigs Cost'!I56 -> 0 | J56: ='Pigs Cost'!J56 -> 0 | ... L56: ='Pigs Cost'!L56 -> 0 | M56: =SUM(C56:L56) -> #REF! | N56: ='Pigs Cost'!N56 -> #REF! | O56: ='Pigs Cost'!O56 -> #REF! | P56: ='Pigs Cost'!P56 -> #REF! | Q56: ='[5]Outgrower pigs Sept 07 ROGATE'!$H38 -> 1.1063953e+11 | R56: =M56+P56+O56+Q56 -> #REF!
A57: BOARS | C57: ='Pigs Cost'!C57 -> 0.074705426 | D57: ='Pigs Cost'!D57 -> 0 | E57: ='Pigs Cost'!E57 -> #REF! | F57: ='Pigs Cost'!F57 -> 0 | G57: ='Pigs Cost'!G57 -> 0 | H57: ='Pigs Cost'!H57 -> 0 | I57: ='Pigs Cost'!I57 -> 0 | J57: ='Pigs Cost'!J57 -> 0 | ... L57: ='Pigs Cost'!L57 -> 0 | M57: =SUM(C57:L57) -> #REF! | N57: ='Pigs Cost'!N57 -> #REF! | O57: ='Pigs Cost'!O57 -> #REF! | P57: ='Pigs Cost'!P57 -> #REF! | Q57: ='[5]Outgrower pigs Sept 07 ROGATE'!$H39 -> 1.1306073e+09 | R57: =M57+P57+O57+Q57 -> #REF!
A58: TOTAL | C58: =SUM(C52:C57) -> 3.575264e+10 | D58: =SUM(D52:D57) -> 0 | E58: =SUM(E52:E56) -> #REF! | F58: =SUM(F52:F57) -> 0 | G58: =SUM(G52:G57) -> 0 | H58: =SUM(H52:H57) -> 0 | I58: =SUM(I52:I57) -> 0 | J58: =SUM(J52:J57) -> 11100000000000 | K58: =SUM(K52:K57) -> 0 | L58: =SUM(L52:L57) -> 0 | M58: =SUM(M52:M57) -> #REF! | ... R58: =SUM(R52:R57) -> #REF! | S58: =R58-'[5]Outgrower pigs Sept 07 ROGATE'!$G$40 -> #REF! | T58: =Q58-'[5]Outgrower pigs Sept 07 ROGATE'!$H$40 -> 0
Q59: =Q58-'[6]Outgrower pigs Sept 07 ROGATE'!$H$40 -> 0
A60: SITE: | B60: QUARANTINE | L60: =+(G58+H58+I58+K58+L58+J58)-K107 -> 11099867973225
A62: DESCRIPTION | B62: SITE | C62: OPENING | D62: PIG PURCHASES | E62: TRANSFER IN | F62: A I CONSUMMABLES | G62: BEDDING AND CONSUMMABLES | H62: CONSULTANCY FEES | I62: DIRECT STAFF COSTS | J62: STOCK FEED | K62: SUNDRY TOOLS | L62: VETERINARY | M62: TOTAL COST | N62: AVERAGE COST | O62: TRANSFER OUT | P62: SALES | Q62: IAS 41 ADJ. | R62: CLOSING
A63: PIGLETS | B63: MAIN | C63: ='Pigs Cost'!C63 -> 0 | D63: ='Pigs Cost'!D63 -> 0 | E63: ='Pigs Cost'!E63 -> 0 | F63: ='Pigs Cost'!F63 -> 0 | G63: ='Pigs Cost'!G63 -> 0 | H63: ='Pigs Cost'!H63 -> 0 | I63: ='Pigs Cost'!I63 -> 0 | J63: ='Pigs Cost'!J63 -> 0 | ... L63: ='Pigs Cost'!L63 -> 0 | M63: =SUM(C63:L63) -> 0 | N63: ='Pigs Cost'!N63 -> 0 | O63: ='Pigs Cost'!O63 -> 0 | P63: ='Pigs Cost'!P63 -> 0 | Q63: ='[5]Outgrower pigs Sept 07 Quaranti'!$H35 -> 0 | R63: =M63+O63+P63+Q63 -> 0
A64: WEANERS | B64: WEANER | C64: ='Pigs Cost'!C64 -> 0 | D64: ='Pigs Cost'!D64 -> 0 | E64: ='Pigs Cost'!E64 -> 0 | F64: ='Pigs Cost'!F64 -> 0 | G64: ='Pigs Cost'!G64 -> 0 | H64: ='Pigs Cost'!H64 -> 0 | I64: ='Pigs Cost'!I64 -> 0 | J64: ='Pigs Cost'!J64 -> 0 | ... L64: ='Pigs Cost'!L64 -> 0 | M64: =SUM(C64:L64) -> 0 | N64: ='Pigs Cost'!N64 -> 0 | O64: ='Pigs Cost'!O64 -> 0 | P64: ='Pigs Cost'!P64 -> 0 | Q64: ='[5]Outgrower pigs Sept 07 Quaranti'!$H36 -> 0 | R64: =M64+O64+P64+Q64 -> 0
A65: GROWERS | B65: GROWER | C65: ='Pigs Cost'!C65 -> 0 | D65: ='Pigs Cost'!D65 -> 0 | E65: ='Pigs Cost'!E65 -> 0 | F65: ='Pigs Cost'!F65 -> 0 | G65: ='Pigs Cost'!G65 -> 0 | H65: ='Pigs Cost'!H65 -> 0 | I65: ='Pigs Cost'!I65 -> 0 | J65: ='Pigs Cost'!J65 -> 0 | ... L65: ='Pigs Cost'!L65 -> 0 | M65: =SUM(C65:L65) -> 0 | N65: ='Pigs Cost'!N65 -> 0 | O65: ='Pigs Cost'!O65 -> 0 | P65: ='Pigs Cost'!P65 -> 0 | Q65: ='[5]Outgrower pigs Sept 07 Quaranti'!$H37 -> 0 | R65: =M65+O65+P65+Q65 -> 0
A66: GILTS | B66: MAIN | C66: ='Pigs Cost'!C66 -> 1322329.6 | D66: ='Pigs Cost'!D66 -> 0 | E66: ='Pigs Cost'!E66 -> #REF! | F66: ='Pigs Cost'!F66 -> 0 | G66: ='Pigs Cost'!G66 -> 0 | H66: ='Pigs Cost'!H66 -> 0 | I66: ='Pigs Cost'!I66 -> 0 | J66: ='Pigs Cost'!J66 -> #REF! | ... L66: ='Pigs Cost'!L66 -> 0 | M66: =SUM(C66:L66) -> #REF! | N66: ='Pigs Cost'!N66 -> #REF! | O66: ='Pigs Cost'!O66 -> #REF! | P66: ='Pigs Cost'!P66 -> #REF! | Q66: ='[5]Outgrower pigs Sept 07 Quaranti'!$H38 -> 0 | R66: =M66+O66+P66+Q66 -> #REF!
A67: SOWS | B67: MAIN | C67: ='Pigs Cost'!C67 -> 0 | D67: ='Pigs Cost'!D67 -> 0 | E67: ='Pigs Cost'!E67 -> 0 | F67: ='Pigs Cost'!F67 -> 0 | G67: ='Pigs Cost'!G67 -> 0 | H67: ='Pigs Cost'!H67 -> 0 | I67: ='Pigs Cost'!I67 -> 0 | J67: ='Pigs Cost'!J67 -> 0 | ... L67: ='Pigs Cost'!L67 -> 0 | M67: =SUM(C67:L67) -> 0 | N67: ='Pigs Cost'!N67 -> 0 | O67: ='Pigs Cost'!O67 -> 0 | P67: ='Pigs Cost'!P67 -> 0 | Q67: ='[5]Outgrower pigs Sept 07 Quaranti'!$H39 -> 1.0125337e+09 | R67: =M67+O67+P67+Q67 -> 1.0125337e+09
A68: BOARS | C68: ='Pigs Cost'!C68 -> 0.12848784 | D68: ='Pigs Cost'!D68 -> 0 | E68: ='Pigs Cost'!E68 -> #REF! | F68: ='Pigs Cost'!F68 -> 0 | G68: ='Pigs Cost'!G68 -> 0 | H68: ='Pigs Cost'!H68 -> 0 | I68: ='Pigs Cost'!I68 -> 0 | J68: ='Pigs Cost'!J68 -> 0 | ... L68: ='Pigs Cost'!L68 -> 0 | M68: =SUM(C68:L68) -> #REF! | N68: ='Pigs Cost'!N68 -> 0 | O68: ='Pigs Cost'!O68 -> 0 | P68: ='Pigs Cost'!P68 -> 0 | Q68: ='[5]Outgrower pigs Sept 07 Quaranti'!$H40 -> 2.1078013e+09 | R68: =M68+O68+P68+Q68 -> #REF!
A69: TOTAL | C69: =SUM(C63:C68) -> 1322329.8 | D69: =SUM(D63:D68) -> 0 | E69: =SUM(E63:E67) -> #REF! | F69: =SUM(F63:F68) -> 0 | G69: =SUM(G63:G68) -> 0 | H69: =SUM(H63:H68) -> 0 | I69: =SUM(I63:I68) -> 0 | J69: =SUM(J63:J68) -> #REF! | K69: =SUM(K63:K68) -> 0 | L69: =SUM(L63:L68) -> 0 | M69: =SUM(M63:M68) -> #REF! | ... R69: =SUM(R63:R68) -> #REF! | S69: =R69-'[5]Outgrower pigs Sept 07 Quaranti'!$G$41 -> #REF! | T69: =Q69-'[5]Outgrower pigs Sept 07 Quaranti'!$H$41 -> 0
L71: =+(G69+H69+I69+K69+L69+J69)-I107 -> #REF!
A72: SITE: | B72: OSWA | L72: =+(G70+H70+I70+K70+L70+J70)-K119 -> 0
A74: DESCRIPTION | B74: SITE | C74: OPENING | D74: PIG PURCHASES | E74: TRANSFER IN | F74: A I CONSUMMABLES | G74: BEDDING AND CONSUMMABLES | H74: CONSULTANCY FEES | I74: DIRECT STAFF COSTS | J74: STOCK FEED | K74: SUNDRY TOOLS | L74: VETERINARY | M74: TOTAL COST | N74: AVERAGE COST | O74: TRANSFER OUT | P74: SALES | Q74: IAS 41 ADJ. | R74: CLOSING
A75: PIGLETS | B75: MAIN | C75: ='Pigs Cost'!C75 -> 3.2710113e+10 | D75: ='Pigs Cost'!D75 -> 0 | E75: ='Pigs Cost'!E75 -> #REF! | F75: ='Pigs Cost'!F75 -> 0 | G75: ='Pigs Cost'!G75 -> 0 | H75: ='Pigs Cost'!H75 -> 0 | I75: ='Pigs Cost'!I75 -> 0 | J75: ='Pigs Cost'!J75 -> #REF! | ... L75: ='Pigs Cost'!L75 -> 0 | M75: =SUM(C75:L75) -> #REF! | N75: ='Pigs Cost'!N75 -> #REF! | O75: ='Pigs Cost'!O75 -> #REF! | P75: ='Pigs Cost'!P75 -> #REF! | Q75: ='[5]Outgrower pigs Sept 07 OSWA'!$H34 -> 7.3784833e+09 | R75: =M75+O75+P75+Q75 -> #REF!
A76: WEANERS | B76: WEANER | C76: ='Pigs Cost'!C76 -> 1.3394549e+10 | D76: ='Pigs Cost'!D76 -> 0 | E76: ='Pigs Cost'!E76 -> #REF! | F76: ='Pigs Cost'!F76 -> 0 | G76: ='Pigs Cost'!G76 -> 0 | H76: ='Pigs Cost'!H76 -> 0 | I76: ='Pigs Cost'!I76 -> 0 | J76: ='Pigs Cost'!J76 -> #REF! | ... L76: ='Pigs Cost'!L76 -> 0 | M76: =SUM(C76:L76) -> #REF! | N76: ='Pigs Cost'!N76 -> #REF! | O76: ='Pigs Cost'!O76 -> #REF! | P76: ='Pigs Cost'!P76 -> #REF! | Q76: ='[5]Outgrower pigs Sept 07 OSWA'!$H35 -> 1.0123922e+11 | R76: =M76+O76+P76+Q76 -> #REF!
A77: GROWERS | B77: GROWER | C77: ='Pigs Cost'!C77 -> 1.7133034e+08 | D77: ='Pigs Cost'!D77 -> 0 | E77: ='Pigs Cost'!E77 -> #REF! | F77: ='Pigs Cost'!F77 -> 0 | G77: ='Pigs Cost'!G77 -> 0 | H77: ='Pigs Cost'!H77 -> 0 | I77: ='Pigs Cost'!I77 -> 0 | J77: ='Pigs Cost'!J77 -> #REF! | ... L77: ='Pigs Cost'!L77 -> 0 | M77: =SUM(C77:L77) -> #REF! | N77: ='Pigs Cost'!N77 -> #REF! | O77: ='Pigs Cost'!O77 -> #REF! | P77: ='Pigs Cost'!P77 -> #REF! | Q77: ='[5]Outgrower pigs Sept 07 OSWA'!$H36 -> 2.6053181e+10 | R77: =M77+O77+P77+Q77 -> #REF!
A78: GILTS | B78: MAIN | C78: ='Pigs Cost'!C78 -> 0 | D78: ='Pigs Cost'!D78 -> 0 | E78: ='Pigs Cost'!E78 -> #REF! | F78: ='Pigs Cost'!F78 -> 0 | G78: ='Pigs Cost'!G78 -> 0 | H78: ='Pigs Cost'!H78 -> 0 | I78: ='Pigs Cost'!I78 -> 0 | J78: ='Pigs Cost'!J78 -> 0 | ... L78: ='Pigs Cost'!L78 -> 0 | M78: =SUM(C78:L78) -> #REF! | N78: ='Pigs Cost'!N78 -> 0 | O78: ='Pigs Cost'!O78 -> #REF! | P78: ='Pigs Cost'!P78 -> 0 | Q78: ='[5]Outgrower pigs Sept 07 OSWA'!$H37 -> 2.0918493e+11 | R78: =M78+O78+P78+Q78 -> #REF!
A79: SOWS | B79: MAIN | C79: ='Pigs Cost'!C79 -> 80.838477 | D79: ='Pigs Cost'!D79 -> 0 | E79: ='Pigs Cost'!E79 -> #REF! | F79: ='Pigs Cost'!F79 -> 0 | G79: ='Pigs Cost'!G79 -> 0 | H79: ='Pigs Cost'!H79 -> 0 | I79: ='Pigs Cost'!I79 -> 0 | J79: ='Pigs Cost'!J79 -> 0 | ... L79: ='Pigs Cost'!L79 -> 0 | M79: =SUM(C79:L79) -> #REF! | N79: ='Pigs Cost'!N79 -> #REF! | O79: ='Pigs Cost'!O79 -> #REF! | P79: ='Pigs Cost'!P79 -> #REF! | Q79: ='[5]Outgrower pigs Sept 07 OSWA'!$H38 -> 5.0765403e+10 | R79: =M79+O79+P79+Q79 -> #REF!
A80: BOARS | C80: ='Pigs Cost'!C80 -> 0.40728137 | D80: ='Pigs Cost'!D80 -> 0 | E80: ='Pigs Cost'!E80 -> 0 | F80: ='Pigs Cost'!F80 -> 0 | G80: ='Pigs Cost'!G80 -> 0 | H80: ='Pigs Cost'!H80 -> 0 | I80: ='Pigs Cost'!I80 -> 0 | J80: ='Pigs Cost'!J80 -> 0 | ... L80: ='Pigs Cost'!L80 -> 0 | M80: =SUM(C80:L80) -> #REF! | N80: ='Pigs Cost'!N80 -> #REF! | O80: ='Pigs Cost'!O80 -> #REF! | P80: ='Pigs Cost'!P80 -> 0 | Q80: ='[5]Outgrower pigs Sept 07 OSWA'!$H39 -> 1.1299704e+09 | R80: =M80+O80+P80+Q80 -> #REF!
A81: TOTAL | C81: =SUM(C75:C80) -> 4.6275992e+10 | D81: =SUM(D75:D80) -> 0 | E81: =SUM(E75:E79) -> #REF! | F81: =SUM(F75:F80) -> 0 | G81: =SUM(G75:G80) -> 0 | H81: =SUM(H75:H80) -> 0 | I81: =SUM(I75:I80) -> 0 | J81: =SUM(J75:J80) -> #REF! | K81: =SUM(K75:K80) -> #REF! | L81: =SUM(L75:L80) -> 0 | M81: =SUM(M75:M80) -> #REF! | ... R81: =SUM(R75:R80) -> #REF! | S81: =R81-'[5]Outgrower pigs Sept 07 OSWA'!$G$40 -> #REF! | T81: =Q81-'[5]Outgrower pigs Sept 07 OSWA'!$H$40 -> 0
M83: =+J81-L103 -> #REF!
A84: SITE: | C84: TOTAL
B85: SITE
A86: MAIN SITE | B86: MAIN | C86: OPENING | D86: PIG PURCHASES | E86: TRANSFER IN | F86: A I CONSUMMABLES | G86: BEDDING AND CONSUMMABLES | H86: CONSULTANCY FEES | I86: DIRECT STAFF COSTS | J86: STOCK FEED | K86: SUNDRY TOOLS | L86: VETERINARY | M86: TOTAL COST | N86: AVERAGE COST | O86: TRANSFER OUT | P86: SALES | Q86: IAS 41 ADJ. | R86: CLOSING
A87: PIGLETS | B87: MAIN | C87: =C13+C25+C37+C63+C52+C75 -> 1.2939767e+11 | D87: =D13+D25+D37+D63+D52+D75 -> 0 | E87: =E13+E25+E37+E63+E52+E75 -> #REF! | F87: =F13+F25+F37+F63+F52+F75 -> #REF! | G87: =G13+G25+G37+G63+G52+G75 -> #REF! | H87: =H13+H25+H37+H63+H52+H75 -> #REF! | I87: =I13+I25+I37+I63+I52+I75 -> #REF! | J87: =J13+J25+J37+J63+J52+J75 -> #REF! | ... R87: =R13+R25+R37+R63+R52+R75 -> #REF!
A88: WEANERS | B88: WEANER | C88: =C14+C26+C38+C64+C53+C76 -> 1.2131395e+11 | D88: =D14+D26+D38+D64+D53+D76 -> 0 | E88: =E14+E26+E38+E64+E53+E76 -> #REF! | F88: =F14+F26+F38+F64+F53+F76 -> #REF! | G88: =G14+G26+G38+G64+G53+G76 -> #REF! | H88: =H14+H26+H38+H64+H53+H76 -> #REF! | I88: =I14+I26+I38+I64+I53+I76 -> #REF! | J88: =J14+J26+J38+J64+J53+J76 -> #REF! | ... R88: =R14+R26+R38+R64+R53+R76 -> #REF!
A89: GROWERS | B89: GROWER | C89: =C15+C27+C39+C65+C54+C77 -> 2.5453352e+11 | D89: =D15+D27+D39+D65+D54+D77 -> 0 | E89: =E15+E27+E39+E65+E54+E77 -> #REF! | F89: =F15+F27+F39+F65+F54+F77 -> #REF! | G89: =G15+G27+G39+G65+G54+G77 -> #REF! | H89: =H15+H27+H39+H65+H54+H77 -> #REF! | I89: =I15+I27+I39+I65+I54+I77 -> #REF! | J89: =J15+J27+J39+J65+J54+J77 -> #REF! | ... R89: =R15+R27+R39+R65+R54+R77 -> #REF!
A90: GILTS | B90: MAIN | C90: =C16+C28+C40+C66+C55+C78 -> 3.1277596e+09 | D90: =D16+D28+D40+D66+D55+D78 -> 0 | E90: =E16+E28+E66+E55+E78+E40 -> #REF! | F90: =F16+F28+F40+F66+F55+F78 -> #REF! | G90: =G16+G28+G40+G66+G55+G78 -> 0 | H90: =H16+H28+H40+H66+H55+H78 -> 0 | I90: =I16+I28+I40+I66+I55+I78 -> 0 | J90: =J16+J28+J40+J66+J55+J78 -> #REF! | K90: =K16+K28+K40+K66+K55+K78 -> #REF! | L90: =L16+L28+L40+L66+L55+L78 -> 0 | M90: =M16+M28+M40+M66+M55+M78 -> #REF! | N90: =N16+N40+N66+N55+N78 -> #REF! | O90: =O16+O28+O40+O66+O55+O78 -> #REF! | P90: =P16+P28+P40+P66+P55+P78 -> #REF! | Q90: =Q16+Q28+Q40+Q66+Q55+Q78 -> 3.6149641e+11 | R90: =R16+R28+R40+R66+R55+R78 -> #REF!
A91: SOWS | B91: MAIN | C91: =C17+C29+C41+C67+C56+C79 -> 2.1482648e+09 | D91: =D17+D29+D41+D67+D56+D79 -> 0 | E91: =E17+E29+E41+E67+E56+E79 -> #REF! | F91: =F17+F29+F41+F67+F56+F79 -> #REF! | G91: =G17+G29+G41+G67+G56+G79 -> 0 | H91: =H17+H29+H41+H67+H56+H79 -> #REF! | I91: =I17+I29+I41+I67+I56+I79 -> 0 | J91: =J17+J29+J41+J67+J56+J79 -> 0 | ... R91: =R17+R29+R41+R67+R56+R79 -> #REF!
A92: BOARS | B92: AI | C92: =C18+C30+C42+C68+C57+C80 -> 109059.16 | D92: =D18+D30+D42+D68+D57+D80 -> 0 | E92: =E18+E30+E42+E68+E57+E80 -> #REF! | F92: =F18+F30+F42+F68+F57+F80 -> 0 | G92: =G18+G30+G42+G68+G57+G80 -> 0 | H92: =H18+H30+H42+H68+H57+H80 -> 0 | I92: =I18+I30+I42+I68+I57+I80 -> 0 | J92: =J18+J30+J42+J68+J57+J80 -> 0 | ... R92: =R18+R30+R42+R68+R57+R80 -> #REF!
A93: TOTAL | C93: =SUM(C87:C92) -> 5.1052126e+11 | D93: =SUM(D87:D92) -> 0 | E93: =SUM(E87:E92) -> #REF! | F93: =SUM(F87:F92) -> #REF! | G93: =SUM(G87:G92) -> #REF! | H93: =SUM(H87:H92) -> #REF! | I93: =SUM(I87:I92) -> #REF! | J93: =SUM(J87:J92) -> #REF! | ... R93: =SUM(R87:R92) -> #REF! | S93: =R93-'[6]PigsMay 07 '!$G$40-'[6]Outgrower pigs Sept07 TRADE WIN'!$G$40-'[6]Outgrower pigs Sept 07 ZIMBO'!$G$40-'[6]Outgrower pigs Sept 07 ROGATE'!$G$40-'[6]Outgrower pigs Sept 07 Quaranti'!$G$41-'[6]Outgrower pigs Sept 07 OSWA'!$G$40 -> #REF!
C94: =C93-'Pigs Cost'!C164 -> -1.2231493e+11 | Q94: =Q93-'[5]PigsMay 07 '!$H$40-'[5]Outgrower pigs Sept07 TRADE WIN'!$H$40-'[5]Outgrower pigs Sept 07 ZIMBO'!$H$40-'[5]Outgrower pigs Sept 07 ROGATE'!$H$40-'[5]Outgrower pigs Sept 07 Quaranti'!$H$41-'[5]Outgrower pigs Sept 07 OSWA'!$H$40 -> 0 | R94: =+R93-'Pigs Cost'!T164 -> #REF!
E95: =E93--O93 -> #REF! | R95: =+Q93-R94 -> #REF!
B97: Direct expenses | F97: Less Cattle | G97: Less Trade winds | H97: Less Zimbo | I97: Less Quarantine | J97: Grasmere | K97: Rotgate | L97: Oswa | O97: =+O93+E93 -> #REF!
B98: Establishment Expenses
B99: Al Consumbables | D99: =+J99 -> 512906500 | E99: =+J99 -> 512906500 | G99: =+'[7]IS - YTD'!M15 -> 0 | H99: =+'[8]IS - YTD'!M15 -> 0 | I99: =+'[9]IS - YTD'!L15 -> 0 | J99: ='[10]IS - YTD'!$B$15 -> 512906500 | K99: =+'[11]IS - YTD'!L15 -> 0 | L99: =+'[12]IS - YTD'!M15 -> 0
B100: Bedding & Consumables | D100: =+J100 -> 2.9929352e+09 | E100: =+J100 -> 2.9929352e+09 | G100: =+'[7]IS - YTD'!M16 -> 0 | H100: =+'[8]IS - YTD'!M16 -> 0 | I100: =+'[9]IS - YTD'!L16 -> 0 | J100: ='[10]IS - YTD'!$B$16 -> 2.9929352e+09 | K100: =+'[11]IS - YTD'!L16 -> 0 | L100: =+'[12]IS - YTD'!M16 -> 0
B101: Consultancy Fees | D101: =+J101 -> 179062500 | E101: =+J101 -> 179062500 | G101: =+'[7]IS - YTD'!M17 -> 0 | H101: =+'[8]IS - YTD'!M17 -> 0 | I101: =+'[9]IS - YTD'!L17 -> 0 | J101: ='[10]IS - YTD'!$B$17 -> 179062500 | K101: =+'[11]IS - YTD'!L17 -> 0 | L101: =+'[12]IS - YTD'!M17 -> 0
B102: Staff & Associated Costs | D102: =+J102 -> 2.1935628e+08 | E102: =+J102 -> 2.1935628e+08 | G102: 0 | H102: 0 | I102: 0 | J102: ='[10]IS - YTD'!$B$18 -> 2.1935628e+08 | K102: 0 | L102: 0
B103: Stockfeed | D103: =+J103 -> 3.1815713e+10 | E103: =SUM(F103:L103) -> 3.2276753e+10 | G103: ='[13]Feed Mvmt Values'!$D$60 -> 179469491 | H103: ='[13]Feed Mvmt Values'!$D$61 -> 19487377 | I103: ='[13]Feed Mvmt Values'!$D$59 -> 830585 | J103: ='[10]IS - YTD'!$B$19-G103-H103-I103-K103-L103 -> 3.1815713e+10 | K103: ='[13]Feed Mvmt Values'!$D$62 -> 132026775 | L103: ='[13]Feed Mvmt Values'!$D$63 -> 129225729
B104: Sundry Tools & Equipment | D104: =+J104 -> 42540000 | E104: =+J104 -> 42540000 | G104: =+'[7]IS - YTD'!M20 -> 0 | H104: =+'[8]IS - YTD'!M20 -> 0 | I104: =+'[9]IS - YTD'!L20 -> 0 | J104: ='[10]IS - YTD'!$B$20 -> 42540000 | L104: =+'[12]IS - YTD'!M20 -> 0
B105: Veterinary, Health & Hygiene | D105: =+J105 -> 1.4533575e+09 | E105: =+J105 -> 1.4533575e+09 | G105: =+'[7]IS - YTD'!M21 -> 0 | H105: =+'[8]IS - YTD'!M21 -> 0 | I105: =+'[9]IS - YTD'!L21 -> 0 | J105: ='[10]IS - YTD'!$B$22 -> 1.4533575e+09 | K105: =+'[11]IS - YTD'!L21 -> 0 | L105: 0
E107: =SUM(E99:E105) -> 3.7676911e+10 | F107: =SUM(F99:F105) -> 0 | G107: =SUM(G99:G105) -> 179469491 | H107: =SUM(H99:H105) -> 19487377 | I107: =SUM(I99:I105) -> 830585 | J107: =SUM(J99:J105) -> 3.7215871e+10 | K107: =SUM(K99:K105) -> 132026775 | L107: =SUM(L99:L105) -> 129225729
J108: =+J107-'[14]IS - YTD'!$B$23 -> 2.3381162e+10 | K108: =+K107-J58 -> -11099867973225
J110: =J107-37985651236.24 -> -7.6978001e+08
G116: =+G103-7288311.75 -> 1.7218118e+08
A123: CR
A124: CR
A125: CR
A126: CR
A127: CR
A128: CR
A129: CR
A130: CR
A131: CR
...

Sheet Pigs Cost
A1: COLCOM HOLDINGS LIMITED
T2: =+'Summary Total Pigs'!C3 -> 46226
A3: TRIPLE C PIGS
A5: LIVESTOCK ANALYSIS SCHEDULE
A7: COST
A10: SITE: | B10: GRASMERE FARM
A12: DESCRIPTION | B12: SITE | C12: OPENING | D12: PIG PURCHASES | E12: TRANSFER IN | F12: A I CONSUMMABLES | G12: BEDDING AND CONSUMMABLES | H12: CONSULTANCY FEES | I12: DIRECT STAFF COSTS | J12: STOCK FEED | K12: SUNDRY TOOLS | L12: VETERINARY | M12: TOTAL COST | N12: AVERAGE COST | O12: TRANSFER OUT | P12: SALES | Q12: ='Summary Total Pigs'!#REF! -> #REF! | R12: CULLS | S12: STOCK ADJMNT | T12: CLOSING
A13: PIGLETS | B13: MAIN | C13: ='[16]Pigs Cost'!$T13 -> 7.6193293e+10 | F13: =E170 -> 0 | G13: =('Summary Total Pigs'!AE12+'Summary Total Pigs'!AE15+'Summary Total Pigs'!AE16+'Summary Total Pigs'!AE17)/'Summary Total Pigs'!#REF!*'Pigs Cost'!E171 -> #REF! | H13: =('Summary Total Pigs'!AE12+'Summary Total Pigs'!AE15+'Summary Total Pigs'!AE16+'Summary Total Pigs'!AE17)/'Summary Total Pigs'!#REF!*'Pigs Cost'!E172 -> #REF! | I13: =E173/3 -> 0 | J13: =('Summary Total Pigs'!AE12+'Summary Total Pigs'!AE15+'Summary Total Pigs'!AE16+'Summary Total Pigs'!AE17)/'Summary Total Pigs'!#REF!*'Pigs Cost'!J174 -> #REF! | K13: =('Summary Total Pigs'!AE12+'Summary Total Pigs'!AE15+'Summary Total Pigs'!AE16+'Summary Total Pigs'!AE17)/'Summary Total Pigs'!#REF!*'Pigs Cost'!E175 -> #REF! | L13: =('Summary Total Pigs'!AE12+'Summary Total Pigs'!AE15+'Summary Total Pigs'!AE16+'Summary Total Pigs'!AE17)/'Summary Total Pigs'!#REF!*'Pigs Cost'!J176 -> #REF! | M13: =SUM(C13:L13) -> #REF! | N13: =M13/'Summary Total Pigs'!#REF! -> #REF! | O13: =N13*'Summary Total Pigs'!#REF! -> #REF! | P13: =N13*'Summary Total Pigs'!X12 -> #REF! | Q13: ='Summary Total Pigs'!#REF!*'Pigs Cost'!N13 -> #REF! | R13: =N13*'Summary Total Pigs'!Z12 -> #REF! | S13: ='Summary Total Pigs'!#REF!*'Pigs Cost'!N13 -> #REF! | T13: =M13+O13+P13+R13+S13+Q13 -> #REF! | V13: =[17]Sheet1!$E163 -> 2.2668926e+08 | W13: =T13-V13 -> #REF!
A14: WEANERS | B14: WEANER | C14: ='[16]Pigs Cost'!$T14 -> 1.0410751e+11 | E14: ='Summary Total Pigs'!D13*N13 -> #REF! | G14: ='Summary Total Pigs'!AE13/'Summary Total Pigs'!#REF!*'Pigs Cost'!E171 -> #REF! | H14: ='Summary Total Pigs'!AE13/'Summary Total Pigs'!#REF!*'Pigs Cost'!E172 -> #REF! | I14: =I13 -> 0 | J14: ='Summary Total Pigs'!AE13/'Summary Total Pigs'!#REF!*'Pigs Cost'!J174 -> #REF! | K14: =('Summary Total Pigs'!AE13)/'Summary Total Pigs'!#REF!*'Pigs Cost'!E175 -> #REF! | L14: ='Summary Total Pigs'!AE13/'Summary Total Pigs'!#REF!*'Pigs Cost'!J176 -> #REF! | M14: =SUM(C14:L14) -> #REF! | N14: =M14/'Summary Total Pigs'!#REF! -> #REF! | O14: =N14*'Summary Total Pigs'!#REF! -> #REF! | P14: =N14*'Summary Total Pigs'!X13 -> #REF! | Q14: ='Summary Total Pigs'!#REF!*'Pigs Cost'!N14 -> #REF! | R14: =N14*'Summary Total Pigs'!Z13 -> #REF! | S14: ='Summary Total Pigs'!#REF!*'Pigs Cost'!N14 -> #REF! | T14: =M14+O14+P14+R14+S14+Q14 -> #REF! | V14: =[17]Sheet1!$E164 -> 2.6090144e+08 | W14: =T14-V14 -> #REF!
A15: GROWERS | B15: GROWER | C15: ='[16]Pigs Cost'!$T15 -> 2.2702568e+11 | E15: =3838*N14+19*N16 -> #REF! | G15: ='Summary Total Pigs'!AE14/'Summary Total Pigs'!#REF!*'Pigs Cost'!E171 -> #REF! | H15: ='Summary Total Pigs'!AE14/'Summary Total Pigs'!#REF!*'Pigs Cost'!E172 -> #REF! | I15: =I14 -> 0 | J15: ='Summary Total Pigs'!AE14/'Summary Total Pigs'!#REF!*'Pigs Cost'!J174 -> #REF! | K15: =('Summary Total Pigs'!AE14)/'Summary Total Pigs'!#REF!*'Pigs Cost'!E175 -> #REF! | L15: ='Summary Total Pigs'!AE14/'Summary Total Pigs'!#REF!*'Pigs Cost'!J176 -> #REF! | M15: =SUM(C15:L15) -> #REF! | N15: =M15/'Summary Total Pigs'!#REF! -> #REF! | O15: =N15*'Summary Total Pigs'!#REF! -> #REF! | P15: =N15*'Summary Total Pigs'!X14 -> #REF! | Q15: ='Summary Total Pigs'!#REF!*'Pigs Cost'!N15 -> #REF! | R15: =N15*'Summary Total Pigs'!Z14 -> #REF! | S15: ='Summary Total Pigs'!#REF!*'Pigs Cost'!N15 -> #REF! | T15: =M15+O15+P15+R15+S15+Q15 -> #REF! | V15: =[17]Sheet1!$E165 -> 5.2935144e+08 | W15: =T15-V15 -> #REF!
A16: GILTS | B16: MAIN | C16: ='[16]Pigs Cost'!$T16 -> 3.0124651e+09 | D16: 0 | E16: =N13*'Summary Total Pigs'!D15 -> #REF! | G16: 0 | H16: 0 | I16: 0 | J16: 0 | K16: 0 | L16: 0 | M16: =SUM(C16:L16) -> #REF! | N16: =M16/'Summary Total Pigs'!#REF! -> #REF! | O16: =N16*'Summary Total Pigs'!#REF! -> #REF! | P16: ='Summary Total Pigs'!X15*'Pigs Cost'!N16 -> #REF! | Q16: ='Summary Total Pigs'!#REF!*'Pigs Cost'!N16 -> #REF! | R16: =N16*'Summary Total Pigs'!Z15 -> #REF! | S16: ='Summary Total Pigs'!#REF!*'Pigs Cost'!N16 -> #REF! | T16: =M16+O16+P16+R16+S16+Q16 -> #REF! | V16: =[17]Sheet1!$E166 -> 13324897 | W16: =T16-V16 -> #REF!
A17: SOWS | B17: MAIN | C17: ='[16]Pigs Cost'!$T17 -> 7.0513089e+08 | E17: ='Summary Total Pigs'!D16*N16 -> #REF! | G17: 0 | H17: 0 | I17: =I16 -> 0 | J17: 0 | K17: 0 | L17: 0 | M17: =SUM(C17:L17) -> #REF! | N17: =M17/'Summary Total Pigs'!#REF! -> #REF! | O17: =N17*'Summary Total Pigs'!#REF! -> #REF! | P17: =N17*'Summary Total Pigs'!X16 -> #REF! | Q17: ='Summary Total Pigs'!#REF!*'Pigs Cost'!N17 -> #REF! | R17: =N17*'Summary Total Pigs'!Z16 -> #REF! | S17: ='Summary Total Pigs'!#REF!*'Pigs Cost'!N17 -> #REF! | T17: =M17+O17+P17+R17+S17+Q17 -> #REF! | V17: =[17]Sheet1!$E167 -> 792833.6 | W17: =T17-V17 -> #REF!
A18: BOARS | B18: AI | C18: ='[16]Pigs Cost'!$T18 -> 109058.54 | E18: ='Summary Total Pigs'!D17*N15 -> #REF! | F18: 0 | G18: 0 | H18: 0 | I18: =I17 -> 0 | J18: 0 | K18: 0 | L18: 0 | M18: =SUM(C18:L18) -> #REF! | N18: =M18/'Summary Total Pigs'!#REF! -> #REF! | O18: =N18*'Summary Total Pigs'!#REF! -> #REF! | P18: =N18*'Summary Total Pigs'!X17 -> #REF! | Q18: ='Summary Total Pigs'!#REF!*'Pigs Cost'!N18 -> #REF! | R18: =N18*'Summary Total Pigs'!Z17 -> #REF! | S18: ='Summary Total Pigs'!#REF!*'Pigs Cost'!N18 -> #REF! | T18: =M18+O18+P18+R18+S18+Q18 -> #REF! | V18: =[17]Sheet1!$E168 -> 109058.54 | W18: =T18-V18 -> #REF!
A19: TOTAL | C19: =SUM(C13:C18) -> 4.1104419e+11 | D19: =SUM(D13:D18) -> 0 | E19: =SUM(E13:E18) -> #REF! | F19: =SUM(F13:F18) -> 0 | G19: =SUM(G13:G18) -> #REF! | H19: =SUM(H13:H18) -> #REF! | I19: =SUM(I13:I18) -> 0 | J19: =SUM(J13:J18) -> #REF! | ... T19: =SUM(T13:T18) -> #REF! | V19: =SUM(V13:V18) -> 1.0311689e+09 | W19: =T19-V19 -> #REF!
E20: =E19+O19 -> #REF! | F20: =F19-E170 -> 0 | G20: =G19-E171 -> #REF! | H20: =H19-E172 -> #REF! | I20: =I19-E173 -> 0 | J20: =J19-J174 -> #REF! | K20: =K19-E175 -> #REF! | L20: =L19-E176 -> #REF! | V20: =C20/$B$178 -> 0
E21: =E20+Sheet1!C14 -> #REF! | L21: =+(G19+H19+I19+K19+L19+J19+F19)-J178 -> #REF! | V21: =C21/$B$178 -> 0
A22: SITE: | B22: TRADE WINDS | V22: =C22/$B$178 -> 0
V23: =C23/$B$178 -> 0
A24: DESCRIPTION | B24: SITE | C24: =+C12 -> OPENING | D24: PIG PURCHASES | E24: TRANSFER IN | F24: A I CONSUMMABLES | G24: BEDDING AND CONSUMMABLES | H24: CONSULTANCY FEES | I24: DIRECT STAFF COSTS | J24: STOCK FEED | K24: SUNDRY TOOLS | L24: VETERINARY | M24: TOTAL COST | N24: AVERAGE COST | O24: TRANSFER OUT | P24: SALES | Q24: ='Summary Total Pigs'!#REF! -> #REF! | R24: =R12 -> CULLS | S24: =+S12 -> STOCK ADJMNT | T24: CLOSING
A25: PIGLETS | B25: MAIN | C25: ='[16]Pigs Cost'!$T25 -> 0 | E25: ='Summary Total Pigs'!#REF!*N23 -> #REF! | G25: =('Summary Total Pigs'!#REF!+'Summary Total Pigs'!#REF!)/'Summary Total Pigs'!#REF!*$G$171 -> #REF! | H25: =('Summary Total Pigs'!#REF!+'Summary Total Pigs'!#REF!)/'Summary Total Pigs'!#REF!*'Pigs Cost'!$G$172 -> #REF! | I25: =('Summary Total Pigs'!#REF!+'Summary Total Pigs'!#REF!)/'Summary Total Pigs'!#REF!*'Pigs Cost'!$G$173 -> #REF! | J25: =('Summary Total Pigs'!#REF!+'Summary Total Pigs'!#REF!)/'Summary Total Pigs'!#REF!*'Pigs Cost'!$G$174 -> #REF! | K25: =('Summary Total Pigs'!#REF!/'Summary Total Pigs'!#REF!)*'Pigs Cost'!$G$175 -> #REF! | L25: =('Summary Total Pigs'!#REF!+'Summary Total Pigs'!#REF!)/'Summary Total Pigs'!#REF!*G176 -> #REF! | M25: =SUM(C25:L25) -> #REF! | N25: 0 | O25: =N25*'Summary Total Pigs'!#REF! -> #REF! | P25: =N25*'Summary Total Pigs'!#REF! -> #REF! | Q25: ='Summary Total Pigs'!#REF!*'Pigs Cost'!N25 -> #REF! | R25: =N25*'Summary Total Pigs'!#REF! -> #REF! | S25: ='Summary Total Pigs'!#REF!*'Pigs Cost'!N25 -> #REF! | T25: =M25+O25+P25+R25+S25+Q25 -> #REF! | V25: =C25/$B$178 -> 0
A26: WEANERS | B26: WEANER | C26: ='[16]Pigs Cost'!$T26 -> 0 | E26: 0 | G26: =('Summary Total Pigs'!#REF!)/'Summary Total Pigs'!#REF!*$G$171 -> #REF! | H26: =('Summary Total Pigs'!#REF!)/'Summary Total Pigs'!#REF!*'Pigs Cost'!G172 -> #REF! | I26: =('Summary Total Pigs'!#REF!)/'Summary Total Pigs'!#REF!*'Pigs Cost'!$G$173 -> #REF! | J26: =('Summary Total Pigs'!#REF!)/'Summary Total Pigs'!#REF!*'Pigs Cost'!$G$174 -> #REF! | K26: =('Summary Total Pigs'!#REF!/'Summary Total Pigs'!#REF!)*'Pigs Cost'!$G$175 -> #REF! | M26: =SUM(C26:L26) -> #REF! | N26: 0 | O26: =N26*'Summary Total Pigs'!#REF! -> #REF! | P26: =N26*'Summary Total Pigs'!#REF! -> #REF! | Q26: ='Summary Total Pigs'!#REF!*'Pigs Cost'!N26 -> #REF! | R26: =N26*'Summary Total Pigs'!#REF! -> #REF! | S26: ='Summary Total Pigs'!#REF!*'Pigs Cost'!N26 -> #REF! | T26: =M26+O26+P26+R26+S26+Q26 -> #REF! | V26: =C26/$B$178 -> 0
A27: GROWERS | B27: GROWER | C27: ='[16]Pigs Cost'!$T27 -> 1.4341696e+10 | E27: =N101*'Summary Total Pigs'!#REF! -> #REF! | G27: =('Summary Total Pigs'!#REF!)/'Summary Total Pigs'!#REF!*$G$171 -> #REF! | H27: =('Summary Total Pigs'!#REF!)/'Summary Total Pigs'!#REF!*'Pigs Cost'!$G$172 -> #REF! | I27: =('Summary Total Pigs'!#REF!)/'Summary Total Pigs'!#REF!*'Pigs Cost'!$G$173 -> #REF! | J27: =('Summary Total Pigs'!#REF!)/'Summary Total Pigs'!#REF!*'Pigs Cost'!$G$174 -> #REF! | K27: =('Summary Total Pigs'!#REF!/'Summary Total Pigs'!#REF!)*'Pigs Cost'!$G$175 -> #REF! | L27: ='Summary Total Pigs'!#REF!/'Summary Total Pigs'!#REF!*G176 -> #REF! | M27: =SUM(C27:L27) -> #REF! | N27: =M27/'Summary Total Pigs'!#REF! -> #REF! | O27: =N27*'Summary Total Pigs'!#REF! -> #REF! | P27: =N27*'Summary Total Pigs'!#REF! -> #REF! | Q27: ='Summary Total Pigs'!#REF!*'Pigs Cost'!N27 -> #REF! | R27: =N27*'Summary Total Pigs'!#REF! -> #REF! | S27: ='Summary Total Pigs'!#REF!*'Pigs Cost'!N27 -> #REF! | T27: =M27+O27+P27+R27+S27+Q27 -> #REF! | V27: =[17]Sheet1!$O$165 -> 35912726 | W27: =T27-V27 -> #REF!
A28: GILTS | B28: MAIN | C28: ='[16]Pigs Cost'!$T28 -> 0 | E28: ='Summary Total Pigs'!#REF!*N26 -> #REF! | K28: =('Summary Total Pigs'!#REF!/'Summary Total Pigs'!#REF!)*'Pigs Cost'!$G$175 -> #REF! | M28: 0 | O28: =N28*'Summary Total Pigs'!#REF! -> #REF! | P28: =N28*'Summary Total Pigs'!#REF! -> #REF! | Q28: ='Summary Total Pigs'!#REF!*'Pigs Cost'!N28 -> #REF! | R28: =N28*'Summary Total Pigs'!#REF! -> #REF! | S28: ='Summary Total Pigs'!#REF!*'Pigs Cost'!N28 -> #REF! | T28: =M28+O28+P28+R28+S28+Q28 -> #REF! | V28: =C28/$B$178 -> 0
A29: SOWS | B29: MAIN | C29: ='[16]Pigs Cost'!$T29 -> 0 | E29: 0 | H29: =('Summary Total Pigs'!#REF!)/'Summary Total Pigs'!#REF!*'Pigs Cost'!$G$172 -> #REF! | K29: =('Summary Total Pigs'!#REF!/'Summary Total Pigs'!#REF!)*'Pigs Cost'!$G$175 -> #REF! | M29: =SUM(C29:L29) -> #REF! | O29: =N29*'Summary Total Pigs'!#REF! -> #REF! | P29: =N29*'Summary Total Pigs'!#REF! -> #REF! | Q29: ='Summary Total Pigs'!#REF!*'Pigs Cost'!N29 -> #REF! | R29: =N29*'Summary Total Pigs'!#REF! -> #REF! | S29: ='Summary Total Pigs'!#REF!*'Pigs Cost'!N29 -> #REF! | T29: =M29+O29+P29+R29+S29+Q29 -> #REF! | V29: =C29/$B$178 -> 0
A30: BOARS | C30: ='[16]Pigs Cost'!$T30 -> 0 | E30: ='Summary Total Pigs'!#REF!*N28 -> #REF! | K30: =('Summary Total Pigs'!#REF!/'Summary Total Pigs'!#REF!)*'Pigs Cost'!$G$175 -> #REF! | M30: =SUM(C30:L30) -> #REF! | O30: =N30*'Summary Total Pigs'!#REF! -> #REF! | Q30: ='Summary Total Pigs'!#REF!*'Pigs Cost'!N30 -> #REF! | R30: =N30*'Summary Total Pigs'!#REF! -> #REF! | S30: ='Summary Total Pigs'!#REF!*'Pigs Cost'!N30 -> #REF! | T30: =M30+O30+P30+R30+S30+Q30 -> #REF! | V30: =C30/$B$178 -> 0
A31: TOTAL | C31: =SUM(C25:C30) -> 1.4341696e+10 | D31: =SUM(D25:D30) -> 0 | E31: =SUM(E25:E30) -> #REF! | F31: =SUM(F25:F30) -> 0 | G31: =SUM(G25:G30) -> #REF! | H31: =SUM(H25:H30) -> #REF! | I31: =SUM(I25:I30) -> #REF! | J31: =SUM(J25:J30) -> #REF! | ... T31: =SUM(T25:T30) -> #REF! | V31: =C31/$B$178 -> 1.4341696
J32: =J31-G174 -> #REF! | K32: =+K31-G175 -> #REF! | V32: =C32/$B$178 -> 0
L33: =+(G31+H31+I31+K31+L31+J31)-G178 -> #REF! | V33: =C33/$B$178 -> 0
A34: SITE: | B34: ZIMBO | V34: =C34/$B$178 -> 0
V35: =C35/$B$178 -> 0
A36: DESCRIPTION | B36: SITE | C36: =+C24 -> OPENING | D36: PIG PURCHASES | E36: TRANSFER IN | F36: A I CONSUMMABLES | G36: BEDDING AND CONSUMMABLES | H36: CONSULTANCY FEES | I36: DIRECT STAFF COSTS | J36: STOCK FEED | K36: SUNDRY TOOLS | L36: VETERINARY | M36: TOTAL COST | N36: AVERAGE COST | O36: TRANSFER OUT | P36: SALES | Q36: ='Summary Total Pigs'!W49 -> Deaths | R36: =R24 -> CULLS | S36: =+S24 -> STOCK ADJMNT | T36: CLOSING
A37: PIGLETS | B37: MAIN | C37: ='[16]Pigs Cost'!$T37 -> 3.1052778e+09 | F37: =+$H$169*'Summary Total Pigs'!#REF!/'Summary Total Pigs'!#REF! -> #REF! | G37: =('Summary Total Pigs'!AE50+'Summary Total Pigs'!AE54)/'Summary Total Pigs'!AE56*'Pigs Cost'!$H$171 -> 0 | H37: =('Summary Total Pigs'!AE50+'Summary Total Pigs'!$AE$54)/'Summary Total Pigs'!$AE$56*'Pigs Cost'!$H$172 -> 0 | I37: =('Summary Total Pigs'!AE50+'Summary Total Pigs'!$AE$54)/'Summary Total Pigs'!$AE$56*'Pigs Cost'!$H$173 -> 0 | J37: =('Summary Total Pigs'!AE50+'Summary Total Pigs'!AE53+'Summary Total Pigs'!AE54+'Summary Total Pigs'!AE55)/'Summary Total Pigs'!$AE$56*'Pigs Cost'!$H$174 -> 1.4288071e+12 | K37: =('Summary Total Pigs'!AE50+'Summary Total Pigs'!$AE$54)/'Summary Total Pigs'!$AE$56*'Pigs Cost'!$H$175 -> 0 | L37: =('Summary Total Pigs'!$AE$50+'Summary Total Pigs'!$AE$54)/'Summary Total Pigs'!$AE$56*'Pigs Cost'!$H$176 -> 0 | M37: =SUM(C37:L37) -> #REF! | N37: =M37/'Summary Total Pigs'!#REF! -> #REF! | O37: ='Summary Total Pigs'!N50*'Pigs Cost'!N37 -> #REF! | P37: =N37*'Summary Total Pigs'!#REF! -> #REF! | Q37: ='Summary Total Pigs'!W50*'Pigs Cost'!N37 -> #REF! | R37: ='Summary Total Pigs'!X50*'Pigs Cost'!N37 -> #REF! | S37: ='Summary Total Pigs'!AD50*'Pigs Cost'!N37 -> #REF! | T37: =M37+O37+P37+R37+S37+Q37 -> #REF! | V37: =[17]Sheet1!$Q163 -> 34479972 | W37: =T37-V37 -> #REF!
A38: WEANERS | B38: WEANER | C38: ='[16]Pigs Cost'!$T38 -> 0 | F38: =+$H$169*'Summary Total Pigs'!#REF!/'Summary Total Pigs'!#REF! -> #REF! | G38: =('Summary Total Pigs'!AE51)/'Summary Total Pigs'!$AE$56*'Pigs Cost'!$H$171 -> 0 | H38: =('Summary Total Pigs'!AE51)/'Summary Total Pigs'!$AE$56*'Pigs Cost'!$H$172 -> 0 | I38: =('Summary Total Pigs'!AE51)/'Summary Total Pigs'!$AE$56*'Pigs Cost'!$H$173 -> 0 | J38: =('Summary Total Pigs'!AE51)/'Summary Total Pigs'!$AE$56*'Pigs Cost'!$H$174 -> 1.471066e+12 | K38: =('Summary Total Pigs'!AE51)/'Summary Total Pigs'!$AE$56*'Pigs Cost'!$H$175 -> 0 | L38: =('Summary Total Pigs'!AE51)/'Summary Total Pigs'!$AE$56*'Pigs Cost'!$H$176 -> 0 | M38: =SUM(C38:L38) -> #REF! | O38: ='Summary Total Pigs'!N51*'Pigs Cost'!N38 -> 0 | P38: =N38*'Summary Total Pigs'!#REF! -> #REF! | Q38: ='Summary Total Pigs'!W51*'Pigs Cost'!N38 -> 0 | R38: ='Summary Total Pigs'!X51*'Pigs Cost'!N38 -> 0 | S38: ='Summary Total Pigs'!AD51*'Pigs Cost'!N38 -> 0 | T38: =M38+O38+P38+R38+S38+Q38 -> #REF! | V38: =[17]Sheet1!$Q164
A39: GROWERS | B39: GROWER | C39: ='[16]Pigs Cost'!$T39 -> -5.9604645e-18 | F39: =+$H$169*'Summary Total Pigs'!#REF!/'Summary Total Pigs'!#REF! -> #REF! | G39: =('Summary Total Pigs'!AE52)/'Summary Total Pigs'!$AE$56*'Pigs Cost'!$H$171 -> 0 | H39: =('Summary Total Pigs'!AE52)/'Summary Total Pigs'!$AE$56*'Pigs Cost'!$H$172 -> 0 | I39: =('Summary Total Pigs'!AE52)/'Summary Total Pigs'!$AE$56*'Pigs Cost'!$H$173 -> 0 | J39: =('Summary Total Pigs'!AE52)/'Summary Total Pigs'!$AE$56*'Pigs Cost'!$H$174 -> 2.8001269e+12 | K39: =('Summary Total Pigs'!AE52)/'Summary Total Pigs'!$AE$56*'Pigs Cost'!$H$175 -> 0 | L39: =('Summary Total Pigs'!AE52)/'Summary Total Pigs'!$AE$56*'Pigs Cost'!$H$176 -> 0 | M39: =SUM(C39:L39) -> #REF! | O39: ='Summary Total Pigs'!N52*'Pigs Cost'!N39 -> 0 | P39: =N39*'Summary Total Pigs'!#REF! -> #REF! | Q39: ='Summary Total Pigs'!W52*'Pigs Cost'!N39 -> 0 | R39: ='Summary Total Pigs'!X52*'Pigs Cost'!N39 -> 0 | S39: ='Summary Total Pigs'!AD52*'Pigs Cost'!N39 -> 0 | T39: =M39+O39+P39+R39+S39+Q39 -> #REF! | V39: =[17]Sheet1!$Q165
A40: GILTS | B40: MAIN | C40: ='[16]Pigs Cost'!$T40 -> 0 | E40: =N66*'Summary Total Pigs'!D53 -> #REF! | F40: =+$H$169*'Summary Total Pigs'!#REF!/'Summary Total Pigs'!#REF! -> #REF! | G40: =('Summary Total Pigs'!AE53)/'Summary Total Pigs'!$AE$56*'Pigs Cost'!$H$171 -> 0 | H40: =('Summary Total Pigs'!AE53)/'Summary Total Pigs'!$AE$56*'Pigs Cost'!$H$172 -> 0 | I40: =('Summary Total Pigs'!AE53)/'Summary Total Pigs'!$AE$56*'Pigs Cost'!$H$173 -> 0 | J40: 0 | K40: =('Summary Total Pigs'!AE53)/'Summary Total Pigs'!$AE$56*'Pigs Cost'!$H$175 -> 0 | L40: =('Summary Total Pigs'!AE53)/'Summary Total Pigs'!$AE$56*'Pigs Cost'!$H$176 -> 0 | M40: =SUM(C40:L40) -> #REF! | N40: =M40/'Summary Total Pigs'!#REF! -> #REF! | O40: ='Summary Total Pigs'!N53*'Pigs Cost'!N40 -> #REF! | P40: =N40*'Summary Total Pigs'!#REF! -> #REF! | Q40: ='Summary Total Pigs'!W53*'Pigs Cost'!N40 -> #REF! | R40: ='Summary Total Pigs'!X53*'Pigs Cost'!N40 -> #REF! | S40: ='Summary Total Pigs'!AD53*'Pigs Cost'!N40 -> #REF! | T40: =M40+O40+P40+R40+S40+Q40 -> #REF! | V40: =[17]Sheet1!$Q166
A41: SOWS | B41: MAIN | C41: ='[16]Pigs Cost'!$T41 -> 146128.33 | E41: =N40*'Summary Total Pigs'!D54 -> #REF! | F41: =+$H$169*'Summary Total Pigs'!#REF!/'Summary Total Pigs'!#REF! -> #REF! | J41: 0 | K41: =('Summary Total Pigs'!AE53)/'Summary Total Pigs'!$AE$56*'Pigs Cost'!$H$175 -> 0 | L41: =H176 -> 0 | M41: =SUM(C41:L41) -> #REF! | N41: =M41/'Summary Total Pigs'!#REF! -> #REF! | O41: ='Summary Total Pigs'!N54*'Pigs Cost'!N41 -> #REF! | P41: =N41*'Summary Total Pigs'!#REF! -> #REF! | Q41: ='Summary Total Pigs'!W54*'Pigs Cost'!N41 -> #REF! | R41: ='Summary Total Pigs'!X54*'Pigs Cost'!N41 -> #REF! | S41: ='Summary Total Pigs'!AD54*'Pigs Cost'!N41 -> #REF! | T41: =M41+O41+P41+R41+S41+Q41 -> #REF! | V41: =[17]Sheet1!$Q167 -> 155612.62 | W41: =T41-V41 -> #REF!
A42: BOARS | C42: ='[16]Pigs Cost'!$T42 -> 0.013277874 | J42: 0 | M42: =SUM(C42:L42) -> 0.013277874 | N42: =M42/'Summary Total Pigs'!#REF! -> #REF! | O42: ='Summary Total Pigs'!N55*'Pigs Cost'!N42 -> #REF! | P42: =N42*'Summary Total Pigs'!#REF! -> #REF! | Q42: ='Summary Total Pigs'!W55*'Pigs Cost'!N42 -> #REF! | R42: ='Summary Total Pigs'!X55*'Pigs Cost'!N42 -> #REF! | S42: ='Summary Total Pigs'!AD55*'Pigs Cost'!N42 -> #REF! | T42: =M42+O42+P42+R42+S42+Q42 -> #REF! | V42: =[17]Sheet1!$Q168
A43: TOTAL | C43: =SUM(C37:C42) -> 3.1054239e+09 | D43: =SUM(D37:D42) -> 0 | E43: =SUM(E37:E42) -> #REF! | F43: =SUM(F37:F42) -> #REF! | G43: =SUM(G37:G42) -> 0 | H43: =SUM(H37:H42) -> 0 | I43: =SUM(I37:I42) -> 0 | J43: =SUM(J37:J42) -> 5700000000000 | ... T43: =SUM(T37:T42) -> #REF! | V43: =SUM(V37:V42) -> 34635585 | W43: =T43-V43 -> #REF!
J44: =J43-H174 -> 0 | P44: 0 | V44: =C44/$B$178 -> 0
L45: =+(G43+H43+I43+K43+L43+J43)-H178 -> 0 | V45: =C45/$B$178 -> 0
V46: =C46/$B$178 -> 0
V47: =C47/$B$178 -> 0
V48: =C48/$B$178 -> 0
A49: SITE: | B49: ROGATE | V49: =C49/$B$178 -> 0
V50: =C50/$B$178 -> 0
A51: DESCRIPTION | B51: SITE | C51: =+C36 -> OPENING | D51: PIG PURCHASES | E51: TRANSFER IN | F51: A I CONSUMMABLES | G51: BEDDING AND CONSUMMABLES | H51: CONSULTANCY FEES | I51: DIRECT STAFF COSTS | J51: STOCK FEED | K51: SUNDRY TOOLS | L51: VETERINARY | M51: TOTAL COST | N51: AVERAGE COST | O51: TRANSFER OUT | P51: SALES | Q51: =Q36 -> Deaths | R51: =R36 -> CULLS | S51: =+S36 -> STOCK ADJMNT | T51: CLOSING
A52: PIGLETS | B52: MAIN | C52: ='[16]Pigs Cost'!$T52 -> 1.7388984e+10 | E52: ='Summary Total Pigs'!D89*'Pigs Cost'!N37 -> #REF! | G52: =('Summary Total Pigs'!$AE$89+'Summary Total Pigs'!$AE$93)/'Summary Total Pigs'!$AE$95*'Pigs Cost'!$H$171 -> 0 | H52: =('Summary Total Pigs'!$AE$89+'Summary Total Pigs'!$AE$93)/'Summary Total Pigs'!$AE$95*'Pigs Cost'!$K$172 -> 0 | I52: =('Summary Total Pigs'!$AE$89+'Summary Total Pigs'!$AE$93)/'Summary Total Pigs'!$AE$95*'Pigs Cost'!$K$173 -> 0 | J52: =('Summary Total Pigs'!AE89+'Summary Total Pigs'!AE92+'Summary Total Pigs'!AE93+'Summary Total Pigs'!AE94)/'Summary Total Pigs'!$AE$95*'Pigs Cost'!$K$174 -> 3.7202398e+12 | K52: =('Summary Total Pigs'!AE89)/'Summary Total Pigs'!$AE$95*'Pigs Cost'!$K$175 -> 0 | L52: =('Summary Total Pigs'!$AE$89+'Summary Total Pigs'!$AE$93)/'Summary Total Pigs'!$AE$95*'Pigs Cost'!$K$176 -> 0 | M52: =SUM(C52:L52) -> #REF! | N52: =M52/'Summary Total Pigs'!M89 -> #REF! | O52: ='Summary Total Pigs'!N89*'Pigs Cost'!N52 -> #REF! | P52: 0 | Q52: ='Summary Total Pigs'!#REF!*'Pigs Cost'!N52 -> #REF! | R52: =N52*'Summary Total Pigs'!Z89 -> #REF! | S52: ='Summary Total Pigs'!#REF!*'Pigs Cost'!N52 -> #REF! | T52: =M52+O52+P52+R52+S52+Q52 -> #REF! | V52: =[17]Sheet1!$M163 -> 68015894 | W52: =T52-V52 -> #REF!
A53: WEANERS | B53: WEANER | C53: ='[16]Pigs Cost'!$T53 -> 3.8118878e+09 | E53: ='Summary Total Pigs'!D90*N52 -> #REF! | G53: =('Summary Total Pigs'!AE90)/'Summary Total Pigs'!$AE$95*'Pigs Cost'!$H$171 -> 0 | H53: =('Summary Total Pigs'!AE90)/'Summary Total Pigs'!$AE$95*'Pigs Cost'!$K$172 -> 0 | I53: =('Summary Total Pigs'!AE90)/'Summary Total Pigs'!$AE$95*'Pigs Cost'!$K$173 -> 0 | J53: =('Summary Total Pigs'!AE90)/'Summary Total Pigs'!$AE$95*'Pigs Cost'!$K$174 -> 2.3306964e+12 | K53: =('Summary Total Pigs'!$AE$90)/'Summary Total Pigs'!$AE$95*'Pigs Cost'!$K$175 -> 0 | L53: =('Summary Total Pigs'!AE90)/'Summary Total Pigs'!$AE$95*'Pigs Cost'!$K$175 -> 0 | M53: =SUM(C53:L53) -> #REF! | N53: =M53/'Summary Total Pigs'!M90 -> #REF! | O53: ='Summary Total Pigs'!N90*'Pigs Cost'!N53 -> #REF! | P53: 0 | Q53: ='Summary Total Pigs'!#REF!*'Pigs Cost'!N53 -> #REF! | R53: =N53*'Summary Total Pigs'!Z90 -> #REF! | S53: ='Summary Total Pigs'!#REF!*'Pigs Cost'!N53 -> #REF! | T53: =M53+O53+P53+R53+S53+Q53 -> #REF! | V53: =[17]Sheet1!$M164 -> 14548831 | W53: =T53-V53 -> #REF!
A54: GROWERS | B54: GROWER | C54: ='[16]Pigs Cost'!$T54 -> 1.2994808e+10 | E54: ='Summary Total Pigs'!D91*N77 -> #REF! | G54: =('Summary Total Pigs'!AE91)/'Summary Total Pigs'!$AE$95*'Pigs Cost'!$H$171 -> 0 | H54: =('Summary Total Pigs'!AE91)/'Summary Total Pigs'!$AE$95*'Pigs Cost'!$K$172 -> 0 | I54: =('Summary Total Pigs'!AE91)/'Summary Total Pigs'!$AE$95*'Pigs Cost'!$K$173 -> 0 | J54: =('Summary Total Pigs'!AE91)/'Summary Total Pigs'!$AE$95*'Pigs Cost'!$K$174 -> 5.0490637e+12 | K54: =('Summary Total Pigs'!AE91)/'Summary Total Pigs'!$AE$95*'Pigs Cost'!$K$175 -> 0 | L54: =('Summary Total Pigs'!AE91)/'Summary Total Pigs'!$AE$95*'Pigs Cost'!$K$175 -> 0 | M54: =SUM(C54:L54) -> #REF! | N54: =M54/'Summary Total Pigs'!M91 -> #REF! | O54: ='Summary Total Pigs'!N94*'Pigs Cost'!N54 -> #REF! | P54: ='Summary Total Pigs'!#REF!*'Pigs Cost'!N54 -> #REF! | Q54: ='Summary Total Pigs'!#REF!*'Pigs Cost'!N54 -> #REF! | R54: =N54*'Summary Total Pigs'!Z91 -> #REF! | S54: ='Summary Total Pigs'!#REF!*'Pigs Cost'!N54 -> #REF! | T54: =M54+O54+P54+R54+S54+Q54 -> #REF! | V54: =[17]Sheet1!$M165 -> 30993128 | W54: =T54-V54 -> #REF!
A55: GILTS | B55: MAIN | C55: ='[16]Pigs Cost'!$T55 -> 1.1397226e+08 | E55: =15*N54+10*N15 -> #REF! | G55: =('Summary Total Pigs'!AE92)/'Summary Total Pigs'!$AE$95*'Pigs Cost'!$K$171 -> 0 | H55: =('Summary Total Pigs'!AE92)/'Summary Total Pigs'!$AE$95*'Pigs Cost'!$K$172 -> 0 | I55: =('Summary Total Pigs'!AE92)/'Summary Total Pigs'!$AE$95*'Pigs Cost'!$K$173 -> 0 | J55: 0 | K55: =('Summary Total Pigs'!AE92)/'Summary Total Pigs'!$AE$95*'Pigs Cost'!$K$175 -> 0 | L55: =('Summary Total Pigs'!AE92)/'Summary Total Pigs'!$AE$95*'Pigs Cost'!$K$176 -> 0 | M55: =SUM(C55:L55) -> #REF! | N55: =M55/'Summary Total Pigs'!M92 -> #REF! | O55: ='Summary Total Pigs'!N92*'Pigs Cost'!N55 -> #REF! | P55: ='Summary Total Pigs'!#REF!*'Pigs Cost'!N55 -> #REF! | Q55: ='Summary Total Pigs'!#REF!*'Pigs Cost'!N55 -> #REF! | R55: =N55*'Summary Total Pigs'!Z92 -> #REF! | S55: ='Summary Total Pigs'!#REF!*'Pigs Cost'!N55 -> #REF! | T55: =M55+O55+P55+R55+S55+Q55 -> #REF! | V55: =[17]Sheet1!$M166 -> 4227.98 | W55: =T55-V55 -> #REF!
A56: SOWS | B56: MAIN | C56: ='[16]Pigs Cost'!$T56 -> 1.4429877e+09 | E56: =N55*'Summary Total Pigs'!D93 -> #REF! | H56: =('Summary Total Pigs'!AE93)/'Summary Total Pigs'!$AE$95*'Pigs Cost'!$H$171 -> 0 | J56: 0 | K56: =('Summary Total Pigs'!AE93)/'Summary Total Pigs'!$AE$95*'Pigs Cost'!$K$175 -> 0 | L56: =('Summary Total Pigs'!AE93)/'Summary Total Pigs'!$AE$95*'Pigs Cost'!$K$176 -> 0 | M56: =SUM(C56:L56) -> #REF! | N56: =M56/'Summary Total Pigs'!M93 -> #REF! | O56: ='Summary Total Pigs'!N93*'Pigs Cost'!N56 -> #REF! | P56: ='Summary Total Pigs'!#REF!*'Pigs Cost'!N56 -> #REF! | Q56: ='Summary Total Pigs'!#REF!*'Pigs Cost'!N56 -> #REF! | R56: =N56*'Summary Total Pigs'!Z93 -> #REF! | S56: ='Summary Total Pigs'!#REF!*'Pigs Cost'!N56 -> #REF! | T56: =M56+O56+P56+R56+S56+Q56 -> #REF! | V56: =[17]Sheet1!$M167 -> 26148.64 | W56: =T56-V56 -> #REF!
A57: BOARS | C57: ='[16]Pigs Cost'!$T57 -> 0.074705426 | E57: ='Summary Total Pigs'!D94*'Pigs Cost'!N56 -> #REF! | J57: 0 | M57: =SUM(C57:L57) -> #REF! | N57: =M57/'Summary Total Pigs'!M94 -> #REF! | O57: ='Summary Total Pigs'!#REF!*'Pigs Cost'!N57 -> #REF! | P57: ='Summary Total Pigs'!#REF!*'Pigs Cost'!N57 -> #REF! | Q57: ='Summary Total Pigs'!#REF!*'Pigs Cost'!N57 -> #REF! | R57: =N57*'Summary Total Pigs'!Z94 -> #REF! | S57: ='Summary Total Pigs'!#REF!*'Pigs Cost'!N57 -> #REF! | T57: =M57+O57+P57+R57+S57+Q57 -> #REF! | V57: =[17]Sheet1!$M168 -> 0.08 | W57: =T57-V57 -> #REF!
A58: TOTAL | C58: =SUM(C52:C57) -> 3.575264e+10 | D58: =SUM(D52:D57) -> 0 | E58: =SUM(E52:E57) -> #REF! | F58: =SUM(F52:F57) -> 0 | G58: =SUM(G52:G57) -> 0 | H58: =SUM(H52:H57) -> 0 | I58: =SUM(I52:I57) -> 0 | J58: =SUM(J52:J57) -> 11100000000000 | ... T58: =SUM(T52:T57) -> #REF! | V58: =SUM(V52:V57) -> 1.1358823e+08 | W58: =SUM(W52:W57) -> #REF!
E59: =E58+O58 -> #REF! | J59: =J58-K174 -> 0 | V59: =C59/$B$178 -> 0
A60: SITE: | B60: QUARANTINE | M60: =10*N54 -> #REF! | V60: =C60/$B$178 -> 0
V61: =C61/$B$178 -> 0
A62: DESCRIPTION | B62: SITE | C62: =C51 -> OPENING | D62: PIG PURCHASES | E62: TRANSFER IN | F62: A I CONSUMMABLES | G62: BEDDING AND CONSUMMABLES | H62: CONSULTANCY FEES | I62: DIRECT STAFF COSTS | J62: STOCK FEED | K62: SUNDRY TOOLS | L62: VETERINARY | M62: TOTAL COST | N62: AVERAGE COST | O62: TRANSFER OUT | P62: SALES | Q62: =Q51 -> Deaths | R62: =R51 -> CULLS | S62: =+S51 -> STOCK ADJMNT | T62: CLOSING
A63: PIGLETS | B63: MAIN | C63: ='[16]Pigs Cost'!$T63 -> 0 | E63: ='Summary Total Pigs'!D130*N61 -> 0 | J63: 0 | M63: =SUM(C63:L63) -> 0 | O63: ='Summary Total Pigs'!Q127*'Pigs Cost'!N63 -> 0 | P63: =N63*'Summary Total Pigs'!Z127 -> 0 | Q63: =N63*'Summary Total Pigs'!AB127 -> 0 | R63: ='Summary Total Pigs'!AD127*'Pigs Cost'!N63 -> 0 | S63: ='Summary Total Pigs'!AG127*'Pigs Cost'!N63 -> 0 | T63: =M63+O63+P63+R63+S63+Q63 -> 0 | V63: =C63/$B$178 -> 0
A64: WEANERS | B64: WEANER | C64: ='[16]Pigs Cost'!$T64 -> 0 | E64: 0 | J64: 0 | M64: =SUM(C64:L64) -> 0 | O64: ='Summary Total Pigs'!Q128*'Pigs Cost'!N64 -> 0 | P64: =N64*'Summary Total Pigs'!Z128 -> 0 | Q64: =N64*'Summary Total Pigs'!AB128 -> 0 | R64: ='Summary Total Pigs'!AD128*'Pigs Cost'!N64 -> 0 | S64: ='Summary Total Pigs'!AG128*'Pigs Cost'!N64 -> 0 | T64: =M64+O64+P64+R64+S64+Q64 -> 0 | V64: =C64/$B$178 -> 0
A65: GROWERS | B65: GROWER | C65: ='[16]Pigs Cost'!$T65 -> 0 | E65: 0 | J65: 0 | M65: =SUM(C65:L65) -> 0 | O65: ='Summary Total Pigs'!Q129*'Pigs Cost'!N65 -> 0 | P65: =N65*'Summary Total Pigs'!Z129 -> 0 | Q65: =N65*'Summary Total Pigs'!AB129 -> 0 | R65: ='Summary Total Pigs'!AD129*'Pigs Cost'!N65 -> 0 | S65: ='Summary Total Pigs'!AG129*'Pigs Cost'!N65 -> 0 | T65: =M65+O65+P65+R65+S65+Q65 -> 0 | V65: =C65/$B$178 -> 0
A66: GILTS | B66: MAIN | C66: ='[16]Pigs Cost'!$T66 -> 1322329.6 | E66: ='Summary Total Pigs'!D130*'Pigs Cost'!N15 -> #REF! | J66: =('Summary Total Pigs'!#REF!)/'Summary Total Pigs'!#REF!*I174 -> #REF! | M66: =SUM(C66:L66) -> #REF! | N66: =+M66/'Summary Total Pigs'!P130 -> #REF! | O66: ='Summary Total Pigs'!Q130*'Pigs Cost'!N66 -> #REF! | P66: =N66*'Summary Total Pigs'!Z130 -> #REF! | Q66: =N66*'Summary Total Pigs'!AB130 -> #REF! | R66: ='Summary Total Pigs'!AD130*'Pigs Cost'!N66 -> #REF! | S66: ='Summary Total Pigs'!AG130*'Pigs Cost'!N66 -> #REF! | T66: =M66+O66+P66+R66+S66+Q66 -> #REF! | V66: =[17]Sheet1!$L166 -> 1322329.6 | W66: =T66-V66 -> #REF!
A67: SOWS | B67: MAIN | C67: ='[16]Pigs Cost'!$T67 -> 0 | E67: 0 | J67: 0 | M67: =SUM(C67:L67) -> 0 | N67: 0 | O67: ='Summary Total Pigs'!Q131*'Pigs Cost'!N67 -> 0 | P67: =N67*'Summary Total Pigs'!Z131 -> 0 | Q67: =N67*'Summary Total Pigs'!AB131 -> 0 | R67: ='Summary Total Pigs'!AD131*'Pigs Cost'!N67 -> 0 | S67: ='Summary Total Pigs'!AG131*'Pigs Cost'!N67 -> 0 | T67: =M67+O67+P67+R67+S67+Q67 -> 0 | V67: =[17]Sheet1!$L167
A68: BOARS | C68: ='[16]Pigs Cost'!$T68 -> 0.12848784 | E68: ='Summary Total Pigs'!D132*N18 -> #REF! | J68: 0 | M68: =SUM(C68:L68) -> #REF! | N68: 0 | O68: ='Summary Total Pigs'!Q132*'Pigs Cost'!N68 -> 0 | P68: =N68*'Summary Total Pigs'!Z132 -> 0 | Q68: =N68*'Summary Total Pigs'!AB132 -> 0 | R68: ='Summary Total Pigs'!AD132*'Pigs Cost'!N68 -> 0 | S68: ='Summary Total Pigs'!AG132*'Pigs Cost'!N68 -> 0 | T68: =M68+O68+P68+R68+S68+Q68 -> #REF! | V68: =[17]Sheet1!$L168 -> 0.13 | W68: =T68-V68 -> #REF!
A69: TOTAL | C69: =SUM(C63:C68) -> 1322329.8 | D69: =SUM(D63:D68) -> 0 | E69: =SUM(E63:E68) -> #REF! | F69: =SUM(F63:F68) -> 0 | G69: =SUM(G63:G68) -> 0 | H69: =SUM(H63:H68) -> 0 | I69: =SUM(I63:I68) -> 0 | J69: =SUM(J63:J68) -> #REF! | ... T69: =SUM(T63:T68) -> #REF! | V69: =SUM(V63:V68) -> 1322329.8
J70: =J69-I174 -> #REF! | V70: =C70/$B$178 -> 0
L71: =+(G69+H69+I69+K69+L69+J69)-I178 -> #REF! | V71: =C71/$B$178 -> 0
A72: SITE: | B72: OSWA | L72: =+(G70+H70+I70+K70+L70+J70)-K190 -> #REF! | V72: =C72/$B$178 -> 0
V73: =C73/$B$178 -> 0
A74: DESCRIPTION | B74: SITE | C74: =+C62 -> OPENING | D74: PIG PURCHASES | E74: TRANSFER IN | F74: A I CONSUMMABLES | G74: BEDDING AND CONSUMMABLES | H74: CONSULTANCY FEES | I74: DIRECT STAFF COSTS | J74: STOCK FEED | K74: SUNDRY TOOLS | L74: VETERINARY | M74: TOTAL COST | N74: AVERAGE COST | O74: TRANSFER OUT | P74: SALES | Q74: =Q62 -> Deaths | R74: =R62 -> CULLS | S74: =+S62 -> STOCK ADJMNT | T74: CLOSING
A75: PIGLETS | B75: MAIN | C75: ='[16]Pigs Cost'!$T75 -> 3.2710113e+10 | E75: ='Summary Total Pigs'!#REF!*N73 -> #REF! | J75: =('Summary Total Pigs'!#REF!+'Summary Total Pigs'!#REF!+'Summary Total Pigs'!#REF!+'Summary Total Pigs'!#REF!)/'Summary Total Pigs'!#REF!*'Pigs Cost'!$L$174 -> #REF! | K75: =('Summary Total Pigs'!#REF!/'Summary Total Pigs'!#REF!)*'Pigs Cost'!$L$175 -> #REF! | M75: =SUM(C75:L75) -> #REF! | N75: =+M75/'Summary Total Pigs'!#REF! -> #REF! | O75: =N75*'Summary Total Pigs'!#REF! -> #REF! | P75: =N75*'Summary Total Pigs'!#REF! -> #REF! | Q75: ='Summary Total Pigs'!#REF!*'Pigs Cost'!N75 -> #REF! | R75: =N75*'Summary Total Pigs'!#REF! -> #REF! | S75: ='Summary Total Pigs'!#REF!*'Pigs Cost'!N75 -> #REF! | T75: =M75+O75+P75+R75+S75+Q75 -> #REF! | V75: =[17]Sheet1!$K163 -> 67797061 | W75: =T75-V75 -> #REF!
A76: WEANERS | B76: WEANER | C76: ='[16]Pigs Cost'!$T76 -> 1.3394549e+10 | E76: =+'Summary Total Pigs'!#REF!*'Pigs Cost'!N75 -> #REF! | J76: =('Summary Total Pigs'!#REF!)/'Summary Total Pigs'!#REF!*'Pigs Cost'!$L$174 -> #REF! | K76: =('Summary Total Pigs'!#REF!/'Summary Total Pigs'!#REF!)*'Pigs Cost'!$L$175 -> #REF! | M76: =SUM(C76:L76) -> #REF! | N76: =+M76/'Summary Total Pigs'!#REF! -> #REF! | O76: =N76*'Summary Total Pigs'!#REF! -> #REF! | P76: =N76*'Summary Total Pigs'!#REF! -> #REF! | Q76: ='Summary Total Pigs'!#REF!*'Pigs Cost'!N76 -> #REF! | R76: =N76*'Summary Total Pigs'!#REF! -> #REF! | S76: ='Summary Total Pigs'!#REF!*'Pigs Cost'!N76 -> #REF! | T76: =M76+O76+P76+R76+S76+Q76 -> #REF! | V76: =[17]Sheet1!$K164 -> 99474250 | W76: =T76-V76 -> #REF!
A77: GROWERS | B77: GROWER | C77: ='[16]Pigs Cost'!$T77 -> 1.7133034e+08 | E77: =+'Summary Total Pigs'!#REF!*'Pigs Cost'!N76 -> #REF! | J77: =('Summary Total Pigs'!#REF!)/'Summary Total Pigs'!#REF!*'Pigs Cost'!$L$174 -> #REF! | K77: =('Summary Total Pigs'!#REF!/'Summary Total Pigs'!#REF!)*'Pigs Cost'!$L$175 -> #REF! | M77: =SUM(C77:L77) -> #REF! | N77: =+M77/'Summary Total Pigs'!#REF! -> #REF! | O77: =N77*'Summary Total Pigs'!#REF! -> #REF! | P77: =N77*'Summary Total Pigs'!#REF! -> #REF! | Q77: ='Summary Total Pigs'!#REF!*'Pigs Cost'!N77 -> #REF! | R77: =N77*'Summary Total Pigs'!#REF! -> #REF! | S77: ='Summary Total Pigs'!#REF!*'Pigs Cost'!N77 -> #REF! | T77: =M77+O77+P77+R77+S77+Q77 -> #REF! | V77: =[17]Sheet1!$K165 -> 1.9480323e+08 | W77: =T77-V77 -> #REF!
A78: GILTS | B78: MAIN | C78: ='[16]Pigs Cost'!$T78 -> 0 | E78: =+'Summary Total Pigs'!#REF!*'Pigs Cost'!N77 -> #REF! | J78: 0 | K78: =('Summary Total Pigs'!#REF!/'Summary Total Pigs'!#REF!)*'Pigs Cost'!$L$175 -> #REF! | M78: =SUM(C78:L78) -> #REF! | O78: =N78*'Summary Total Pigs'!#REF! -> #REF! | Q78: ='Summary Total Pigs'!#REF!*'Pigs Cost'!N78 -> #REF! | R78: =N78*'Summary Total Pigs'!#REF! -> #REF! | S78: ='Summary Total Pigs'!#REF!*'Pigs Cost'!N78 -> #REF! | T78: =M78+O78+P78+R78+S78+Q78 -> #REF! | V78: =[17]Sheet1!$K166
A79: SOWS | B79: MAIN | C79: ='[16]Pigs Cost'!$T79 -> 80.838477 | E79: =+'Summary Total Pigs'!#REF!*N56 -> #REF! | J79: 0 | K79: =('Summary Total Pigs'!#REF!/'Summary Total Pigs'!#REF!)*'Pigs Cost'!$L$175 -> #REF! | M79: =SUM(C79:L79) -> #REF! | N79: =+M79/'Summary Total Pigs'!#REF! -> #REF! | O79: =N79*'Summary Total Pigs'!#REF! -> #REF! | P79: ='Summary Total Pigs'!#REF!*'Pigs Cost'!N79 -> #REF! | Q79: ='Summary Total Pigs'!#REF!*'Pigs Cost'!N79 -> #REF! | R79: =N79*'Summary Total Pigs'!#REF! -> #REF! | S79: ='Summary Total Pigs'!#REF!*'Pigs Cost'!N79 -> #REF! | T79: =M79+O79+P79+R79+S79+Q79 -> #REF! | V79: =[17]Sheet1!$K167 -> 178.67 | W79: =T79-V79 -> #REF!
A80: BOARS | C80: ='[16]Pigs Cost'!$T80 -> 0.40728137 | J80: 0 | K80: =('Summary Total Pigs'!#REF!/'Summary Total Pigs'!#REF!)*'Pigs Cost'!$L$175 -> #REF! | M80: =SUM(C80:L80) -> #REF! | N80: =+M80/'Summary Total Pigs'!#REF! -> #REF! | O80: =N80*'Summary Total Pigs'!#REF! -> #REF! | Q80: ='Summary Total Pigs'!#REF!*'Pigs Cost'!N80 -> #REF! | R80: =N80*'Summary Total Pigs'!#REF! -> #REF! | S80: ='Summary Total Pigs'!#REF!*'Pigs Cost'!N80 -> #REF! | T80: =M80+O80+P80+R80+S80+Q80 -> #REF! | V80: =[17]Sheet1!$K168 -> 0.54 | W80: =T80-V80 -> #REF!
A81: TOTAL | C81: =SUM(C75:C80) -> 4.6275992e+10 | D81: =SUM(D75:D80) -> 0 | E81: =SUM(E75:E80) -> #REF! | F81: =SUM(F75:F80) -> 0 | G81: =SUM(G75:G80) -> 0 | H81: =SUM(H75:H80) -> 0 | I81: =SUM(I75:I80) -> 0 | J81: =SUM(J75:J80) -> #REF! | ... T81: =SUM(T75:T80) -> #REF! | V81: =SUM(V75:V80) -> 3.6207472e+08 | W81: =T81-V81 -> #REF!
J82: =J81-L174 -> #REF! | K82: =K81-L175 -> #REF! | V82: =C82/$B$178 -> 0
V83: =C83/$B$178 -> 0
A84: SITE: | B84: UMFULI BANKS | D84: =240*N100 -> #REF! | L84: =+(G82+H82+I82+K82+L82+J82)-K202 -> #REF! | O84: =O89/N89 -> #REF! | V84: =C84/$B$178 -> 0
V85: =C85/$B$178 -> 0
A86: DESCRIPTION | B86: SITE | C86: =+C74 -> OPENING | D86: PIG PURCHASES | E86: TRANSFER IN | F86: A I CONSUMMABLES | G86: BEDDING AND CONSUMMABLES | H86: CONSULTANCY FEES | I86: DIRECT STAFF COSTS | J86: STOCK FEED | K86: SUNDRY TOOLS | L86: VETERINARY | M86: TOTAL COST | N86: AVERAGE COST | O86: TRANSFER OUT | P86: SALES | Q86: =Q74 -> Deaths | R86: =R74 -> CULLS | S86: =+S74 -> STOCK ADJMNT | T86: CLOSING
A87: PIGLETS | B87: MAIN | C87: ='[16]Pigs Cost'!$T87 -> 0 | J87: =('Summary Total Pigs'!#REF!)/'Summary Total Pigs'!#REF!*'Pigs Cost'!$O$174 -> #REF! | M87: =SUM(C87:L87) -> #REF! | N87: 0 | O87: =N87*'Summary Total Pigs'!#REF! -> #REF! | P87: =N87*'Summary Total Pigs'!#REF! -> #REF! | Q87: ='Summary Total Pigs'!#REF!*'Pigs Cost'!N87 -> #REF! | R87: =N87*'Summary Total Pigs'!#REF! -> #REF! | S87: ='Summary Total Pigs'!#REF!*'Pigs Cost'!N87 -> #REF! | T87: =M87+O87+P87+R87+S87+Q87 -> #REF! | V87: =[17]Sheet1!$P163
A88: WEANERS | B88: WEANER | C88: ='[16]Pigs Cost'!$T88 -> 0 | J88: =('Summary Total Pigs'!#REF!)/'Summary Total Pigs'!#REF!*'Pigs Cost'!$O$174 -> #REF! | M88: =SUM(C88:L88) -> #REF! | N88: 0 | O88: =N88*'Summary Total Pigs'!#REF! -> #REF! | P88: =N88*'Summary Total Pigs'!#REF! -> #REF! | Q88: ='Summary Total Pigs'!#REF!*'Pigs Cost'!N88 -> #REF! | R88: =N88*'Summary Total Pigs'!#REF! -> #REF! | S88: ='Summary Total Pigs'!#REF!*'Pigs Cost'!N88 -> #REF! | T88: =M88+O88+P88+R88+S88+Q88 -> #REF! | V88: =[17]Sheet1!$P164 -> 0 | W88: =T88-V88 -> #REF!
A89: GROWERS | B89: GROWER | C89: ='[16]Pigs Cost'!$T89 -> 2.4631157e+10 | E89: ='Summary Total Pigs'!#REF!*N101 -> #REF! | J89: =('Summary Total Pigs'!#REF!)/'Summary Total Pigs'!#REF!*'Pigs Cost'!$O$174 -> #REF! | M89: =SUM(C89:L89) -> #REF! | N89: =M89/'Summary Total Pigs'!#REF! -> #REF! | O89: =N89*'Summary Total Pigs'!#REF! -> #REF! | P89: =N89*'Summary Total Pigs'!#REF! -> #REF! | Q89: ='Summary Total Pigs'!#REF!*'Pigs Cost'!N89 -> #REF! | R89: =N89*'Summary Total Pigs'!#REF! -> #REF! | S89: ='Summary Total Pigs'!#REF!*'Pigs Cost'!N89 -> #REF! | T89: =M89+O89+P89+R89+S89+Q89 -> #REF! | V89: =[17]Sheet1!$P165 -> 80264139 | W89: =T89-V89 -> #REF!
A90: GILTS | B90: MAIN | C90: ='[16]Pigs Cost'!$T90 -> 0 | J90: =('Summary Total Pigs'!#REF!)/'Summary Total Pigs'!#REF!*'Pigs Cost'!$O$174 -> #REF! | M90: =SUM(C90:L90) -> #REF! | O90: =N90*'Summary Total Pigs'!#REF! -> #REF! | P90: =N90*'Summary Total Pigs'!#REF! -> #REF! | Q90: ='Summary Total Pigs'!#REF!*'Pigs Cost'!N90 -> #REF! | R90: =N90*'Summary Total Pigs'!#REF! -> #REF! | S90: ='Summary Total Pigs'!#REF!*'Pigs Cost'!N90 -> #REF! | T90: =M90+O90+P90+R90+S90+Q90 -> #REF! | V90: =[17]Sheet1!$P166
A91: SOWS | B91: MAIN | C91: ='[16]Pigs Cost'!$T91 -> 0 | J91: =('Summary Total Pigs'!#REF!)/'Summary Total Pigs'!#REF!*'Pigs Cost'!$O$174 -> #REF! | M91: =SUM(C91:L91) -> #REF! | O91: =N91*'Summary Total Pigs'!#REF! -> #REF! | P91: =N91*'Summary Total Pigs'!#REF! -> #REF! | Q91: ='Summary Total Pigs'!#REF!*'Pigs Cost'!N91 -> #REF! | R91: =N91*'Summary Total Pigs'!#REF! -> #REF! | S91: ='Summary Total Pigs'!#REF!*'Pigs Cost'!N91 -> #REF! | T91: =M91+O91+P91+R91+S91+Q91 -> #REF! | V91: =[17]Sheet1!$P167
A92: BOARS | C92: ='[16]Pigs Cost'!$T92 -> 0 | J92: =('Summary Total Pigs'!#REF!)/'Summary Total Pigs'!#REF!*'Pigs Cost'!$O$174 -> #REF! | M92: =SUM(C92:L92) -> #REF! | O92: =N92*'Summary Total Pigs'!#REF! -> #REF! | P92: =N92*'Summary Total Pigs'!#REF! -> #REF! | Q92: ='Summary Total Pigs'!#REF!*'Pigs Cost'!N92 -> #REF! | R92: =N92*'Summary Total Pigs'!#REF! -> #REF! | S92: ='Summary Total Pigs'!#REF!*'Pigs Cost'!N92 -> #REF! | T92: =M92+O92+P92+R92+S92+Q92 -> #REF! | V92: =[17]Sheet1!$P168
A93: TOTAL | C93: =SUM(C87:C92) -> 2.4631157e+10 | D93: =SUM(D87:D92) -> 0 | E93: =SUM(E87:E92) -> #REF! | F93: =SUM(F87:F92) -> 0 | G93: =SUM(G87:G92) -> 0 | H93: =SUM(H87:H92) -> 0 | I93: =SUM(I87:I92) -> 0 | J93: =SUM(J87:J92) -> #REF! | ... T93: =SUM(T87:T92) -> #REF! | V93: =SUM(V87:V92) -> 80264139 | W93: =T93-V93 -> #REF!
J94: =J93-O174 -> #REF! | V94: =C94/$B$178 -> 0
S95: =+S93+'IAS 41 Mvmnt Pigs'!K93 -> #REF! | V95: =C95/$B$178 -> 0
A96: SITE: | B96: SEAFORTH FARM | L96: =+(G94+H94+I94+K94+L94+J94)-K214 -> #REF! | V96: =C96/$B$178 -> 0
V97: =C97/$B$178 -> 0
A98: DESCRIPTION | B98: SITE | C98: =+C86 -> OPENING | D98: PIG PURCHASES | E98: TRANSFER IN | F98: A I CONSUMMABLES | G98: BEDDING AND CONSUMMABLES | H98: CONSULTANCY FEES | I98: DIRECT STAFF COSTS | J98: STOCK FEED | K98: SUNDRY TOOLS | L98: VETERINARY | M98: TOTAL COST | N98: AVERAGE COST | O98: TRANSFER OUT | P98: SALES | Q98: =Q86 -> Deaths | R98: =R86 -> CULLS | S98: =+S86 -> STOCK ADJMNT | T98: CLOSING
A99: PIGLETS | B99: MAIN | C99: ='[16]Pigs Cost'!$T99 -> 0 | E99: ='Summary Total Pigs'!#REF!*'Pigs Cost'!N37 -> #REF! | J99: =('Summary Total Pigs'!#REF!/'Summary Total Pigs'!#REF!)*'Pigs Cost'!$P$174 -> #REF! | M99: =SUM(C99:L99) -> #REF! | O99: =N99*'Summary Total Pigs'!#REF! -> #REF! | P99: =N99*'Summary Total Pigs'!#REF! -> #REF! | Q99: ='Summary Total Pigs'!#REF!*'Pigs Cost'!N99 -> #REF! | R99: =N99*'Summary Total Pigs'!#REF! -> #REF! | S99: 0 | T99: =M99+O99+P99+R99+S99+Q99 -> #REF! | V99: =[17]Sheet1!$N163
A100: WEANERS | B100: WEANER | C100: ='[16]Pigs Cost'!$T100 -> 2.4683772e+10 | E100: =(603*N37)+(489*N53) -> #REF! | J100: =('Summary Total Pigs'!#REF!/'Summary Total Pigs'!#REF!)*'Pigs Cost'!$P$174 -> #REF! | M100: =SUM(C100:L100) -> #REF! | N100: =M100/'Summary Total Pigs'!#REF! -> #REF! | O100: =N100*'Summary Total Pigs'!#REF! -> #REF! | P100: =N100*'Summary Total Pigs'!#REF! -> #REF! | Q100: ='Summary Total Pigs'!#REF!*'Pigs Cost'!N100 -> #REF! | R100: =N100*'Summary Total Pigs'!#REF! -> #REF! | S100: 0 | T100: =M100+O100+P100+R100+S100+Q100 -> #REF! | V100: =[17]Sheet1!$N164 -> 53571797 | W100: =T100-V100 -> #REF!
A101: GROWERS | B101: GROWER | C101: ='[16]Pigs Cost'!$T101 -> 1.3226807e+09 | E101: ='Summary Total Pigs'!#REF!*N100 -> #REF! | J101: =('Summary Total Pigs'!#REF!/'Summary Total Pigs'!#REF!)*'Pigs Cost'!$P$174 -> #REF! | M101: =SUM(C101:L101) -> #REF! | N101: =M101/'Summary Total Pigs'!#REF! -> #REF! | O101: =N101*'Summary Total Pigs'!#REF! -> #REF! | P101: =N101*'Summary Total Pigs'!#REF! -> #REF! | Q101: ='Summary Total Pigs'!#REF!*'Pigs Cost'!N101 -> #REF! | R101: =N101*'Summary Total Pigs'!#REF! -> #REF! | S101: ='Summary Total Pigs'!#REF!*'Pigs Cost'!N101 -> #REF! | T101: =M101+O101+P101+R101+S101+Q101 -> #REF! | V101: =[17]Sheet1!$N165 -> 13997083 | W101: =T101-V101 -> #REF!
A102: GILTS | B102: MAIN | C102: ='[16]Pigs Cost'!$T102 -> 0 | J102: =('Summary Total Pigs'!#REF!/'Summary Total Pigs'!#REF!)*'Pigs Cost'!$P$174 -> #REF! | M102: =SUM(C102:L102) -> #REF! | N102: 0 | O102: =N102*'Summary Total Pigs'!#REF! -> #REF! | P102: =N102*'Summary Total Pigs'!#REF! -> #REF! | Q102: ='Summary Total Pigs'!#REF!*'Pigs Cost'!N102 -> #REF! | R102: =N102*'Summary Total Pigs'!#REF! -> #REF! | S102: ='Summary Total Pigs'!#REF!*'Pigs Cost'!N102 -> #REF! | T102: =M102+O102+P102+R102+S102+Q102 -> #REF! | V102: =[17]Sheet1!$N166
A103: SOWS | B103: MAIN | C103: ='[16]Pigs Cost'!$T103 -> 0 | J103: =('Summary Total Pigs'!#REF!/'Summary Total Pigs'!#REF!)*'Pigs Cost'!$P$174 -> #REF! | M103: =SUM(C103:L103) -> #REF! | N103: 0 | O103: =N103*'Summary Total Pigs'!#REF! -> #REF! | P103: =N103*'Summary Total Pigs'!#REF! -> #REF! | Q103: ='Summary Total Pigs'!#REF!*'Pigs Cost'!N103 -> #REF! | R103: =N103*'Summary Total Pigs'!#REF! -> #REF! | S103: ='Summary Total Pigs'!#REF!*'Pigs Cost'!N103 -> #REF! | T103: =M103+O103+P103+R103+S103+Q103 -> #REF! | V103: =[17]Sheet1!$N167
A104: BOARS | C104: ='[16]Pigs Cost'!$T104 -> 0 | J104: =('Summary Total Pigs'!#REF!/'Summary Total Pigs'!#REF!)*'Pigs Cost'!$P$174 -> #REF! | M104: =SUM(C104:L104) -> #REF! | N104: 0 | O104: =N104*'Summary Total Pigs'!#REF! -> #REF! | P104: =N104*'Summary Total Pigs'!#REF! -> #REF! | Q104: ='Summary Total Pigs'!#REF!*'Pigs Cost'!N104 -> #REF! | R104: =N104*'Summary Total Pigs'!#REF! -> #REF! | S104: ='Summary Total Pigs'!#REF!*'Pigs Cost'!N104 -> #REF! | T104: =M104+O104+P104+R104+S104+Q104 -> #REF! | V104: =[17]Sheet1!$N168
A105: TOTAL | C105: =SUM(C99:C104) -> 2.6006453e+10 | D105: =SUM(D99:D104) -> 0 | E105: =SUM(E99:E104) -> #REF! | F105: =SUM(F99:F104) -> 0 | G105: =SUM(G99:G104) -> 0 | H105: =SUM(H99:H104) -> 0 | I105: =SUM(I99:I104) -> 0 | J105: =SUM(J99:J104) -> #REF! | ... T105: =SUM(T99:T104) -> #REF! | V105: =SUM(V100:V104) -> 67568880
...

Sheet IAS 41 Mvmnt Pigs
A1: COLCOM HOLDINGS LIMITED
L2: =+'Pigs Cost'!T2 -> 46226
A3: TRIPLE C PIGS
A5: LIVESTOCK ANALYSIS SCHEDULE
A8: IAS 41 MOVEMENT
A10: SITE: | B10: GRASMERE FARM
A12: DESCRIPTION | B12: SITE | C12: OPENING | D12: TRANSFER IN | E12: TOTAL COST | F12: AVERAGE COST | G12: TRANSFER OUT | H12: SALES | I12: ='Pigs Cost'!Q12 -> #REF! | J12: CULLS | K12: STOCK ADJMNT | L12: SUB TOTAL | M12: CURRENT ADJMNT | N12: CLOSING BAL | O12: CLOSING BAL
A13: PIGLETS | B13: MAIN | C13: ='[16]IAS 41 Mvmnt Pigs'!$N13 -> 1.2957317e+08 | E13: =SUM(C13:D13) -> 1.2957317e+08 | F13: =$E13/'Summary Total Pigs'!#REF! -> #REF! | G13: ='Summary Total Pigs'!#REF!*'IAS 41 Mvmnt Pigs'!F13 -> #REF! | H13: =$F13*'Summary Total Pigs'!$X12 -> #REF! | I13: ='Summary Total Pigs'!#REF!*'IAS 41 Mvmnt Pigs'!F13 -> #REF! | J13: =$F13*'Summary Total Pigs'!$Z12 -> #REF! | K13: ='Summary Total Pigs'!#REF!*'IAS 41 Mvmnt Pigs'!F13 -> #REF! | L13: =E13+G13+H13+J13+K13+I13 -> #REF! | M13: 0 | N13: =+L13+M13 -> #REF! | O13: =[17]Sheet1!$E169 -> 2.8784866e+08 | P13: =N13-O13 -> #REF!
A14: WEANERS | B14: WEANER | C14: ='[16]IAS 41 Mvmnt Pigs'!$N14 -> 2.1078684e+09 | D14: ='Summary Total Pigs'!D13*F13 -> #REF! | E14: =SUM(C14:D14) -> #REF! | F14: =$E14/'Summary Total Pigs'!#REF! -> #REF! | G14: ='Summary Total Pigs'!#REF!*'IAS 41 Mvmnt Pigs'!F14 -> #REF! | H14: =$F14*'Summary Total Pigs'!$X13 -> #REF! | I14: ='Summary Total Pigs'!#REF!*'IAS 41 Mvmnt Pigs'!F14 -> #REF! | J14: =$F14*'Summary Total Pigs'!$Z13 -> #REF! | K14: ='Summary Total Pigs'!#REF!*'IAS 41 Mvmnt Pigs'!F14 -> #REF! | L14: =E14+G14+H14+J14+K14+I14 -> #REF! | M14: 0 | N14: =+L14+M14 -> #REF! | O14: =[17]Sheet1!$E170 -> 4.040958e+09 | P14: =N14-O14 -> #REF!
A15: GROWERS | B15: GROWER | C15: ='[16]IAS 41 Mvmnt Pigs'!$N15 -> 8.4247275e+09 | D15: =3838*F14+19*F16 -> #REF! | E15: =SUM(C15:D15) -> #REF! | F15: =$E15/'Summary Total Pigs'!#REF! -> #REF! | G15: ='Summary Total Pigs'!#REF!*'IAS 41 Mvmnt Pigs'!F15 -> #REF! | H15: ='Summary Total Pigs'!X14*'IAS 41 Mvmnt Pigs'!F15 -> #REF! | I15: ='Summary Total Pigs'!#REF!*'IAS 41 Mvmnt Pigs'!F15 -> #REF! | J15: =$F15*'Summary Total Pigs'!$Z14 -> #REF! | K15: ='Summary Total Pigs'!#REF!*'IAS 41 Mvmnt Pigs'!F15 -> #REF! | L15: =E15+G15+H15+J15+K15+I15 -> #REF! | M15: 0 | N15: =+L15+M15 -> #REF! | O15: =[17]Sheet1!$E171 -> 1.0392149e+10 | P15: =N15-O15 -> #REF!
A16: GILTS | B16: MAIN | C16: ='[16]IAS 41 Mvmnt Pigs'!$N16 -> 9.3443108e+08 | D16: =F13*'Summary Total Pigs'!D15 -> #REF! | E16: =SUM(C16:D16) -> #REF! | F16: =$E16/'Summary Total Pigs'!#REF! -> #REF! | G16: ='Summary Total Pigs'!#REF!*'IAS 41 Mvmnt Pigs'!F16 -> #REF! | H16: =$F16*'Summary Total Pigs'!$X15 -> #REF! | I16: ='Summary Total Pigs'!#REF!*'IAS 41 Mvmnt Pigs'!F16 -> #REF! | J16: =$F16*'Summary Total Pigs'!$Z15 -> #REF! | K16: ='Summary Total Pigs'!#REF!*'IAS 41 Mvmnt Pigs'!F16 -> #REF! | L16: =E16+G16+H16+J16+K16+I16 -> #REF! | M16: 0 | N16: =+L16+M16 -> #REF! | O16: =[17]Sheet1!$E172 -> 1.1174234e+09 | P16: =N16-O16 -> #REF!
A17: SOWS | B17: MAIN | C17: ='[16]IAS 41 Mvmnt Pigs'!$N17 -> 2.024274e+09 | D17: =F16*'Summary Total Pigs'!D16 -> #REF! | E17: =SUM(C17:D17) -> #REF! | F17: =$E17/'Summary Total Pigs'!#REF! -> #REF! | G17: ='Summary Total Pigs'!#REF!*'IAS 41 Mvmnt Pigs'!F17 -> #REF! | H17: =$F17*'Summary Total Pigs'!$X16 -> #REF! | I17: ='Summary Total Pigs'!#REF!*'IAS 41 Mvmnt Pigs'!F17 -> #REF! | J17: =$F17*'Summary Total Pigs'!$Z16 -> #REF! | K17: ='Summary Total Pigs'!#REF!*'IAS 41 Mvmnt Pigs'!F17 -> #REF! | L17: =E17+G17+H17+J17+K17+I17 -> #REF! | M17: 0 | N17: =+L17+M17 -> #REF! | O17: =[17]Sheet1!$E173 -> 2.0925556e+09 | P17: =N17-O17 -> #REF!
A18: BOARS | B18: AI | C18: ='[16]IAS 41 Mvmnt Pigs'!$N18 -> 64762941 | D18: ='Summary Total Pigs'!D17*F15 -> #REF! | E18: =SUM(C18:D18) -> #REF! | F18: =$E18/'Summary Total Pigs'!#REF! -> #REF! | G18: ='Summary Total Pigs'!#REF!*'IAS 41 Mvmnt Pigs'!F18 -> #REF! | H18: =$F18*'Summary Total Pigs'!$X17 -> #REF! | I18: ='Summary Total Pigs'!#REF!*'IAS 41 Mvmnt Pigs'!F18 -> #REF! | J18: =$F18*'Summary Total Pigs'!$Z17 -> #REF! | K18: ='Summary Total Pigs'!#REF!*'IAS 41 Mvmnt Pigs'!F18 -> #REF! | L18: =E18+G18+H18+J18+K18+I18 -> #REF! | M18: 0 | N18: =+L18+M18 -> #REF! | O18: =[17]Sheet1!$E174 -> 64762941 | P18: =N18-O18 -> #REF!
A19: TOTAL | C19: =SUM(C13:C18) -> 1.3685637e+10 | D19: =SUM(D13:D18) -> #REF! | E19: =SUM(E13:E18) -> #REF! | F19: =SUM(F13:F18) -> #REF! | G19: =SUM(G13:G18) -> #REF! | H19: =SUM(H13:H18) -> #REF! | I19: =SUM(I13:I18) -> #REF! | J19: =SUM(J13:J18) -> #REF! | ... O19: =SUM(O13:O18) -> 1.7995697e+10 | P19: =N19-O19 -> #REF! | Q19: =[17]Sheet1!$E$16 -> -1.7992163e+10
D20: =D19+G19 -> #REF! | L20: =E19+G19+H19+J19+K19+I19 -> #REF! | Q20: =Q19+M19 -> -1.7992163e+10
L21: =+L19-L20 -> #REF!
A22: SITE: | B22: TRADE WINDS
A24: DESCRIPTION | B24: SITE | C24: OPENING | D24: TRANSFER IN | E24: TOTAL COST | F24: AVERAGE COST | G24: TRANSFER OUT | H24: SALES | I24: =I12 -> #REF! | J24: =J12 -> CULLS | K24: =+K12 -> STOCK ADJMNT | L24: SUB TOTAL | M24: =M12 -> CURRENT ADJMNT | N24: =+N12 -> CLOSING BAL | O24: CLOSING BAL
A25: PIGLETS | B25: MAIN | C25: ='[16]IAS 41 Mvmnt Pigs'!$N25 -> 0 | D25: ='Summary Total Pigs'!#REF!*M23 -> #REF! | E25: =SUM(C25:D25) -> #REF! | F25: 0 | G25: ='Summary Total Pigs'!#REF!*'IAS 41 Mvmnt Pigs'!F25 -> #REF! | H25: =F25*'Summary Total Pigs'!#REF! -> #REF! | I25: =F25*'Summary Total Pigs'!#REF! -> #REF! | J25: =F25*'Summary Total Pigs'!#REF! -> #REF! | K25: ='Summary Total Pigs'!#REF!*'IAS 41 Mvmnt Pigs'!F25 -> #REF! | L25: =E25+G25+H25+J25+K25+I25 -> #REF! | M25: 0 | N25: =+L25+M25 -> #REF! | O25: =[17]Sheet1!$O163
A26: WEANERS | B26: WEANER | C26: ='[16]IAS 41 Mvmnt Pigs'!$N26 -> 0 | D26: 0 | E26: =SUM(C26:D26) -> 0 | F26: 0 | G26: ='Summary Total Pigs'!#REF!*'IAS 41 Mvmnt Pigs'!F26 -> #REF! | H26: =F26*'Summary Total Pigs'!#REF! -> #REF! | I26: =F26*'Summary Total Pigs'!#REF! -> #REF! | J26: =F26*'Summary Total Pigs'!#REF! -> #REF! | K26: ='Summary Total Pigs'!#REF!*'IAS 41 Mvmnt Pigs'!F26 -> #REF! | L26: =E26+G26+H26+J26+K26+I26 -> #REF! | M26: 0 | N26: =+L26+M26 -> #REF! | O26: 0 | P26: =N26-O26 -> #REF!
A27: GROWERS | B27: GROWER | C27: ='[16]IAS 41 Mvmnt Pigs'!$N27 -> 3.8161986e+08 | D27: =F101*'Summary Total Pigs'!#REF! -> #REF! | E27: =SUM(C27:D27) -> #REF! | F27: =$E27/'Summary Total Pigs'!#REF! -> #REF! | G27: ='Summary Total Pigs'!#REF!*'IAS 41 Mvmnt Pigs'!F27 -> #REF! | H27: =F27*'Summary Total Pigs'!#REF! -> #REF! | I27: =F27*'Summary Total Pigs'!#REF! -> #REF! | J27: =F27*'Summary Total Pigs'!#REF! -> #REF! | K27: ='Summary Total Pigs'!#REF!*'IAS 41 Mvmnt Pigs'!F27 -> #REF! | L27: =E27+G27+H27+J27+K27+I27 -> #REF! | M27: 0 | N27: =+L27+M27 -> #REF! | O27: =[17]Sheet1!$O$171 -> 6.7846227e+08 | P27: =N27-O27 -> #REF!
A28: GILTS | B28: MAIN | C28: ='[16]IAS 41 Mvmnt Pigs'!$N28 -> 0 | D28: ='Summary Total Pigs'!#REF!*M26 -> #REF! | E28: =SUM(C28:D28) -> #REF! | F28: 0 | G28: ='Summary Total Pigs'!#REF!*'IAS 41 Mvmnt Pigs'!F28 -> #REF! | H28: =F28*'Summary Total Pigs'!#REF! -> #REF! | I28: =F28*'Summary Total Pigs'!#REF! -> #REF! | J28: =F28*'Summary Total Pigs'!#REF! -> #REF! | K28: ='Summary Total Pigs'!#REF!*'IAS 41 Mvmnt Pigs'!F28 -> #REF! | L28: =E28+G28+H28+J28+K28+I28 -> #REF! | M28: 0 | N28: =+L28+M28 -> #REF! | O28: 0 | P28: =N28-O28 -> #REF!
A29: SOWS | B29: MAIN | C29: ='[16]IAS 41 Mvmnt Pigs'!$N29 -> 0 | D29: 0 | E29: =SUM(C29:D29) -> 0 | F29: 0 | G29: ='Summary Total Pigs'!#REF!*'IAS 41 Mvmnt Pigs'!F29 -> #REF! | H29: =F29*'Summary Total Pigs'!#REF! -> #REF! | I29: =F29*'Summary Total Pigs'!#REF! -> #REF! | J29: =F29*'Summary Total Pigs'!#REF! -> #REF! | K29: ='Summary Total Pigs'!#REF!*'IAS 41 Mvmnt Pigs'!F29 -> #REF! | L29: =E29+G29+H29+J29+K29+I29 -> #REF! | M29: 0 | N29: =+L29+M29 -> #REF! | O29: 0 | P29: =N29-O29 -> #REF!
A30: BOARS | C30: ='[16]IAS 41 Mvmnt Pigs'!$N30 -> 0 | D30: ='Summary Total Pigs'!#REF!*M28 -> #REF! | E30: =SUM(C30:D30) -> #REF! | F30: 0 | G30: ='Summary Total Pigs'!#REF!*'IAS 41 Mvmnt Pigs'!F30 -> #REF! | H30: =F30*'Summary Total Pigs'!#REF! -> #REF! | I30: =F30*'Summary Total Pigs'!#REF! -> #REF! | J30: =F30*'Summary Total Pigs'!#REF! -> #REF! | K30: ='Summary Total Pigs'!#REF!*'IAS 41 Mvmnt Pigs'!F30 -> #REF! | L30: =E30+G30+H30+J30+K30+I30 -> #REF! | M30: 0 | N30: =+L30+M30 -> #REF! | O30: 0 | P30: =N30-O30 -> #REF!
A31: TOTAL | C31: =SUM(C25:C30) -> 3.8161986e+08 | D31: =SUM(D25:D29) -> #REF! | E31: =SUM(E25:E30) -> #REF! | F31: =SUM(F25:F30) -> #REF! | G31: =SUM(G25:G30) -> #REF! | H31: =SUM(H25:H30) -> #REF! | I31: =SUM(I25:I30) -> #REF! | J31: =SUM(J25:J30) -> #REF! | K31: =SUM(K25:K30) -> #REF! | L31: =SUM(L25:L30) -> #REF! | ... N31: =SUM(N25:N30) -> #REF! | O31: =SUM(O26:O30) -> 6.7846227e+08 | P31: =N31-O31 -> #REF! | Q31: =[17]Sheet1!$O$16 -> -6.7827279e+08
Q32: =M31+Q31 -> -6.7827279e+08
A34: SITE: | B34: ZIMBO | E34: =21*2127853690 -> 44684927490 | G34: =393+34 -> 427
A36: DESCRIPTION | B36: SITE | C36: OPENING | D36: TRANSFER IN | E36: TOTAL COST | F36: AVERAGE COST | G36: TRANSFER OUT | H36: SALES | I36: =I24 -> #REF! | J36: =+J24 -> CULLS | K36: =+K24 -> STOCK ADJMNT | L36: SUB TOTAL | M36: =+M24 -> CURRENT ADJMNT | N36: =+N24 -> CLOSING BAL | O36: CLOSING BAL
A37: PIGLETS | B37: MAIN | C37: ='[16]IAS 41 Mvmnt Pigs'!$N37 -> 16928588 | E37: =SUM(C37:D37) -> 16928588 | F37: =$E37/'Summary Total Pigs'!#REF! -> #REF! | G37: ='Summary Total Pigs'!N50*'IAS 41 Mvmnt Pigs'!F37 -> #REF! | H37: ='Summary Total Pigs'!#REF!*F37 -> #REF! | I37: =F37*'Summary Total Pigs'!W50 -> #REF! | J37: ='Summary Total Pigs'!X50*'IAS 41 Mvmnt Pigs'!F37 -> #REF! | K37: ='Summary Total Pigs'!AD50*'IAS 41 Mvmnt Pigs'!F37 -> #REF! | L37: =E37+G37+H37+J37+K37+I37 -> #REF! | M37: 0 | N37: =+L37+M37 -> #REF! | O37: =[17]Sheet1!$Q169 -> 32013468 | P37: =N37-O37 -> #REF!
A38: WEANERS | B38: WEANER | C38: ='[16]IAS 41 Mvmnt Pigs'!$N38 -> 0 | E38: =SUM(C38:D38) -> 0 | G38: ='Summary Total Pigs'!N51*'IAS 41 Mvmnt Pigs'!F38 -> 0 | H38: ='Summary Total Pigs'!#REF!*'IAS 41 Mvmnt Pigs'!F38 -> #REF! | I38: =F38*'Summary Total Pigs'!W51 -> 0 | J38: ='Summary Total Pigs'!X51*'IAS 41 Mvmnt Pigs'!F38 -> 0 | K38: ='Summary Total Pigs'!AD51*'IAS 41 Mvmnt Pigs'!F38 -> 0 | L38: =E38+G38+H38+J38+K38+I38 -> #REF! | M38: 0 | N38: =+L38+M38 -> #REF! | O38: =[17]Sheet1!$Q170
A39: GROWERS | B39: GROWER | C39: ='[16]IAS 41 Mvmnt Pigs'!$N39 -> 5.9604645e-18 | E39: =SUM(C39:D39) -> 5.9604645e-18 | G39: ='Summary Total Pigs'!N52*'IAS 41 Mvmnt Pigs'!F39 -> 0 | H39: ='Summary Total Pigs'!#REF!*'IAS 41 Mvmnt Pigs'!F39 -> #REF! | I39: =F39*'Summary Total Pigs'!W52 -> 0 | J39: ='Summary Total Pigs'!X52*'IAS 41 Mvmnt Pigs'!F39 -> 0 | K39: ='Summary Total Pigs'!AD52*'IAS 41 Mvmnt Pigs'!F39 -> 0 | L39: =E39+G39+H39+J39+K39+I39 -> #REF! | M39: 0 | N39: =+L39+M39 -> #REF! | O39: =[17]Sheet1!$Q171
A40: GILTS | B40: MAIN | C40: ='[16]IAS 41 Mvmnt Pigs'!$N40 -> 0 | D40: =F66*'Summary Total Pigs'!D53 -> #REF! | E40: =SUM(C40:D40) -> #REF! | F40: =$E40/'Summary Total Pigs'!#REF! -> #REF! | G40: ='Summary Total Pigs'!N53*'IAS 41 Mvmnt Pigs'!F40 -> #REF! | H40: ='Summary Total Pigs'!#REF!*'IAS 41 Mvmnt Pigs'!F40 -> #REF! | I40: =F40*'Summary Total Pigs'!W53 -> #REF! | J40: ='Summary Total Pigs'!X53*'IAS 41 Mvmnt Pigs'!F40 -> #REF! | K40: ='Summary Total Pigs'!AD53*'IAS 41 Mvmnt Pigs'!F40 -> #REF! | L40: =E40+G40+H40+J40+K40+I40 -> #REF! | M40: 0 | N40: =+L40+M40 -> #REF! | O40: =[17]Sheet1!$Q172
A41: SOWS | B41: MAIN | C41: ='[16]IAS 41 Mvmnt Pigs'!$N41 -> 3.9690606e+08 | D41: =F40*'Summary Total Pigs'!D54 -> #REF! | E41: =SUM(C41:D41) -> #REF! | F41: =$E41/'Summary Total Pigs'!#REF! -> #REF! | G41: ='Summary Total Pigs'!N54*'IAS 41 Mvmnt Pigs'!F41 -> #REF! | H41: ='Summary Total Pigs'!#REF!*'IAS 41 Mvmnt Pigs'!F41 -> #REF! | I41: =F41*'Summary Total Pigs'!W54 -> #REF! | J41: ='Summary Total Pigs'!X54*'IAS 41 Mvmnt Pigs'!F41 -> #REF! | K41: ='Summary Total Pigs'!AD54*'IAS 41 Mvmnt Pigs'!F41 -> #REF! | L41: =E41+G41+H41+J41+K41+I41 -> #REF! | M41: 0 | N41: =+L41+M41 -> #REF! | O41: =[17]Sheet1!$Q173 -> 4.2266679e+08 | P41: =N41-O41 -> #REF!
A42: BOARS | C42: ='[16]IAS 41 Mvmnt Pigs'!$N42 -> 6081750 | E42: =SUM(C42:D42) -> 6081750 | F42: =$E42/'Summary Total Pigs'!#REF! -> #REF! | G42: ='Summary Total Pigs'!N55*'IAS 41 Mvmnt Pigs'!F42 -> #REF! | H42: ='Summary Total Pigs'!#REF!*'IAS 41 Mvmnt Pigs'!$F42 -> #REF! | I42: =F42*'Summary Total Pigs'!W55 -> #REF! | J42: ='Summary Total Pigs'!X55*'IAS 41 Mvmnt Pigs'!F42 -> #REF! | K42: ='Summary Total Pigs'!AD55*'IAS 41 Mvmnt Pigs'!F42 -> #REF! | L42: =E42+G42+H42+J42+K42+I42 -> #REF! | M42: 0 | N42: =+L42+M42 -> #REF! | O42: =[17]Sheet1!$Q174 -> 6081750 | P42: =N42-O42 -> #REF!
A43: TOTAL | C43: =SUM(C37:C42) -> 4.199164e+08 | D43: =SUM(D37:D41) -> #REF! | E43: =SUM(E37:E42) -> #REF! | F43: =SUM(F37:F42) -> #REF! | G43: =SUM(G37:G42) -> #REF! | H43: =SUM(H37:H42) -> #REF! | I43: =SUM(I37:I42) -> #REF! | J43: =SUM(J37:J42) -> #REF! | K43: =SUM(K37:K42) -> #REF! | L43: =SUM(L37:L42) -> #REF! | ... O43: =SUM(O37:O42) -> 4.6076201e+08 | P43: =N43-O43 -> #REF! | Q43: =[17]Sheet1!$Q$16 -> -4.605947e+08
Q44: =M43+Q43 -> -4.605947e+08
A49: SITE: | B49: ROGATE
A51: DESCRIPTION | B51: SITE | C51: OPENING | D51: TRANSFER IN | E51: TOTAL COST | F51: AVERAGE COST | G51: TRANSFER OUT | H51: SALES | I51: =I36 -> #REF! | J51: =+J36 -> CULLS | K51: =+K36 -> STOCK ADJMNT | L51: SUB TOTAL | M51: =+M36 -> CURRENT ADJMNT | N51: =+N36 -> CLOSING BAL | O51: CLOSING BAL
A52: PIGLETS | B52: MAIN | C52: ='[16]IAS 41 Mvmnt Pigs'!$N52 -> 14314484 | D52: ='Summary Total Pigs'!D89*F37 -> #REF! | E52: =SUM(C52:D52) -> #REF! | F52: =$E52/'Summary Total Pigs'!$M89 -> #REF! | G52: ='Summary Total Pigs'!N89*'IAS 41 Mvmnt Pigs'!F52 -> #REF! | H52: ='Summary Total Pigs'!#REF!*'IAS 41 Mvmnt Pigs'!F52 -> #REF! | I52: =F52*'Summary Total Pigs'!#REF! -> #REF! | J52: ='Summary Total Pigs'!Z89*'IAS 41 Mvmnt Pigs'!F52 -> #REF! | K52: ='Summary Total Pigs'!#REF!*'IAS 41 Mvmnt Pigs'!F52 -> #REF! | L52: =E52+G52+H52+J52+K52+I52 -> #REF! | M52: 0 | N52: =+L52+M52 -> #REF! | O52: =[17]Sheet1!$M169 -> 30151786 | P52: =N52-O52 -> #REF!
A53: WEANERS | B53: WEANER | C53: ='[16]IAS 41 Mvmnt Pigs'!$N53 -> 1.8133208e+08 | D53: ='Summary Total Pigs'!D90*F52 -> #REF! | E53: =SUM(C53:D53) -> #REF! | F53: =$E53/'Summary Total Pigs'!$M90 -> #REF! | G53: ='Summary Total Pigs'!N90*'IAS 41 Mvmnt Pigs'!F53 -> #REF! | H53: ='Summary Total Pigs'!#REF!*'IAS 41 Mvmnt Pigs'!F53 -> #REF! | I53: =F53*'Summary Total Pigs'!#REF! -> #REF! | J53: ='Summary Total Pigs'!Z90*'IAS 41 Mvmnt Pigs'!F53 -> #REF! | K53: ='Summary Total Pigs'!#REF!*'IAS 41 Mvmnt Pigs'!F53 -> #REF! | L53: =E53+G53+H53+J53+K53+I53 -> #REF! | M53: 0 | N53: =+L53+M53 -> #REF! | O53: =[17]Sheet1!$M170 -> 3.1258197e+08 | P53: =N53-O53 -> #REF!
A54: GROWERS | B54: GROWER | C54: ='[16]IAS 41 Mvmnt Pigs'!$N54 -> 3.7481825e+08 | D54: ='Summary Total Pigs'!D91*F77 -> #REF! | E54: =SUM(C54:D54) -> #REF! | F54: =$E54/'Summary Total Pigs'!$M91 -> #REF! | G54: ='Summary Total Pigs'!N94*'IAS 41 Mvmnt Pigs'!F54 -> #REF! | H54: ='Summary Total Pigs'!#REF!*'IAS 41 Mvmnt Pigs'!F54 -> #REF! | I54: =F54*'Summary Total Pigs'!#REF! -> #REF! | J54: ='Summary Total Pigs'!Z91*'IAS 41 Mvmnt Pigs'!F54 -> #REF! | K54: ='Summary Total Pigs'!#REF!*'IAS 41 Mvmnt Pigs'!F54 -> #REF! | L54: =E54+G54+H54+J54+K54+I54 -> #REF! | M54: 0 | N54: =+L54+M54 -> #REF! | O54: =[17]Sheet1!$M171 -> 2.9863187e+08 | P54: =N54-O54 -> #REF!
A55: GILTS | B55: MAIN | C55: ='[16]IAS 41 Mvmnt Pigs'!$N55 -> 4052510.7 | D55: =10*F15+15*F54 -> #REF! | E55: =SUM(C55:D55) -> #REF! | F55: =$E55/'Summary Total Pigs'!$M92 -> #REF! | G55: ='Summary Total Pigs'!N92*'IAS 41 Mvmnt Pigs'!F55 -> #REF! | H55: ='Summary Total Pigs'!#REF!*'IAS 41 Mvmnt Pigs'!F55 -> #REF! | I55: =F55*'Summary Total Pigs'!#REF! -> #REF! | J55: ='Summary Total Pigs'!Z92*'IAS 41 Mvmnt Pigs'!F55 -> #REF! | K55: ='Summary Total Pigs'!#REF!*'IAS 41 Mvmnt Pigs'!F55 -> #REF! | L55: =E55+G55+H55+J55+K55+I55 -> #REF! | M55: 0 | N55: =+L55+M55 -> #REF! | O55: =[17]Sheet1!$M172 -> 12816047 | P55: =N55-O55 -> #REF!
A56: SOWS | B56: MAIN | C56: ='[16]IAS 41 Mvmnt Pigs'!$N56 -> 4.3669412e+08 | D56: =F55*'Summary Total Pigs'!D93 -> #REF! | E56: =SUM(C56:D56) -> #REF! | F56: =$E56/'Summary Total Pigs'!$M93 -> #REF! | G56: ='Summary Total Pigs'!N93*'IAS 41 Mvmnt Pigs'!F56 -> #REF! | H56: ='Summary Total Pigs'!#REF!*'IAS 41 Mvmnt Pigs'!F56 -> #REF! | I56: =F56*'Summary Total Pigs'!#REF! -> #REF! | J56: ='Summary Total Pigs'!Z93*'IAS 41 Mvmnt Pigs'!F56 -> #REF! | K56: ='Summary Total Pigs'!#REF!*'IAS 41 Mvmnt Pigs'!F56 -> #REF! | L56: =E56+G56+H56+J56+K56+I56 -> #REF! | M56: 0 | N56: =+L56+M56 -> #REF! | O56: =[17]Sheet1!$M173 -> 4.7942425e+08 | P56: =N56-O56 -> #REF!
A57: BOARS | C57: ='[16]IAS 41 Mvmnt Pigs'!$N57 -> 6081749.9 | D57: ='Summary Total Pigs'!D94*F56 -> #REF! | E57: =SUM(C57:D57) -> #REF! | F57: =$E57/'Summary Total Pigs'!$M94 -> #REF! | G57: ='Summary Total Pigs'!#REF!*'IAS 41 Mvmnt Pigs'!F57 -> #REF! | H57: ='Summary Total Pigs'!#REF!*'IAS 41 Mvmnt Pigs'!F57 -> #REF! | I57: =F57*'Summary Total Pigs'!#REF! -> #REF! | J57: ='Summary Total Pigs'!Z94*'IAS 41 Mvmnt Pigs'!F57 -> #REF! | K57: ='Summary Total Pigs'!#REF!*'IAS 41 Mvmnt Pigs'!F57 -> #REF! | L57: =E57+G57+H57+J57+K57+I57 -> #REF! | M57: 0 | N57: =+L57+M57 -> #REF! | O57: =[17]Sheet1!$M174 -> 6081749.9 | P57: =N57-O57 -> #REF!
A58: TOTAL | C58: =SUM(C52:C57) -> 1.0172932e+09 | D58: =SUM(D52:D56) -> #REF! | E58: =SUM(E52:E57) -> #REF! | F58: =SUM(F52:F57) -> #REF! | G58: =SUM(G52:G57) -> #REF! | H58: =SUM(H52:H57) -> #REF! | I58: =SUM(I52:I57) -> #REF! | J58: =SUM(J52:J57) -> #REF! | K58: =SUM(K52:K57) -> #REF! | L58: =SUM(L52:L57) -> #REF! | ... O58: =SUM(O52:O57) -> 1.1396877e+09 | P58: =N58-O58 -> #REF! | Q58: =[17]Sheet1!$M$16 -> -1.1394476e+09
Q59: =M58+Q58 -> -1.1394476e+09
A60: SITE: | B60: QUARANTINE
A62: DESCRIPTION | B62: SITE | C62: OPENING | D62: TRANSFER IN | E62: TOTAL COST | F62: AVERAGE COST | G62: TRANSFER OUT | H62: SALES | I62: =I51 -> #REF! | J62: =+J51 -> CULLS | K62: =+K51 -> STOCK ADJMNT | L62: SUB TOTAL | M62: =+M51 -> CURRENT ADJMNT | N62: =+N51 -> CLOSING BAL | O62: CLOSING BAL
A63: PIGLETS | B63: MAIN | C63: ='[16]IAS 41 Mvmnt Pigs'!$N63 -> 0 | E63: =SUM(C63:D63) -> 0 | G63: ='Summary Total Pigs'!Q127*'IAS 41 Mvmnt Pigs'!F63 -> 0 | H63: ='Summary Total Pigs'!Z127*'IAS 41 Mvmnt Pigs'!F63 -> 0 | I63: =F63*'Summary Total Pigs'!AB127 -> 0 | J63: ='Summary Total Pigs'!AD127*'IAS 41 Mvmnt Pigs'!F63 -> 0 | K63: ='Summary Total Pigs'!AG127*'IAS 41 Mvmnt Pigs'!F63 -> 0 | L63: =E63+G63+H63+J63+K63+I63 -> 0 | M63: 0 | N63: =+L63+M63 -> 0 | O63: 0 | P63: =N63-O63 -> 0
A64: WEANERS | B64: WEANER | C64: ='[16]IAS 41 Mvmnt Pigs'!$N64 -> 0 | D64: 0 | E64: =SUM(C64:D64) -> 0 | G64: ='Summary Total Pigs'!Q128*'IAS 41 Mvmnt Pigs'!F64 -> 0 | H64: ='Summary Total Pigs'!Z128*'IAS 41 Mvmnt Pigs'!F64 -> 0 | I64: =F64*'Summary Total Pigs'!AB128 -> 0 | J64: ='Summary Total Pigs'!AD128*'IAS 41 Mvmnt Pigs'!F64 -> 0 | K64: ='Summary Total Pigs'!AG128*'IAS 41 Mvmnt Pigs'!F64 -> 0 | L64: =E64+G64+H64+J64+K64+I64 -> 0 | M64: 0 | N64: =+L64+M64 -> 0 | O64: 0 | P64: =N64-O64 -> 0
A65: GROWERS | B65: GROWER | C65: ='[16]IAS 41 Mvmnt Pigs'!$N65 -> 0 | D65: 0 | E65: =SUM(C65:D65) -> 0 | G65: ='Summary Total Pigs'!Q129*'IAS 41 Mvmnt Pigs'!F65 -> 0 | H65: ='Summary Total Pigs'!Z129*'IAS 41 Mvmnt Pigs'!F65 -> 0 | I65: =F65*'Summary Total Pigs'!AB129 -> 0 | J65: ='Summary Total Pigs'!AD129*'IAS 41 Mvmnt Pigs'!F65 -> 0 | K65: ='Summary Total Pigs'!AG129*'IAS 41 Mvmnt Pigs'!F65 -> 0 | L65: =E65+G65+H65+J65+K65+I65 -> 0 | M65: 0 | N65: =+L65+M65 -> 0 | O65: 0 | P65: =N65-O65 -> 0
A66: GILTS | B66: MAIN | C66: ='[16]IAS 41 Mvmnt Pigs'!$N66 -> 1.8457166e+08 | D66: ='Summary Total Pigs'!D130*'IAS 41 Mvmnt Pigs'!F15 -> #REF! | E66: =SUM(C66:D66) -> #REF! | F66: =+E66/'Summary Total Pigs'!P130 -> #REF! | G66: ='Summary Total Pigs'!Q130*'IAS 41 Mvmnt Pigs'!F66 -> #REF! | H66: ='Summary Total Pigs'!Z130*'IAS 41 Mvmnt Pigs'!F66 -> #REF! | I66: =F66*'Summary Total Pigs'!AB130 -> #REF! | J66: ='Summary Total Pigs'!AD130*'IAS 41 Mvmnt Pigs'!F66 -> #REF! | K66: ='Summary Total Pigs'!AG130*'IAS 41 Mvmnt Pigs'!F66 -> #REF! | L66: =E66+G66+H66+J66+K66+I66 -> #REF! | M66: 0 | N66: =+L66+M66 -> #REF! | O66: =[17]Sheet1!$L$172 -> 1.8457166e+08 | P66: =N66-O66 -> #REF!
A67: SOWS | B67: MAIN | C67: ='[16]IAS 41 Mvmnt Pigs'!$N67 -> 0 | D67: 0 | E67: =SUM(C67:D67) -> 0 | G67: ='Summary Total Pigs'!Q131*'IAS 41 Mvmnt Pigs'!F67 -> 0 | H67: ='Summary Total Pigs'!Z131*'IAS 41 Mvmnt Pigs'!F67 -> 0 | I67: =F67*'Summary Total Pigs'!AB131 -> 0 | J67: ='Summary Total Pigs'!AD131*'IAS 41 Mvmnt Pigs'!F67 -> 0 | K67: ='Summary Total Pigs'!AG131*'IAS 41 Mvmnt Pigs'!F67 -> 0 | L67: =E67+G67+H67+J67+K67+I67 -> 0 | M67: 0 | N67: =+L67+M67 -> 0 | O67: 0 | P67: =N67-O67 -> 0
A68: BOARS | C68: ='[16]IAS 41 Mvmnt Pigs'!$N68 -> 2027249.9 | D68: ='Summary Total Pigs'!D132*F18 -> #REF! | E68: =SUM(C68:D68) -> #REF! | F68: 0 | G68: ='Summary Total Pigs'!Q132*'IAS 41 Mvmnt Pigs'!F68 -> 0 | H68: ='Summary Total Pigs'!Z132*'IAS 41 Mvmnt Pigs'!F68 -> 0 | I68: =F68*'Summary Total Pigs'!AB132 -> 0 | J68: ='Summary Total Pigs'!AD132*'IAS 41 Mvmnt Pigs'!F68 -> 0 | K68: ='Summary Total Pigs'!AG132*'IAS 41 Mvmnt Pigs'!F68 -> 0 | L68: =E68+G68+H68+J68+K68+I68 -> #REF! | M68: 0 | N68: =+L68+M68 -> #REF! | O68: =[17]Sheet1!$L$174 -> 2027249.9 | P68: =N68-O68 -> #REF!
A69: TOTAL | C69: =SUM(C63:C68) -> 1.8659891e+08 | D69: =SUM(D63:D67) -> #REF! | E69: =SUM(E63:E68) -> #REF! | F69: =SUM(F63:F68) -> #REF! | G69: =SUM(G63:G68) -> #REF! | H69: =SUM(H63:H68) -> #REF! | I69: =SUM(I63:I68) -> #REF! | J69: =SUM(J63:J68) -> #REF! | K69: =SUM(K63:K68) -> #REF! | L69: =SUM(L63:L68) -> #REF! | ... O69: =SUM(O63:O68) -> 1.8659891e+08 | P69: =N69-O69 -> #REF! | Q69: =[17]Sheet1!$L$16 -> -1.8654575e+08
Q70: =Q69+M69 -> -1.8654575e+08
A72: SITE: | B72: OSWA
A74: DESCRIPTION | B74: SITE | C74: OPENING | D74: TRANSFER IN | E74: TOTAL COST | F74: AVERAGE COST | G74: TRANSFER OUT | H74: SALES | I74: =I62 -> #REF! | J74: =+J62 -> CULLS | K74: =+K62 -> STOCK ADJMNT | L74: SUB TOTAL | M74: =+M62 -> CURRENT ADJMNT | N74: =+N62 -> CLOSING BAL | O74: CLOSING BAL
A75: PIGLETS | B75: MAIN | C75: ='[16]IAS 41 Mvmnt Pigs'!$N75 -> -1415941.4 | E75: =SUM(C75:D75) -> -1415941.4 | F75: =E75/'Summary Total Pigs'!#REF! -> #REF! | G75: ='Summary Total Pigs'!#REF!*'IAS 41 Mvmnt Pigs'!F75 -> #REF! | H75: ='Summary Total Pigs'!#REF!*'IAS 41 Mvmnt Pigs'!F75 -> #REF! | I75: =F75*'Summary Total Pigs'!#REF! -> #REF! | J75: ='Summary Total Pigs'!#REF!*'IAS 41 Mvmnt Pigs'!F75 -> #REF! | K75: ='Summary Total Pigs'!#REF!*'IAS 41 Mvmnt Pigs'!F75 -> #REF! | L75: =E75+G75+H75+J75+K75+I75 -> #REF! | M75: 0 | N75: =+L75+M75 -> #REF! | O75: =[17]Sheet1!$K169 -> -1415941.4 | P75: =N75-O75 -> #REF!
A76: WEANERS | B76: WEANER | C76: ='[16]IAS 41 Mvmnt Pigs'!$N76 -> 5.4634308e+08 | D76: ='Summary Total Pigs'!#REF!*'IAS 41 Mvmnt Pigs'!F75 -> #REF! | E76: =SUM(C76:D76) -> #REF! | F76: =E76/'Summary Total Pigs'!#REF! -> #REF! | G76: ='Summary Total Pigs'!#REF!*'IAS 41 Mvmnt Pigs'!F76 -> #REF! | H76: ='Summary Total Pigs'!#REF!*'IAS 41 Mvmnt Pigs'!F76 -> #REF! | I76: =F76*'Summary Total Pigs'!#REF! -> #REF! | J76: ='Summary Total Pigs'!#REF!*'IAS 41 Mvmnt Pigs'!F76 -> #REF! | K76: ='Summary Total Pigs'!#REF!*'IAS 41 Mvmnt Pigs'!F76 -> #REF! | L76: =E76+G76+H76+J76+K76+I76 -> #REF! | M76: 0 | N76: =+L76+M76 -> #REF! | O76: =[17]Sheet1!$K170 -> 6.2450375e+08 | P76: =N76-O76 -> #REF!
A77: GROWERS | B77: GROWER | C77: ='[16]IAS 41 Mvmnt Pigs'!$N77 -> 1.1059841e+08 | D77: ='Summary Total Pigs'!#REF!*'IAS 41 Mvmnt Pigs'!F76 -> #REF! | E77: =SUM(C77:D77) -> #REF! | F77: =E77/'Summary Total Pigs'!#REF! -> #REF! | G77: ='Summary Total Pigs'!#REF!*'IAS 41 Mvmnt Pigs'!F77 -> #REF! | H77: ='Summary Total Pigs'!#REF!*'IAS 41 Mvmnt Pigs'!F77 -> #REF! | I77: =F77*'Summary Total Pigs'!#REF! -> #REF! | J77: ='Summary Total Pigs'!#REF!*'IAS 41 Mvmnt Pigs'!F77 -> #REF! | K77: ='Summary Total Pigs'!#REF!*'IAS 41 Mvmnt Pigs'!F77 -> #REF! | L77: =E77+G77+H77+J77+K77+I77 -> #REF! | M77: 0 | N77: =+L77+M77 -> #REF! | O77: =[17]Sheet1!$K171 -> 1.6569468e+09 | P77: =N77-O77 -> #REF!
A78: GILTS | B78: MAIN | C78: ='[16]IAS 41 Mvmnt Pigs'!$N78 -> 0 | D78: ='Summary Total Pigs'!#REF!*'IAS 41 Mvmnt Pigs'!F77 -> #REF! | E78: =SUM(C78:D78) -> #REF! | G78: ='Summary Total Pigs'!#REF!*'IAS 41 Mvmnt Pigs'!F78 -> #REF! | H78: ='Summary Total Pigs'!#REF!*'IAS 41 Mvmnt Pigs'!F78 -> #REF! | I78: =F78*'Summary Total Pigs'!#REF! -> #REF! | J78: ='Summary Total Pigs'!#REF!*'IAS 41 Mvmnt Pigs'!F78 -> #REF! | K78: ='Summary Total Pigs'!#REF!*'IAS 41 Mvmnt Pigs'!F78 -> #REF! | L78: =E78+G78+H78+J78+K78+I78 -> #REF! | M78: 0 | N78: =+L78+M78 -> #REF! | O78: =[17]Sheet1!$K172
A79: SOWS | B79: MAIN | C79: ='[16]IAS 41 Mvmnt Pigs'!$N79 -> 2.403995e+08 | D79: ='Summary Total Pigs'!#REF!*F56 -> #REF! | E79: =SUM(C79:D79) -> #REF! | F79: =E79/'Summary Total Pigs'!#REF! -> #REF! | G79: ='Summary Total Pigs'!#REF!*'IAS 41 Mvmnt Pigs'!F79 -> #REF! | H79: ='Summary Total Pigs'!#REF!*'IAS 41 Mvmnt Pigs'!F79 -> #REF! | I79: =F79*'Summary Total Pigs'!#REF! -> #REF! | J79: ='Summary Total Pigs'!#REF!*'IAS 41 Mvmnt Pigs'!F79 -> #REF! | K79: ='Summary Total Pigs'!#REF!*'IAS 41 Mvmnt Pigs'!F79 -> #REF! | L79: =E79+G79+H79+J79+K79+I79 -> #REF! | M79: 0 | N79: =+L79+M79 -> #REF! | O79: =[17]Sheet1!$K173 -> 5.3135922e+08 | P79: =N79-O79 -> #REF!
A80: BOARS | C80: ='[16]IAS 41 Mvmnt Pigs'!$N80 -> 12163500 | D80: ='Summary Total Pigs'!#REF!*'IAS 41 Mvmnt Pigs'!F79 -> #REF! | E80: =SUM(C80:D80) -> #REF! | F80: =E80/'Summary Total Pigs'!#REF! -> #REF! | G80: ='Summary Total Pigs'!#REF!*'IAS 41 Mvmnt Pigs'!F80 -> #REF! | H80: ='Summary Total Pigs'!#REF!*'IAS 41 Mvmnt Pigs'!F80 -> #REF! | I80: =F80*'Summary Total Pigs'!#REF! -> #REF! | J80: ='Summary Total Pigs'!#REF!*'IAS 41 Mvmnt Pigs'!F80 -> #REF! | K80: ='Summary Total Pigs'!#REF!*'IAS 41 Mvmnt Pigs'!F80 -> #REF! | L80: =E80+G80+H80+J80+K80+I80 -> #REF! | M80: 0 | N80: =+L80+M80 -> #REF! | O80: =[17]Sheet1!$K174 -> 16217999 | P80: =N80-O80 -> #REF!
A81: TOTAL | C81: =SUM(C75:C80) -> 9.0808855e+08 | D81: =SUM(D75:D79) -> #REF! | E81: =SUM(E75:E80) -> #REF! | F81: =SUM(F75:F80) -> #REF! | G81: =SUM(G75:G80) -> #REF! | H81: =SUM(H75:H80) -> #REF! | I81: =SUM(I75:I80) -> #REF! | J81: =SUM(J75:J80) -> #REF! | K81: =SUM(K75:K80) -> #REF! | L81: =SUM(L75:L80) -> #REF! | ... O81: =SUM(O75:O80) -> 2.8276118e+09 | P81: =N81-O81 -> #REF! | Q81: =[17]Sheet1!$K$16 -> -2.8270356e+09
Q82: =M81+Q81 -> -2.8270356e+09
A84: SITE: | B84: UMFULI BANKS
A86: DESCRIPTION | B86: SITE | C86: OPENING | D86: TRANSFER IN | E86: TOTAL COST | F86: AVERAGE COST | G86: TRANSFER OUT | H86: SALES | I86: =I74 -> #REF! | J86: =+J74 -> CULLS | K86: =+K74 -> STOCK ADJMNT | L86: SUB TOTAL | M86: =+M74 -> CURRENT ADJMNT | N86: =+N74 -> CLOSING BAL | O86: CLOSING BAL
A87: PIGLETS | B87: MAIN | C87: ='[16]IAS 41 Mvmnt Pigs'!$N87 -> 0 | E87: =SUM(C87:D87) -> 0 | G87: ='Summary Total Pigs'!#REF!*'IAS 41 Mvmnt Pigs'!F87 -> #REF! | H87: ='Summary Total Pigs'!#REF!*'IAS 41 Mvmnt Pigs'!F87 -> #REF! | I87: =F87*'Summary Total Pigs'!#REF! -> #REF! | J87: =F87*'Summary Total Pigs'!AD200 -> 0 | K87: ='Summary Total Pigs'!#REF!*'IAS 41 Mvmnt Pigs'!F87 -> #REF! | L87: =E87+G87+H87+J87+K87+I87 -> #REF! | M87: 0 | N87: =+L87+M87 -> #REF! | O87: =[17]Sheet1!$P169
A88: WEANERS | B88: WEANER | C88: ='[16]IAS 41 Mvmnt Pigs'!$N88 -> 0 | E88: =SUM(C88:D88) -> 0 | F88: 0 | G88: ='Summary Total Pigs'!#REF!*'IAS 41 Mvmnt Pigs'!F88 -> #REF! | H88: ='Summary Total Pigs'!#REF!*'IAS 41 Mvmnt Pigs'!F88 -> #REF! | I88: =F88*'Summary Total Pigs'!#REF! -> #REF! | J88: =F88*'Summary Total Pigs'!AD201 -> 0 | K88: ='Summary Total Pigs'!#REF!*'IAS 41 Mvmnt Pigs'!F88 -> #REF! | L88: =E88+G88+H88+J88+K88+I88 -> #REF! | M88: 0 | N88: =+L88+M88 -> #REF! | O88: =[17]Sheet1!$P170
A89: GROWERS | B89: GROWER | C89: ='[16]IAS 41 Mvmnt Pigs'!$N89 -> 6.5404343e+08 | D89: ='Summary Total Pigs'!#REF!*F101 -> #REF! | E89: =SUM(C89:D89) -> #REF! | F89: =E89/'Summary Total Pigs'!#REF! -> #REF! | G89: ='Summary Total Pigs'!#REF!*'IAS 41 Mvmnt Pigs'!F89 -> #REF! | H89: ='Summary Total Pigs'!#REF!*'IAS 41 Mvmnt Pigs'!F89 -> #REF! | I89: =F89*'Summary Total Pigs'!#REF! -> #REF! | J89: =F89*'Summary Total Pigs'!AD202 -> #REF! | K89: ='Summary Total Pigs'!#REF!*'IAS 41 Mvmnt Pigs'!F89 -> #REF! | L89: =E89+G89+H89+J89+K89+I89 -> #REF! | M89: 0 | N89: =+L89+M89 -> #REF! | O89: =[17]Sheet1!$P171 -> 6.7686086e+08 | P89: =N89-O89 -> #REF! | R89: 3.1319483e+13
A90: GILTS | B90: MAIN | C90: ='[16]IAS 41 Mvmnt Pigs'!$N90 -> 0 | E90: =SUM(C90:D90) -> 0 | G90: ='Summary Total Pigs'!#REF!*'IAS 41 Mvmnt Pigs'!F90 -> #REF! | H90: ='Summary Total Pigs'!#REF!*'IAS 41 Mvmnt Pigs'!F90 -> #REF! | I90: =F90*'Summary Total Pigs'!#REF! -> #REF! | J90: =F90*'Summary Total Pigs'!AD203 -> 0 | K90: ='Summary Total Pigs'!#REF!*'IAS 41 Mvmnt Pigs'!F90 -> #REF! | L90: =E90+G90+H90+J90+K90+I90 -> #REF! | M90: 0 | N90: =+L90+M90 -> #REF! | O90: =[17]Sheet1!$P172
A91: SOWS | B91: MAIN | C91: ='[16]IAS 41 Mvmnt Pigs'!$N91 -> 0 | E91: =SUM(C91:D91) -> 0 | G91: ='Summary Total Pigs'!#REF!*'IAS 41 Mvmnt Pigs'!F91 -> #REF! | H91: ='Summary Total Pigs'!#REF!*'IAS 41 Mvmnt Pigs'!F91 -> #REF! | I91: =F91*'Summary Total Pigs'!#REF! -> #REF! | J91: =F91*'Summary Total Pigs'!AD205 -> 0 | K91: ='Summary Total Pigs'!#REF!*'IAS 41 Mvmnt Pigs'!F91 -> #REF! | L91: =E91+G91+H91+J91+K91+I91 -> #REF! | M91: 0 | N91: =+L91+M91 -> #REF! | O91: =[17]Sheet1!$P173
A92: BOARS | C92: ='[16]IAS 41 Mvmnt Pigs'!$N92 -> 0 | E92: =SUM(C92:D92) -> 0 | G92: ='Summary Total Pigs'!#REF!*'IAS 41 Mvmnt Pigs'!F92 -> #REF! | H92: ='Summary Total Pigs'!#REF!*'IAS 41 Mvmnt Pigs'!F92 -> #REF! | I92: =F92*'Summary Total Pigs'!#REF! -> #REF! | J92: =F92*'Summary Total Pigs'!AD207 -> 0 | K92: ='Summary Total Pigs'!#REF!*'IAS 41 Mvmnt Pigs'!F92 -> #REF! | L92: =E92+G92+H92+J92+K92+I92 -> #REF! | M92: 0 | N92: =+L92+M92 -> #REF! | O92: =[17]Sheet1!$P174
A93: TOTAL | C93: =SUM(C87:C92) -> 6.5404343e+08 | D93: =SUM(D87:D91) -> #REF! | E93: =SUM(E87:E92) -> #REF! | F93: =SUM(F87:F92) -> #REF! | G93: =SUM(G87:G92) -> #REF! | H93: =SUM(H87:H92) -> #REF! | I93: =SUM(I87:I92) -> #REF! | J93: =SUM(J87:J92) -> #REF! | K93: =SUM(K87:K92) -> #REF! | L93: =SUM(L87:L92) -> #REF! | ... O93: =SUM(O87:O92) -> 6.7686086e+08 | P93: =N93-O93 -> #REF! | Q93: =[17]Sheet1!$P$16 -> -6.7668944e+08
Q94: =M93+Q93 -> -6.7668944e+08
D95: =G94+(297*F37) -> #REF!
A96: SITE: | B96: SEAFORTH FARM
A98: DESCRIPTION | B98: SITE | C98: OPENING | D98: TRANSFER IN | E98: TOTAL COST | F98: AVERAGE COST | G98: TRANSFER OUT | H98: SALES | I98: =I86 -> #REF! | J98: =+J86 -> CULLS | K98: =+K86 -> STOCK ADJMNT | L98: SUB TOTAL | M98: =+M86 -> CURRENT ADJMNT | N98: =+N86 -> CLOSING BAL | O98: CLOSING BAL
A99: PIGLETS | B99: MAIN | C99: ='[16]IAS 41 Mvmnt Pigs'!$N99 -> 0 | D99: ='Summary Total Pigs'!#REF!*'Pigs Cost'!M37 -> #REF! | E99: =SUM(C99:D99) -> #REF! | G99: =F99*'Summary Total Pigs'!#REF! -> #REF! | H99: ='Summary Total Pigs'!#REF!*F99 -> #REF! | I99: =F99*'Summary Total Pigs'!#REF! -> #REF! | J99: =F99*'Summary Total Pigs'!#REF! -> #REF! | K99: ='Summary Total Pigs'!#REF!*'IAS 41 Mvmnt Pigs'!F99 -> #REF! | L99: =E99+G99+H99+J99+K99+I99 -> #REF! | M99: 0 | N99: =+L99+M99 -> #REF! | O99: 0 | P99: =N99-O99 -> #REF!
A100: WEANERS | B100: WEANER | C100: ='[16]IAS 41 Mvmnt Pigs'!$N100 -> 6.9282236e+08 | D100: =(603*F37)+(489*F53) -> #REF! | E100: =SUM(C100:D100) -> #REF! | F100: =E100/'Summary Total Pigs'!#REF! -> #REF! | G100: =F100*'Summary Total Pigs'!#REF! -> #REF! | H100: ='Summary Total Pigs'!#REF!*F100 -> #REF! | I100: =F100*'Summary Total Pigs'!#REF! -> #REF! | J100: =F100*'Summary Total Pigs'!#REF! -> #REF! | K100: ='Summary Total Pigs'!#REF!*'IAS 41 Mvmnt Pigs'!F100 -> #REF! | L100: =E100+G100+H100+J100+K100+I100 -> #REF! | M100: 0 | N100: =+L100+M100 -> #REF! | O100: =[17]Sheet1!$N170 -> 1.033289e+09 | P100: =N100-O100 -> #REF!
A101: GROWERS | B101: GROWER | C101: ='[16]IAS 41 Mvmnt Pigs'!$N101 -> 63912102 | D101: ='Summary Total Pigs'!#REF!*F100 -> #REF! | E101: =SUM(C101:D101) -> #REF! | F101: =E101/'Summary Total Pigs'!#REF! -> #REF! | G101: =F101*'Summary Total Pigs'!#REF! -> #REF! | H101: ='Summary Total Pigs'!#REF!*F101 -> #REF! | I101: =F101*'Summary Total Pigs'!#REF! -> #REF! | J101: =F101*'Summary Total Pigs'!#REF! -> #REF! | K101: ='Summary Total Pigs'!#REF!*'IAS 41 Mvmnt Pigs'!F101 -> #REF! | L101: =E101+G101+H101+J101+K101+I101 -> #REF! | M101: 0 | N101: =+L101+M101 -> #REF! | O101: =[17]Sheet1!$N171 -> 3.0325292e+08 | P101: =N101-O101 -> #REF!
A102: GILTS | B102: MAIN | C102: ='[16]IAS 41 Mvmnt Pigs'!$N102 -> 0 | E102: =SUM(C102:D102) -> 0 | G102: =F102*'Summary Total Pigs'!#REF! -> #REF! | H102: ='Summary Total Pigs'!#REF!*F102 -> #REF! | I102: =F102*'Summary Total Pigs'!#REF! -> #REF! | J102: =F102*'Summary Total Pigs'!#REF! -> #REF! | K102: ='Summary Total Pigs'!#REF!*'IAS 41 Mvmnt Pigs'!F102 -> #REF! | L102: =E102+G102+H102+J102+K102+I102 -> #REF! | M102: 0 | N102: =+L102+M102 -> #REF! | O102: 0 | P102: =N102-O102 -> #REF!
A103: SOWS | B103: MAIN | C103: ='[16]IAS 41 Mvmnt Pigs'!$N103 -> 0 | E103: =SUM(C103:D103) -> 0 | G103: =F103*'Summary Total Pigs'!#REF! -> #REF! | H103: ='Summary Total Pigs'!#REF!*'IAS 41 Mvmnt Pigs'!F103 -> #REF! | I103: =F103*'Summary Total Pigs'!#REF! -> #REF! | J103: =F103*'Summary Total Pigs'!#REF! -> #REF! | K103: ='Summary Total Pigs'!#REF!*'IAS 41 Mvmnt Pigs'!F103 -> #REF! | L103: =E103+G103+H103+J103+K103+I103 -> #REF! | M103: 0 | N103: =+L103+M103 -> #REF! | O103: 0 | P103: =N103-O103 -> #REF!
A104: BOARS | C104: ='[16]IAS 41 Mvmnt Pigs'!$N104 -> 0 | E104: =SUM(C104:D104) -> 0 | G104: =F104*'Summary Total Pigs'!#REF! -> #REF! | H104: ='Summary Total Pigs'!#REF!*'IAS 41 Mvmnt Pigs'!F104 -> #REF! | I104: =F104*'Summary Total Pigs'!#REF! -> #REF! | J104: =F104*'Summary Total Pigs'!#REF! -> #REF! | K104: ='Summary Total Pigs'!#REF!*'IAS 41 Mvmnt Pigs'!F104 -> #REF! | L104: =E104+G104+H104+J104+K104+I104 -> #REF! | M104: 0 | N104: =+L104+M104 -> #REF! | O104: 0 | P104: =N104-O104 -> #REF!
A105: TOTAL | C105: =SUM(C99:C104) -> 7.5673447e+08 | D105: =SUM(D99:D103) -> #REF! | E105: =SUM(E99:E104) -> #REF! | F105: =SUM(F99:F104) -> #REF! | G105: =SUM(G99:G104) -> #REF! | H105: =SUM(H99:H104) -> #REF! | I105: =SUM(I99:I104) -> #REF! | J105: =SUM(J99:J104) -> #REF! | K105: =SUM(K99:K104) -> #REF! | L105: =SUM(L99:L104) -> #REF! | ... O105: =SUM(O99:O104) -> 1.3365419e+09 | P105: =N105-O105 -> #REF! | Q105: =[17]Sheet1!$N$16 -> -1.3364701e+09
Q106: =M105+Q105 -> -1.3364701e+09
A108: SITE: | B108: MOON FARM
A110: DESCRIPTION | B110: SITE | C110: OPENING | D110: TRANSFER IN | E110: TOTAL COST | F110: AVERAGE COST | G110: TRANSFER OUT | H110: SALES | I110: =I98 -> #REF! | J110: =+J98 -> CULLS | K110: =+K98 -> STOCK ADJMNT | L110: SUB TOTAL | M110: =+M98 -> CURRENT ADJMNT | N110: =+N98 -> CLOSING BAL | O110: CLOSING BAL
A111: PIGLETS | B111: MAIN | C111: ='[16]IAS 41 Mvmnt Pigs'!$N111 -> 0 | D111: ='Summary Total Pigs'!#REF!*'IAS 41 Mvmnt Pigs'!F76 -> #REF! | E111: =SUM(C111:D111) -> #REF! | G111: ='Summary Total Pigs'!#REF!*'IAS 41 Mvmnt Pigs'!F111 -> #REF! | H111: ='Summary Total Pigs'!#REF!*'IAS 41 Mvmnt Pigs'!F111 -> #REF! | I111: =F111*'Summary Total Pigs'!#REF! -> #REF! | J111: =F111*'Summary Total Pigs'!AD228 -> 0 | K111: ='Summary Total Pigs'!#REF!*'IAS 41 Mvmnt Pigs'!F111 -> #REF! | L111: =E111+G111+H111+J111+K111+I111 -> #REF! | M111: 0 | N111: =+L111+M111 -> #REF! | O111: 0 | P111: =N111-O111 -> #REF!
A112: WEANERS | B112: WEANER | C112: ='[16]IAS 41 Mvmnt Pigs'!$N112 -> 0 | D112: ='Summary Total Pigs'!#REF!*'IAS 41 Mvmnt Pigs'!F53 -> #REF! | E112: 0 | F112: 0 | G112: ='Summary Total Pigs'!#REF!*'IAS 41 Mvmnt Pigs'!F112 -> #REF! | H112: ='Summary Total Pigs'!#REF!*'IAS 41 Mvmnt Pigs'!F112 -> #REF! | I112: =F112*'Summary Total Pigs'!#REF! -> #REF! | J112: =F112*'Summary Total Pigs'!AD229 -> 0 | K112: ='Summary Total Pigs'!#REF!*'IAS 41 Mvmnt Pigs'!F112 -> #REF! | L112: =E112+G112+H112+J112+K112+I112 -> #REF! | M112: 0 | N112: =+L112+M112 -> #REF! | O112: 0 | P112: =N112-O112 -> #REF!
A113: GROWERS | B113: GROWER | C113: ='[16]IAS 41 Mvmnt Pigs'!$N113 -> 3.4851191e+08 | D113: =160*F77+150*F101 -> #REF! | E113: =SUM(C113:D113) -> #REF! | F113: =E113/'Summary Total Pigs'!#REF! -> #REF! | G113: ='Summary Total Pigs'!#REF!*'IAS 41 Mvmnt Pigs'!F113 -> #REF! | H113: ='Summary Total Pigs'!#REF!*'IAS 41 Mvmnt Pigs'!F113 -> #REF! | I113: =F113*'Summary Total Pigs'!#REF! -> #REF! | J113: =F113*'Summary Total Pigs'!AD230 -> #REF! | K113: ='Summary Total Pigs'!#REF!*'IAS 41 Mvmnt Pigs'!F113 -> #REF! | L113: =E113+G113+H113+J113+K113+I113 -> #REF! | M113: 0 | N113: =+L113+M113 -> #REF! | O113: =[17]Sheet1!$J$171 -> 3.8951658e+08 | P113: =N113-O113 -> #REF!
A114: GILTS | B114: MAIN | C114: ='[16]IAS 41 Mvmnt Pigs'!$N114 -> 0 | E114: =SUM(C114:D114) -> 0 | G114: ='Summary Total Pigs'!#REF!*'IAS 41 Mvmnt Pigs'!F114 -> #REF! | H114: ='Summary Total Pigs'!#REF!*'IAS 41 Mvmnt Pigs'!F114 -> #REF! | I114: =F114*'Summary Total Pigs'!#REF! -> #REF! | J114: =F114*'Summary Total Pigs'!AD231 -> 0 | K114: ='Summary Total Pigs'!#REF!*'IAS 41 Mvmnt Pigs'!F114 -> #REF! | L114: =E114+G114+H114+J114+K114+I114 -> #REF! | M114: 0 | N114: =+L114+M114 -> #REF! | O114: 0 | P114: =N114-O114 -> #REF!
A115: SOWS | B115: MAIN | C115: ='[16]IAS 41 Mvmnt Pigs'!$N115 -> 0 | D115: 0 | E115: =SUM(C115:D115) -> 0 | G115: ='Summary Total Pigs'!#REF!*'IAS 41 Mvmnt Pigs'!F115 -> #REF! | H115: ='Summary Total Pigs'!#REF!*'IAS 41 Mvmnt Pigs'!F115 -> #REF! | I115: =F115*'Summary Total Pigs'!#REF! -> #REF! | J115: =F115*'Summary Total Pigs'!AD232 -> 0 | K115: ='Summary Total Pigs'!#REF!*'IAS 41 Mvmnt Pigs'!F115 -> #REF! | L115: =E115+G115+H115+J115+K115+I115 -> #REF! | M115: 0 | N115: =+L115+M115 -> #REF! | O115: 0 | P115: =N115-O115 -> #REF!
A116: BOARS | C116: ='[16]IAS 41 Mvmnt Pigs'!$N116 -> 0 | D116: 0 | E116: =SUM(C116:D116) -> 0 | G116: ='Summary Total Pigs'!#REF!*'IAS 41 Mvmnt Pigs'!F116 -> #REF! | H116: ='Summary Total Pigs'!#REF!*'IAS 41 Mvmnt Pigs'!F116 -> #REF! | I116: =F116*'Summary Total Pigs'!#REF! -> #REF! | J116: =F116*'Summary Total Pigs'!AD233 -> 0 | K116: ='Summary Total Pigs'!#REF!*'IAS 41 Mvmnt Pigs'!F116 -> #REF! | L116: =E116+G116+H116+J116+K116+I116 -> #REF! | M116: 0 | N116: =+L116+M116 -> #REF! | O116: 0 | P116: =N116-O116 -> #REF!
A117: TOTAL | C117: =SUM(C111:C116) -> 3.4851191e+08 | D117: =SUM(D111:D115) -> #REF! | E117: =SUM(E111:E116) -> #REF! | F117: =SUM(F111:F116) -> #REF! | G117: =SUM(G111:G116) -> #REF! | H117: =SUM(H111:H116) -> #REF! | I117: =SUM(I111:I116) -> #REF! | J117: =SUM(J111:J116) -> #REF! | K117: =SUM(K111:K116) -> #REF! | L117: =SUM(L111:L116) -> #REF! | ... O117: =SUM(O111:O116) -> 3.8951658e+08 | P117: =N117-O117 -> #REF! | Q117: =[17]Sheet1!$J$16 -> -3.8946289e+08
Q118: =Q117+M117 -> -3.8946289e+08
A120: SITE: | B120: DZUMBUNU
A122: DESCRIPTION | B122: SITE | C122: OPENING | D122: TRANSFER IN | E122: TOTAL COST | F122: AVERAGE COST | G122: TRANSFER OUT | H122: SALES | I122: =I110 -> #REF! | J122: =+J110 -> CULLS | K122: =+K110 -> STOCK ADJMNT | L122: SUB TOTAL | M122: =+M110 -> CURRENT ADJMNT | N122: =+N110 -> CLOSING BAL | O122: CLOSING BAL
A123: PIGLETS | B123: MAIN | C123: ='[16]IAS 41 Mvmnt Pigs'!$N123 -> 0 | E123: =SUM(C123:D123) -> 0 | G123: ='Summary Total Pigs'!#REF!*'IAS 41 Mvmnt Pigs'!F123 -> #REF! | H123: ='Summary Total Pigs'!#REF!*'IAS 41 Mvmnt Pigs'!F123 -> #REF! | I123: =F123*'Summary Total Pigs'!#REF! -> #REF! | J123: =F123*'Summary Total Pigs'!AD240 -> 0 | K123: ='Summary Total Pigs'!#REF!*'IAS 41 Mvmnt Pigs'!F123 -> #REF! | L123: =E123+G123+H123+J123+K123+I123 -> #REF! | M123: 0 | N123: =+L123+M123 -> #REF! | O123: 0 | P123: =N123-O123 -> #REF!
...

Sheet USD
A1: COLCOM HOLDINGS LIMITED
T2: =+'Summary Total Pigs'!C3 -> 46226
A3: TRIPLE C PIGS
A5: LIVESTOCK ANALYSIS SCHEDULE
A7: =[23]USD!$A$7 -> COST USD
A10: SITE: | B10: GRASMERE FARM
A12: DESCRIPTION | B12: SITE | C12: OPENING | D12: PIG PURCHASES | E12: TRANSFER IN | F12: A I CONSUMMABLES | G12: BEDDING AND CONSUMMABLES | H12: CONSULTANCY FEES | I12: DIRECT STAFF COSTS | J12: STOCK FEED | K12: SUNDRY TOOLS | L12: VETERINARY | M12: TOTAL COST | N12: AVERAGE COST | O12: TRANSFER OUT | P12: SALES | Q12: ='Summary Total Pigs'!#REF! -> #REF! | R12: CULLS | S12: STOCK ADJMNT | T12: CLOSING
A13: PIGLETS | B13: MAIN | C13: =[16]USD!$T13 -> 170498.14 | F13: =E170 -> 0 | G13: =('Summary Total Pigs'!AE12+'Summary Total Pigs'!AE15+'Summary Total Pigs'!AE16+'Summary Total Pigs'!AE17)/'Summary Total Pigs'!#REF!*'Pigs Cost'!E171 -> #REF! | H13: =('Summary Total Pigs'!AE12+'Summary Total Pigs'!AE15+'Summary Total Pigs'!AE16+'Summary Total Pigs'!AE17)/'Summary Total Pigs'!#REF!*'Pigs Cost'!E172 -> #REF! | I13: =E173/3 -> 0 | J13: =('Summary Total Pigs'!AE12+'Summary Total Pigs'!AE15+'Summary Total Pigs'!AE16+'Summary Total Pigs'!AE17)/'Summary Total Pigs'!#REF!*J174 -> #REF! | K13: =('Summary Total Pigs'!AE12+'Summary Total Pigs'!AE15+'Summary Total Pigs'!AE16+'Summary Total Pigs'!AE17)/'Summary Total Pigs'!#REF!*'Pigs Cost'!E175 -> #REF! | L13: =('Summary Total Pigs'!AE12+'Summary Total Pigs'!AE15+'Summary Total Pigs'!AE16+'Summary Total Pigs'!AE17)/'Summary Total Pigs'!#REF!*'Pigs Cost'!J176 -> #REF! | M13: =SUM(C13:L13) -> #REF! | N13: =M13/'Summary Total Pigs'!#REF! -> #REF! | O13: =N13*'Summary Total Pigs'!#REF! -> #REF! | P13: =N13*'Summary Total Pigs'!X12 -> #REF! | Q13: ='Summary Total Pigs'!#REF!*N13 -> #REF! | R13: =N13*'Summary Total Pigs'!Z12 -> #REF! | S13: ='Summary Total Pigs'!#REF!*N13 -> #REF! | T13: =M13+O13+P13+R13+S13+Q13 -> #REF! | V13: =C13/$B$178 -> 1.7049814e-05
A14: WEANERS | B14: WEANER | C14: =[16]USD!$T14 -> 327744.46 | E14: ='Summary Total Pigs'!D13*N13 -> #REF! | G14: ='Summary Total Pigs'!AE13/'Summary Total Pigs'!#REF!*'Pigs Cost'!E171 -> #REF! | H14: ='Summary Total Pigs'!AE13/'Summary Total Pigs'!#REF!*'Pigs Cost'!E172 -> #REF! | I14: =I13 -> 0 | J14: ='Summary Total Pigs'!AE13/'Summary Total Pigs'!#REF!*J174 -> #REF! | K14: =('Summary Total Pigs'!AE13)/'Summary Total Pigs'!#REF!*'Pigs Cost'!E175 -> #REF! | L14: ='Summary Total Pigs'!AE13/'Summary Total Pigs'!#REF!*'Pigs Cost'!J176 -> #REF! | M14: =SUM(C14:L14) -> #REF! | N14: =M14/'Summary Total Pigs'!#REF! -> #REF! | O14: =N14*'Summary Total Pigs'!#REF! -> #REF! | P14: =N14*'Summary Total Pigs'!X13 -> #REF! | Q14: ='Summary Total Pigs'!#REF!*N14 -> #REF! | R14: =N14*'Summary Total Pigs'!Z13 -> #REF! | S14: ='Summary Total Pigs'!#REF!*N14 -> #REF! | T14: =M14+O14+P14+R14+S14+Q14 -> #REF! | V14: =C14/$B$178 -> 3.2774446e-05
A15: GROWERS | B15: GROWER | C15: =[16]USD!$T15 -> 1109796.3 | E15: =3838*N14+19*N16 -> #REF! | G15: ='Summary Total Pigs'!AE14/'Summary Total Pigs'!#REF!*'Pigs Cost'!E171 -> #REF! | H15: ='Summary Total Pigs'!AE14/'Summary Total Pigs'!#REF!*'Pigs Cost'!E172 -> #REF! | I15: =I14 -> 0 | J15: ='Summary Total Pigs'!AE14/'Summary Total Pigs'!#REF!*J174 -> #REF! | K15: =('Summary Total Pigs'!AE14)/'Summary Total Pigs'!#REF!*'Pigs Cost'!E175 -> #REF! | L15: ='Summary Total Pigs'!AE14/'Summary Total Pigs'!#REF!*'Pigs Cost'!J176 -> #REF! | M15: =SUM(C15:L15) -> #REF! | N15: =M15/'Summary Total Pigs'!#REF! -> #REF! | O15: =N15*'Summary Total Pigs'!#REF! -> #REF! | P15: =N15*'Summary Total Pigs'!X14 -> #REF! | Q15: ='Summary Total Pigs'!#REF!*N15 -> #REF! | R15: =N15*'Summary Total Pigs'!Z14 -> #REF! | S15: ='Summary Total Pigs'!#REF!*N15 -> #REF! | T15: =M15+O15+P15+R15+S15+Q15 -> #REF! | V15: =C15/$B$178 -> 0.00011097963
A16: GILTS | B16: MAIN | C16: =[16]USD!$T16 -> 56382.007 | D16: 0 | E16: =106*N13 -> #REF! | G16: 0 | H16: 0 | I16: 0 | J16: 0 | K16: 0 | L16: 0 | M16: =SUM(C16:L16) -> #REF! | N16: =M16/'Summary Total Pigs'!#REF! -> #REF! | O16: =N16*'Summary Total Pigs'!#REF! -> #REF! | P16: ='Summary Total Pigs'!X15*N16 -> #REF! | Q16: ='Summary Total Pigs'!#REF!*N16 -> #REF! | R16: =N16*'Summary Total Pigs'!Z15 -> #REF! | S16: ='Summary Total Pigs'!#REF!*N16 -> #REF! | T16: =M16+O16+P16+R16+S16+Q16 -> #REF! | V16: =C16/$B$178 -> 5.6382007e-06
A17: SOWS | B17: MAIN | C17: =[16]USD!$T17 -> 150254.39 | E17: ='Summary Total Pigs'!D16*N16 -> #REF! | G17: 0 | H17: 0 | I17: =I16 -> 0 | J17: 0 | K17: 0 | L17: 0 | M17: =SUM(C17:L17) -> #REF! | N17: =M17/'Summary Total Pigs'!#REF! -> #REF! | O17: =N17*'Summary Total Pigs'!#REF! -> #REF! | P17: =N17*'Summary Total Pigs'!X16 -> #REF! | Q17: ='Summary Total Pigs'!#REF!*N17 -> #REF! | R17: =N17*'Summary Total Pigs'!Z16 -> #REF! | S17: ='Summary Total Pigs'!#REF!*N17 -> #REF! | T17: =M17+O17+P17+R17+S17+Q17 -> #REF! | V17: =C17/$B$178 -> 1.5025439e-05
A18: BOARS | B18: AI | C18: =[16]USD!$T18 -> 4774.3468 | E18: ='Summary Total Pigs'!D17*N15 -> #REF! | F18: 0 | G18: 0 | H18: 0 | I18: =I17 -> 0 | J18: 0 | K18: 0 | L18: 0 | M18: =SUM(C18:L18) -> #REF! | N18: =M18/'Summary Total Pigs'!#REF! -> #REF! | O18: =N18*'Summary Total Pigs'!Q218 -> #REF! | P18: =N18*'Summary Total Pigs'!X17 -> #REF! | Q18: ='Summary Total Pigs'!#REF!*N18 -> #REF! | R18: =N18*'Summary Total Pigs'!Z17 -> #REF! | S18: ='Summary Total Pigs'!#REF!*N18 -> #REF! | T18: =M18+O18+P18+R18+S18+Q18 -> #REF! | V18: =C18/$B$178 -> 4.7743468e-07
A19: TOTAL | C19: =SUM(C13:C18) -> 1819449.6 | D19: =SUM(D13:D18) -> 0 | E19: =SUM(E13:E18) -> #REF! | F19: =SUM(F13:F18) -> 0 | G19: =SUM(G13:G18) -> #REF! | H19: =SUM(H13:H18) -> #REF! | I19: =SUM(I13:I18) -> 0 | J19: =SUM(J13:J18) -> #REF! | ... T19: =SUM(T13:T18) -> #REF! | V19: =C19/$B$178 -> 0.00018194496
E20: =E19+O19 -> #REF! | F20: =F19-E170 -> 0 | G20: =G19-E171 -> #REF! | H20: =H19-E172 -> #REF! | I20: =I19-E173 -> 0 | J20: =J19-J174 -> #REF! | K20: =K19-E175 -> #REF! | L20: =L19-E176 -> #REF! | M20: ='Summary Total Pigs'!#REF!*N15 -> #REF! | V20: =C20/$B$178 -> 0
L21: =+(G19+H19+I19+K19+L19+J19+F19)-J178 -> #REF! | M21: =E20-M20 -> #REF! | V21: =C21/$B$178 -> 0
A22: SITE: | B22: TRADE WINDS | V22: =C22/$B$178 -> 0
V23: =C23/$B$178 -> 0
A24: DESCRIPTION | B24: SITE | C24: =+C12 -> OPENING | D24: PIG PURCHASES | E24: TRANSFER IN | F24: A I CONSUMMABLES | G24: BEDDING AND CONSUMMABLES | H24: CONSULTANCY FEES | I24: DIRECT STAFF COSTS | J24: STOCK FEED | K24: SUNDRY TOOLS | L24: VETERINARY | M24: TOTAL COST | N24: AVERAGE COST | O24: TRANSFER OUT | P24: SALES | Q24: ='Summary Total Pigs'!#REF! -> #REF! | R24: =R12 -> CULLS | S24: =+S12 -> STOCK ADJMNT | T24: CLOSING | V24: =C24/$B$178 -> #VALUE!
A25: PIGLETS | B25: MAIN | C25: =[16]USD!$T25 -> 0 | E25: ='Summary Total Pigs'!#REF!*N23 -> #REF! | G25: =('Summary Total Pigs'!#REF!+'Summary Total Pigs'!#REF!)/'Summary Total Pigs'!#REF!*$G$171 -> #REF! | H25: =('Summary Total Pigs'!#REF!+'Summary Total Pigs'!#REF!)/'Summary Total Pigs'!#REF!*'Pigs Cost'!$G$172 -> #REF! | I25: =('Summary Total Pigs'!#REF!+'Summary Total Pigs'!#REF!)/'Summary Total Pigs'!#REF!*'Pigs Cost'!$G$173 -> #REF! | J25: =('Summary Total Pigs'!#REF!)/'Summary Total Pigs'!#REF!*$G$174 -> #REF! | K25: =('Summary Total Pigs'!#REF!/'Summary Total Pigs'!#REF!)*'Pigs Cost'!$G$175 -> #REF! | L25: =('Summary Total Pigs'!#REF!+'Summary Total Pigs'!#REF!)/'Summary Total Pigs'!#REF!*G176 -> #REF! | M25: =SUM(C25:L25) -> #REF! | N25: 0 | O25: =N25*'Summary Total Pigs'!#REF! -> #REF! | P25: =N25*'Summary Total Pigs'!#REF! -> #REF! | Q25: =N25*'Summary Total Pigs'!#REF! -> #REF! | R25: =N25*'Summary Total Pigs'!#REF! -> #REF! | S25: ='Summary Total Pigs'!#REF!*'Pigs Cost'!N25 -> #REF! | T25: =M25+O25+P25+R25+S25+Q25 -> #REF! | V25: =C25/$B$178 -> 0
A26: WEANERS | B26: WEANER | C26: =[16]USD!$T26 -> 0 | E26: 0 | G26: =('Summary Total Pigs'!#REF!)/'Summary Total Pigs'!#REF!*$G$171 -> #REF! | H26: =('Summary Total Pigs'!#REF!)/'Summary Total Pigs'!#REF!*'Pigs Cost'!G172 -> #REF! | I26: =('Summary Total Pigs'!#REF!)/'Summary Total Pigs'!#REF!*'Pigs Cost'!$G$173 -> #REF! | J26: =('Summary Total Pigs'!#REF!)/'Summary Total Pigs'!#REF!*$G$174 -> #REF! | K26: =('Summary Total Pigs'!#REF!/'Summary Total Pigs'!#REF!)*'Pigs Cost'!$G$175 -> #REF! | M26: =SUM(C26:L26) -> #REF! | N26: 0 | O26: =N26*'Summary Total Pigs'!#REF! -> #REF! | P26: =N26*'Summary Total Pigs'!#REF! -> #REF! | Q26: =N26*'Summary Total Pigs'!#REF! -> #REF! | R26: =N26*'Summary Total Pigs'!#REF! -> #REF! | S26: ='Summary Total Pigs'!#REF!*'Pigs Cost'!N26 -> #REF! | T26: =M26+O26+P26+R26+S26+Q26 -> #REF! | V26: =C26/$B$178 -> 0
A27: GROWERS | B27: GROWER | C27: =[16]USD!$T27 -> 20589.682 | E27: =N101*'Summary Total Pigs'!#REF! -> #REF! | G27: =('Summary Total Pigs'!#REF!)/'Summary Total Pigs'!#REF!*$G$171 -> #REF! | H27: =('Summary Total Pigs'!#REF!)/'Summary Total Pigs'!#REF!*'Pigs Cost'!$G$172 -> #REF! | I27: =('Summary Total Pigs'!#REF!)/'Summary Total Pigs'!#REF!*'Pigs Cost'!$G$173 -> #REF! | J27: =('Summary Total Pigs'!#REF!)/'Summary Total Pigs'!#REF!*$G$174 -> #REF! | K27: =('Summary Total Pigs'!#REF!/'Summary Total Pigs'!#REF!)*'Pigs Cost'!$G$175 -> #REF! | L27: ='Summary Total Pigs'!#REF!/'Summary Total Pigs'!#REF!*G176 -> #REF! | M27: =SUM(C27:L27) -> #REF! | N27: =M27/'Summary Total Pigs'!#REF! -> #REF! | O27: =N27*'Summary Total Pigs'!#REF! -> #REF! | P27: =N27*'Summary Total Pigs'!#REF! -> #REF! | Q27: =N27*'Summary Total Pigs'!#REF! -> #REF! | R27: =N27*'Summary Total Pigs'!#REF! -> #REF! | S27: ='Summary Total Pigs'!#REF!*'Pigs Cost'!N27 -> #REF! | T27: =M27+O27+P27+R27+S27+Q27 -> #REF! | V27: =C27/$B$178 -> 2.0589682e-06
A28: GILTS | B28: MAIN | C28: =[16]USD!$T28 -> 0 | E28: ='Summary Total Pigs'!#REF!*N26 -> #REF! | K28: =('Summary Total Pigs'!#REF!/'Summary Total Pigs'!#REF!)*'Pigs Cost'!$G$175 -> #REF! | M28: 0 | O28: =N28*'Summary Total Pigs'!#REF! -> #REF! | P28: =N28*'Summary Total Pigs'!#REF! -> #REF! | Q28: =N28*'Summary Total Pigs'!#REF! -> #REF! | R28: =N28*'Summary Total Pigs'!#REF! -> #REF! | S28: ='Summary Total Pigs'!#REF!*'Pigs Cost'!N28 -> #REF! | T28: =M28+O28+P28+R28+S28+Q28 -> #REF! | V28: =C28/$B$178 -> 0
A29: SOWS | B29: MAIN | C29: =[16]USD!$T29 -> 0 | E29: 0 | H29: =('Summary Total Pigs'!#REF!)/'Summary Total Pigs'!#REF!*'Pigs Cost'!$G$172 -> #REF! | K29: =('Summary Total Pigs'!#REF!/'Summary Total Pigs'!#REF!)*'Pigs Cost'!$G$175 -> #REF! | M29: =SUM(C29:L29) -> #REF! | O29: =N29*'Summary Total Pigs'!#REF! -> #REF! | P29: =N29*'Summary Total Pigs'!#REF! -> #REF! | Q29: =N29*'Summary Total Pigs'!#REF! -> #REF! | R29: =N29*'Summary Total Pigs'!#REF! -> #REF! | S29: ='Summary Total Pigs'!#REF!*'Pigs Cost'!N29 -> #REF! | T29: =M29+O29+P29+R29+S29+Q29 -> #REF! | V29: =C29/$B$178 -> 0
A30: BOARS | C30: =[16]USD!$T30 -> 0 | E30: ='Summary Total Pigs'!#REF!*N28 -> #REF! | K30: =('Summary Total Pigs'!#REF!/'Summary Total Pigs'!#REF!)*'Pigs Cost'!$G$175 -> #REF! | M30: =SUM(C30:L30) -> #REF! | O30: =N30*'Summary Total Pigs'!#REF! -> #REF! | Q30: =N30*'Summary Total Pigs'!#REF! -> #REF! | R30: =N30*'Summary Total Pigs'!#REF! -> #REF! | S30: ='Summary Total Pigs'!#REF!*'Pigs Cost'!N30 -> #REF! | T30: =M30+O30+P30+R30+S30+Q30 -> #REF! | V30: =C30/$B$178 -> 0
A31: TOTAL | C31: =SUM(C25:C30) -> 20589.682 | D31: =SUM(D25:D30) -> 0 | E31: =SUM(E25:E30) -> #REF! | F31: =SUM(F25:F30) -> 0 | G31: =SUM(G25:G30) -> #REF! | H31: =SUM(H25:H30) -> #REF! | I31: =SUM(I25:I30) -> #REF! | J31: =SUM(J25:J30) -> #REF! | ... T31: =SUM(T25:T30) -> #REF! | V31: =C31/$B$178 -> 2.0589682e-06
J32: =J31-G174 -> #REF! | K32: =+K31-G175 -> #REF! | V32: =C32/$B$178 -> 0
L33: =+(G31+H31+I31+K31+L31+J31)-G178 -> #REF! | V33: =C33/$B$178 -> 0
A34: SITE: | B34: ZIMBO | V34: =C34/$B$178 -> 0
V35: =C35/$B$178 -> 0
A36: DESCRIPTION | B36: SITE | C36: =+C24 -> OPENING | D36: PIG PURCHASES | E36: TRANSFER IN | F36: A I CONSUMMABLES | G36: BEDDING AND CONSUMMABLES | H36: CONSULTANCY FEES | I36: DIRECT STAFF COSTS | J36: STOCK FEED | K36: SUNDRY TOOLS | L36: VETERINARY | M36: TOTAL COST | N36: AVERAGE COST | O36: TRANSFER OUT | P36: SALES | Q36: ='Summary Total Pigs'!W49 -> Deaths | R36: =R24 -> CULLS | S36: =+S24 -> STOCK ADJMNT | T36: CLOSING | V36: =C36/$B$178 -> #VALUE!
A37: PIGLETS | B37: MAIN | C37: =[16]USD!$T37 -> 347.53472 | E37: ='Summary Total Pigs'!D50*N35 -> 0 | F37: =+$H$169*'Summary Total Pigs'!#REF!/'Summary Total Pigs'!#REF! -> #REF! | G37: =('Summary Total Pigs'!AE50+'Summary Total Pigs'!AE54)/'Summary Total Pigs'!AE56*'Pigs Cost'!$H$171 -> 0 | H37: =('Summary Total Pigs'!AE50+'Summary Total Pigs'!$AE$54)/'Summary Total Pigs'!$AE$56*'Pigs Cost'!$H$172 -> 0 | I37: =('Summary Total Pigs'!AE50+'Summary Total Pigs'!$AE$54)/'Summary Total Pigs'!$AE$56*'Pigs Cost'!$H$173 -> 0 | J37: =('Summary Total Pigs'!AE50+'Summary Total Pigs'!AE53+'Summary Total Pigs'!AE54+'Summary Total Pigs'!AE55)/'Summary Total Pigs'!$AE$56*$H$174 -> 2286.0914 | K37: =('Summary Total Pigs'!AE50+'Summary Total Pigs'!$AE$54)/'Summary Total Pigs'!$AE$56*'Pigs Cost'!$H$175 -> 0 | L37: =('Summary Total Pigs'!$AE$50+'Summary Total Pigs'!$AE$54)/'Summary Total Pigs'!$AE$56*'Pigs Cost'!$H$176 -> 0 | M37: =SUM(C37:L37) -> #REF! | N37: =M37/'Summary Total Pigs'!#REF! -> #REF! | O37: ='Summary Total Pigs'!N50*N37 -> #REF! | P37: =N37*'Summary Total Pigs'!#REF! -> #REF! | Q37: =N37*'Summary Total Pigs'!W50 -> #REF! | R37: ='Summary Total Pigs'!X50*N37 -> #REF! | S37: ='Summary Total Pigs'!AD50*'Pigs Cost'!N37 -> #REF! | T37: =M37+O37+P37+R37+S37+Q37 -> #REF! | V37: =C37/$B$178 -> 3.4753472e-08
A38: WEANERS | B38: WEANER | C38: =[16]USD!$T38 -> -1.1368684e-13 | E38: ='Summary Total Pigs'!D51*N37 -> #REF! | F38: =+$H$169*'Summary Total Pigs'!#REF!/'Summary Total Pigs'!#REF! -> #REF! | G38: =('Summary Total Pigs'!AE51)/'Summary Total Pigs'!$AE$56*'Pigs Cost'!$H$171 -> 0 | H38: =('Summary Total Pigs'!AE51)/'Summary Total Pigs'!$AE$56*'Pigs Cost'!$H$172 -> 0 | I38: =('Summary Total Pigs'!AE51)/'Summary Total Pigs'!$AE$56*'Pigs Cost'!$H$173 -> 0 | J38: =('Summary Total Pigs'!AE51)/'Summary Total Pigs'!$AE$56*'Pigs Cost'!$H$174 -> 1.471066e+12 | K38: =('Summary Total Pigs'!AE51)/'Summary Total Pigs'!$AE$56*'Pigs Cost'!$H$175 -> 0 | L38: =('Summary Total Pigs'!AE51)/'Summary Total Pigs'!$AE$56*'Pigs Cost'!$H$176 -> 0 | M38: =SUM(C38:L38) -> #REF! | O38: ='Summary Total Pigs'!N51*N38 -> 0 | P38: =N38*'Summary Total Pigs'!#REF! -> #REF! | Q38: =N38*'Summary Total Pigs'!W51 -> 0 | R38: ='Summary Total Pigs'!X51*N38 -> 0 | S38: ='Summary Total Pigs'!AD51*'Pigs Cost'!N38 -> 0 | T38: =M38+O38+P38+R38+S38+Q38 -> #REF! | V38: =C38/$B$178 -> -1.1368684e-23
A39: GROWERS | B39: GROWER | C39: =[16]USD!$T39 -> 0 | F39: =+$H$169*'Summary Total Pigs'!#REF!/'Summary Total Pigs'!#REF! -> #REF! | G39: =('Summary Total Pigs'!AE52)/'Summary Total Pigs'!$AE$56*'Pigs Cost'!$H$171 -> 0 | H39: =('Summary Total Pigs'!AE52)/'Summary Total Pigs'!$AE$56*'Pigs Cost'!$H$172 -> 0 | I39: =('Summary Total Pigs'!AE52)/'Summary Total Pigs'!$AE$56*'Pigs Cost'!$H$173 -> 0 | J39: =('Summary Total Pigs'!AE52)/'Summary Total Pigs'!$AE$56*'Pigs Cost'!$H$174 -> 2.8001269e+12 | K39: =('Summary Total Pigs'!AE52)/'Summary Total Pigs'!$AE$56*'Pigs Cost'!$H$175 -> 0 | L39: =('Summary Total Pigs'!AE52)/'Summary Total Pigs'!$AE$56*'Pigs Cost'!$H$176 -> 0 | M39: =SUM(C39:L39) -> #REF! | O39: ='Summary Total Pigs'!N52*N39 -> 0 | P39: =N39*'Summary Total Pigs'!#REF! -> #REF! | Q39: =N39*'Summary Total Pigs'!W52 -> 0 | R39: ='Summary Total Pigs'!X52*N39 -> 0 | S39: ='Summary Total Pigs'!AD52*'Pigs Cost'!N39 -> 0 | T39: =M39+O39+P39+R39+S39+Q39 -> #REF! | V39: =C39/$B$178 -> 0
A40: GILTS | B40: MAIN | C40: =[16]USD!$T40 -> 1594.9131 | E40: =N66*'Summary Total Pigs'!D53 -> #REF! | F40: =+$H$169*'Summary Total Pigs'!#REF!/'Summary Total Pigs'!#REF! -> #REF! | G40: =('Summary Total Pigs'!AE53)/'Summary Total Pigs'!$AE$56*'Pigs Cost'!$H$171 -> 0 | H40: =('Summary Total Pigs'!AE53)/'Summary Total Pigs'!$AE$56*'Pigs Cost'!$H$172 -> 0 | I40: =('Summary Total Pigs'!AE53)/'Summary Total Pigs'!$AE$56*'Pigs Cost'!$H$173 -> 0 | J40: 0 | K40: =('Summary Total Pigs'!AE53)/'Summary Total Pigs'!$AE$56*'Pigs Cost'!$H$175 -> 0 | L40: =('Summary Total Pigs'!AE53)/'Summary Total Pigs'!$AE$56*'Pigs Cost'!$H$176 -> 0 | M40: =SUM(C40:L40) -> #REF! | N40: =M40/'Summary Total Pigs'!#REF! -> #REF! | O40: ='Summary Total Pigs'!N53*N40 -> #REF! | P40: =N40*'Summary Total Pigs'!#REF! -> #REF! | Q40: =N40*'Summary Total Pigs'!W53 -> #REF! | R40: ='Summary Total Pigs'!X53*N40 -> #REF! | S40: ='Summary Total Pigs'!AD53*'Pigs Cost'!N40 -> #REF! | T40: =M40+O40+P40+R40+S40+Q40 -> #REF! | V40: =C40/$B$178 -> 1.5949131e-07
A41: SOWS | B41: MAIN | C41: =[16]USD!$T41 -> 28570.933 | E41: =N40*'Summary Total Pigs'!D54 -> #REF! | F41: =+$H$169*'Summary Total Pigs'!#REF!/'Summary Total Pigs'!#REF! -> #REF! | J41: 0 | K41: =('Summary Total Pigs'!AE53)/'Summary Total Pigs'!$AE$56*'Pigs Cost'!$H$175 -> 0 | L41: =H176 -> 0 | M41: =SUM(C41:L41) -> #REF! | N41: =M41/'Summary Total Pigs'!#REF! -> #REF! | O41: ='Summary Total Pigs'!N54*N41 -> #REF! | P41: =N41*'Summary Total Pigs'!#REF! -> #REF! | Q41: =N41*'Summary Total Pigs'!W54 -> #REF! | R41: ='Summary Total Pigs'!X54*N41 -> #REF! | S41: ='Summary Total Pigs'!AD54*'Pigs Cost'!N41 -> #REF! | T41: =M41+O41+P41+R41+S41+Q41 -> #REF! | V41: =C41/$B$178 -> 2.8570933e-06
A42: BOARS | C42: =[16]USD!$T42 -> 455.7258 | J42: 0 | M42: =SUM(C42:L42) -> 455.7258 | N42: =M42/'Summary Total Pigs'!#REF! -> #REF! | O42: ='Summary Total Pigs'!N55*N42 -> #REF! | P42: =N42*'Summary Total Pigs'!#REF! -> #REF! | Q42: =N42*'Summary Total Pigs'!W55 -> #REF! | R42: ='Summary Total Pigs'!X55*N42 -> #REF! | S42: ='Summary Total Pigs'!AD55*'Pigs Cost'!N42 -> #REF! | T42: =M42+O42+P42+R42+S42+Q42 -> #REF! | V42: =C42/$B$178 -> 4.557258e-08
A43: TOTAL | C43: =SUM(C37:C42) -> 30969.107 | D43: =SUM(D37:D42) -> 0 | E43: =SUM(E37:E42) -> #REF! | F43: =SUM(F37:F42) -> #REF! | G43: =SUM(G37:G42) -> 0 | H43: =SUM(H37:H42) -> 0 | I43: =SUM(I37:I42) -> 0 | J43: =SUM(J37:J42) -> 4.2711929e+12 | ... T43: =SUM(T37:T42) -> #REF! | V43: =C43/$B$178 -> 3.0969107e-06
J44: =J43-H174 -> 4.2711929e+12 | P44: 0 | V44: =C44/$B$178 -> 0
L45: =+(G43+H43+I43+K43+L43+J43)-H178 -> 4.2711929e+12 | V45: =C45/$B$178 -> 0
V46: =C46/$B$178 -> 0
V47: =C47/$B$178 -> 0
V48: =C48/$B$178 -> 0
A49: SITE: | B49: ROGATE | V49: =C49/$B$178 -> 0
V50: =C50/$B$178 -> 0
A51: DESCRIPTION | B51: SITE | C51: =+C36 -> OPENING | D51: PIG PURCHASES | E51: TRANSFER IN | F51: A I CONSUMMABLES | G51: BEDDING AND CONSUMMABLES | H51: CONSULTANCY FEES | I51: DIRECT STAFF COSTS | J51: STOCK FEED | K51: SUNDRY TOOLS | L51: VETERINARY | M51: TOTAL COST | N51: AVERAGE COST | O51: TRANSFER OUT | P51: SALES | Q51: =Q36 -> Deaths | R51: =R36 -> CULLS | S51: =+S36 -> STOCK ADJMNT | T51: CLOSING | V51: =C51/$B$178 -> #VALUE!
A52: PIGLETS | B52: MAIN | C52: =[16]USD!$T52 -> 5268.2208 | E52: ='Summary Total Pigs'!D89*N37 -> #REF! | G52: =('Summary Total Pigs'!$AE$89+'Summary Total Pigs'!$AE$93)/'Summary Total Pigs'!$AE$95*'Pigs Cost'!$H$171 -> 0 | H52: =('Summary Total Pigs'!$AE$89+'Summary Total Pigs'!$AE$93)/'Summary Total Pigs'!$AE$95*'Pigs Cost'!$K$172 -> 0 | I52: =('Summary Total Pigs'!$AE$89+'Summary Total Pigs'!$AE$93)/'Summary Total Pigs'!$AE$95*'Pigs Cost'!$K$173 -> 0 | J52: =('Summary Total Pigs'!AE89+'Summary Total Pigs'!AE92+'Summary Total Pigs'!AE93+'Summary Total Pigs'!AE94)/'Summary Total Pigs'!$AE$95*$K$174 -> 5952.3838 | K52: =('Summary Total Pigs'!AE89)/'Summary Total Pigs'!$AE$95*'Pigs Cost'!$K$175 -> 0 | L52: =('Summary Total Pigs'!$AE$89+'Summary Total Pigs'!$AE$93)/'Summary Total Pigs'!$AE$95*'Pigs Cost'!$K$176 -> 0 | M52: =SUM(C52:L52) -> #REF! | N52: =M52/'Summary Total Pigs'!M89 -> #REF! | O52: ='Summary Total Pigs'!N89*N52 -> #REF! | Q52: =N52*'Summary Total Pigs'!#REF! -> #REF! | R52: =N52*'Summary Total Pigs'!Z89 -> #REF! | S52: ='Summary Total Pigs'!#REF!*N52 -> #REF! | T52: =M52+O52+P52+R52+S52+Q52 -> #REF! | V52: =C52/$B$178 -> 5.2682208e-07
A53: WEANERS | B53: WEANER | C53: =[16]USD!$T53 -> 9194.0021 | E53: ='Summary Total Pigs'!D90*N52 -> #REF! | G53: =('Summary Total Pigs'!AE90)/'Summary Total Pigs'!$AE$95*'Pigs Cost'!$H$171 -> 0 | H53: =('Summary Total Pigs'!AE90)/'Summary Total Pigs'!$AE$95*'Pigs Cost'!$K$172 -> 0 | I53: =('Summary Total Pigs'!AE90)/'Summary Total Pigs'!$AE$95*'Pigs Cost'!$K$173 -> 0 | J53: =('Summary Total Pigs'!AE90)/'Summary Total Pigs'!$AE$95*$K$174 -> 3729.1142 | K53: =('Summary Total Pigs'!$AE$90)/'Summary Total Pigs'!$AE$95*'Pigs Cost'!$K$175 -> 0 | L53: =('Summary Total Pigs'!AE90)/'Summary Total Pigs'!$AE$95*'Pigs Cost'!$K$175 -> 0 | M53: =SUM(C53:L53) -> #REF! | N53: =M53/'Summary Total Pigs'!M90 -> #REF! | O53: ='Summary Total Pigs'!N90*N53 -> #REF! | P53: 0 | Q53: =N53*'Summary Total Pigs'!#REF! -> #REF! | R53: =N53*'Summary Total Pigs'!Z90 -> #REF! | S53: ='Summary Total Pigs'!#REF!*N53 -> #REF! | T53: =M53+O53+P53+R53+S53+Q53 -> #REF! | V53: =C53/$B$178 -> 9.1940021e-07
A54: GROWERS | B54: GROWER | C54: =[16]USD!$T54 -> 18907.912 | E54: ='Summary Total Pigs'!D91*N77 -> #REF! | G54: =('Summary Total Pigs'!AE91)/'Summary Total Pigs'!$AE$95*'Pigs Cost'!$H$171 -> 0 | H54: =('Summary Total Pigs'!AE91)/'Summary Total Pigs'!$AE$95*'Pigs Cost'!$K$172 -> 0 | I54: =('Summary Total Pigs'!AE91)/'Summary Total Pigs'!$AE$95*'Pigs Cost'!$K$173 -> 0 | J54: =('Summary Total Pigs'!AE91)/'Summary Total Pigs'!$AE$95*$K$174 -> 8078.502 | K54: =('Summary Total Pigs'!AE91)/'Summary Total Pigs'!$AE$95*'Pigs Cost'!$K$175 -> 0 | L54: =('Summary Total Pigs'!AE91)/'Summary Total Pigs'!$AE$95*'Pigs Cost'!$K$175 -> 0 | M54: =SUM(C54:L54) -> #REF! | N54: =M54/'Summary Total Pigs'!M91 -> #REF! | O54: ='Summary Total Pigs'!N94*N54 -> #REF! | P54: ='Summary Total Pigs'!#REF!*N54 -> #REF! | Q54: =N54*'Summary Total Pigs'!#REF! -> #REF! | R54: =N54*'Summary Total Pigs'!Z91 -> #REF! | S54: ='Summary Total Pigs'!#REF!*N54 -> #REF! | T54: =M54+O54+P54+R54+S54+Q54 -> #REF! | V54: =C54/$B$178 -> 1.8907912e-06
A55: GILTS | B55: MAIN | C55: =[16]USD!$T55 -> -370.42679 | E55: =15*N54+10*N15 -> #REF! | G55: =('Summary Total Pigs'!AE92)/'Summary Total Pigs'!$AE$95*'Pigs Cost'!$K$171 -> 0 | H55: =('Summary Total Pigs'!AE92)/'Summary Total Pigs'!$AE$95*'Pigs Cost'!$K$172 -> 0 | I55: =('Summary Total Pigs'!AE92)/'Summary Total Pigs'!$AE$95*'Pigs Cost'!$K$173 -> 0 | J55: 0 | K55: =('Summary Total Pigs'!AE92)/'Summary Total Pigs'!$AE$95*'Pigs Cost'!$K$175 -> 0 | L55: =('Summary Total Pigs'!AE92)/'Summary Total Pigs'!$AE$95*'Pigs Cost'!$K$176 -> 0 | M55: =SUM(C55:L55) -> #REF! | N55: =M55/'Summary Total Pigs'!M92 -> #REF! | O55: ='Summary Total Pigs'!N92*N55 -> #REF! | P55: ='Summary Total Pigs'!#REF!*N55 -> #REF! | Q55: =N55*'Summary Total Pigs'!#REF! -> #REF! | R55: =N55*'Summary Total Pigs'!Z92 -> #REF! | S55: ='Summary Total Pigs'!#REF!*N55 -> #REF! | T55: =M55+O55+P55+R55+S55+Q55 -> #REF! | V55: =C55/$B$178 -> -3.7042679e-08
A56: SOWS | B56: MAIN | C56: =[16]USD!$T56 -> 26248.31 | E56: =N55*'Summary Total Pigs'!D93 -> #REF! | H56: =('Summary Total Pigs'!AE93)/'Summary Total Pigs'!$AE$95*'Pigs Cost'!$H$171 -> 0 | J56: 0 | K56: =('Summary Total Pigs'!AE93)/'Summary Total Pigs'!$AE$95*'Pigs Cost'!$K$175 -> 0 | L56: =('Summary Total Pigs'!AE93)/'Summary Total Pigs'!$AE$95*'Pigs Cost'!$K$176 -> 0 | M56: =SUM(C56:L56) -> #REF! | N56: =M56/'Summary Total Pigs'!M93 -> #REF! | O56: ='Summary Total Pigs'!N93*N56 -> #REF! | P56: ='Summary Total Pigs'!#REF!*N56 -> #REF! | Q56: =N56*'Summary Total Pigs'!#REF! -> #REF! | R56: =N56*'Summary Total Pigs'!Z93 -> #REF! | S56: ='Summary Total Pigs'!#REF!*N56 -> #REF! | T56: =M56+O56+P56+R56+S56+Q56 -> #REF! | V56: =C56/$B$178 -> 2.624831e-06
A57: BOARS | C57: =[16]USD!$T57 -> 455.7258 | E57: ='Summary Total Pigs'!D94*N56 -> #REF! | J57: 0 | M57: =SUM(C57:L57) -> #REF! | N57: =M57/'Summary Total Pigs'!M94 -> #REF! | O57: ='Summary Total Pigs'!#REF!*N57 -> #REF! | P57: =N57*'Summary Total Pigs'!#REF! -> #REF! | Q57: =N57*'Summary Total Pigs'!#REF! -> #REF! | R57: =N57*'Summary Total Pigs'!Z94 -> #REF! | S57: ='Summary Total Pigs'!#REF!*N57 -> #REF! | T57: =M57+O57+P57+R57+S57+Q57 -> #REF! | V57: =C57/$B$178 -> 4.557258e-08
A58: TOTAL | C58: =SUM(C52:C57) -> 59703.745 | D58: =SUM(D52:D57) -> 0 | E58: =SUM(E52:E57) -> #REF! | F58: =SUM(F52:F57) -> 0 | G58: =SUM(G52:G57) -> 0 | H58: =SUM(H52:H57) -> 0 | I58: =SUM(I52:I57) -> 0 | J58: =SUM(J52:J57) -> 17760 | ... T58: =SUM(T52:T57) -> #REF! | V58: =C58/$B$178 -> 5.9703745e-06
J59: =J58-K174 -> 0 | V59: =C59/$B$178 -> 0
A60: SITE: | B60: QUARANTINE | E60: =-16*N16 -> #REF! | V60: =C60/$B$178 -> 0
V61: =C61/$B$178 -> 0
A62: DESCRIPTION | B62: SITE | C62: =+C51 -> OPENING | D62: PIG PURCHASES | E62: TRANSFER IN | F62: A I CONSUMMABLES | G62: BEDDING AND CONSUMMABLES | H62: CONSULTANCY FEES | I62: DIRECT STAFF COSTS | J62: STOCK FEED | K62: SUNDRY TOOLS | L62: VETERINARY | M62: TOTAL COST | N62: AVERAGE COST | O62: TRANSFER OUT | P62: SALES | Q62: =Q51 -> Deaths | R62: =R51 -> CULLS | S62: =+S51 -> STOCK ADJMNT | T62: CLOSING | V62: =C62/$B$178 -> #VALUE!
A63: PIGLETS | B63: MAIN | C63: =[16]USD!$T63 -> 0 | E63: ='Summary Total Pigs'!D130*N61 -> 0 | J63: 0 | M63: =SUM(C63:L63) -> 0 | O63: ='Summary Total Pigs'!Q127*N63 -> 0 | P63: =N63*'Summary Total Pigs'!Z127 -> 0 | Q63: =N63*'Summary Total Pigs'!AB127 -> 0 | R63: ='Summary Total Pigs'!AD127*N63 -> 0 | S63: ='Summary Total Pigs'!AG127*'Pigs Cost'!N63 -> 0 | T63: =M63+O63+P63+R63+S63+Q63 -> 0 | V63: =C63/$B$178 -> 0
A64: WEANERS | B64: WEANER | C64: =[16]USD!$T64 -> 0 | E64: 0 | J64: 0 | M64: =SUM(C64:L64) -> 0 | O64: ='Summary Total Pigs'!Q128*N64 -> 0 | P64: =N64*'Summary Total Pigs'!Z128 -> 0 | Q64: =N64*'Summary Total Pigs'!AB128 -> 0 | R64: ='Summary Total Pigs'!AD128*N64 -> 0 | S64: ='Summary Total Pigs'!AG128*'Pigs Cost'!N64 -> 0 | T64: =M64+O64+P64+R64+S64+Q64 -> 0 | V64: =C64/$B$178 -> 0
A65: GROWERS | B65: GROWER | C65: =[16]USD!$T65 -> 0 | E65: 0 | J65: 0 | M65: =SUM(C65:L65) -> 0 | O65: ='Summary Total Pigs'!Q129*N65 -> 0 | P65: =N65*'Summary Total Pigs'!Z129 -> 0 | Q65: =N65*'Summary Total Pigs'!AB129 -> 0 | R65: ='Summary Total Pigs'!AD129*N65 -> 0 | S65: ='Summary Total Pigs'!AG129*'Pigs Cost'!N65 -> 0 | T65: =M65+O65+P65+R65+S65+Q65 -> 0 | V65: =C65/$B$178 -> 0
A66: GILTS | B66: MAIN | C66: =[16]USD!$T66 -> 13603.671 | E66: ='Summary Total Pigs'!D130*N15 -> #REF! | J66: =USD!I174 -> 480 | M66: =SUM(C66:L66) -> #REF! | N66: =+M66/'Summary Total Pigs'!P130 -> #REF! | O66: ='Summary Total Pigs'!Q130*N66 -> #REF! | P66: =N66*'Summary Total Pigs'!Z130 -> #REF! | Q66: =N66*'Summary Total Pigs'!AB130 -> #REF! | R66: ='Summary Total Pigs'!AD130*N66 -> #REF! | S66: ='Summary Total Pigs'!AG130*'Pigs Cost'!N66 -> #REF! | T66: =M66+O66+P66+R66+S66+Q66 -> #REF! | V66: =C66/$B$178 -> 1.3603671e-06
A67: SOWS | B67: MAIN | C67: =[16]USD!$T67 -> 0 | E67: 0 | J67: 0 | M67: =SUM(C67:L67) -> 0 | N67: 0 | O67: ='Summary Total Pigs'!Q131*N67 -> 0 | P67: =N67*'Summary Total Pigs'!Z131 -> 0 | Q67: =N67*'Summary Total Pigs'!AB131 -> 0 | R67: ='Summary Total Pigs'!AD131*N67 -> 0 | S67: ='Summary Total Pigs'!AG131*'Pigs Cost'!N67 -> 0 | T67: =M67+O67+P67+R67+S67+Q67 -> 0 | V67: =C67/$B$178 -> 0
A68: BOARS | C68: =[16]USD!$T68 -> 151.9086 | E68: ='Summary Total Pigs'!D132*N18 -> #REF! | J68: 0 | M68: =SUM(C68:L68) -> #REF! | N68: 0 | O68: ='Summary Total Pigs'!Q132*N68 -> 0 | P68: =N68*'Summary Total Pigs'!Z132 -> 0 | Q68: =N68*'Summary Total Pigs'!AB132 -> 0 | R68: ='Summary Total Pigs'!AD132*N68 -> 0 | S68: ='Summary Total Pigs'!AG132*'Pigs Cost'!N68 -> 0 | T68: =M68+O68+P68+R68+S68+Q68 -> #REF! | V68: =C68/$B$178 -> 1.519086e-08
A69: TOTAL | C69: =SUM(C63:C68) -> 13755.579 | D69: =SUM(D63:D68) -> 0 | E69: =SUM(E63:E68) -> #REF! | F69: =SUM(F63:F68) -> 0 | G69: =SUM(G63:G68) -> 0 | H69: =SUM(H63:H68) -> 0 | I69: =SUM(I63:I68) -> 0 | J69: =SUM(J63:J68) -> 480 | ... T69: =SUM(T63:T68) -> #REF! | V69: =C69/$B$178 -> 1.3755579e-06
J70: =J69-I174 -> 0 | V70: =C70/$B$178 -> 0
L71: =+(G69+H69+I69+K69+L69+J69)-I178 -> 0 | V71: =C71/$B$178 -> 0
A72: SITE: | B72: OSWA | L72: =+(G70+H70+I70+K70+L70+J70)-K190 -> 0 | V72: =C72/$B$178 -> 0
V73: =C73/$B$178 -> 0
A74: DESCRIPTION | B74: SITE | C74: =+C62 -> OPENING | D74: PIG PURCHASES | E74: TRANSFER IN | F74: A I CONSUMMABLES | G74: BEDDING AND CONSUMMABLES | H74: CONSULTANCY FEES | I74: DIRECT STAFF COSTS | J74: STOCK FEED | K74: SUNDRY TOOLS | L74: VETERINARY | M74: TOTAL COST | N74: AVERAGE COST | O74: TRANSFER OUT | P74: SALES | Q74: =Q62 -> Deaths | R74: =R62 -> CULLS | S74: =+S62 -> STOCK ADJMNT | T74: CLOSING | V74: =C74/$B$178 -> #VALUE!
A75: PIGLETS | B75: MAIN | C75: =[16]USD!$T75 -> 8543.703 | E75: ='Summary Total Pigs'!#REF!*N73 -> #REF! | J75: =('Summary Total Pigs'!#REF!+'Summary Total Pigs'!#REF!+'Summary Total Pigs'!#REF!+'Summary Total Pigs'!#REF!)/'Summary Total Pigs'!#REF!*$L$174 -> #REF! | K75: =('Summary Total Pigs'!#REF!/'Summary Total Pigs'!#REF!)*'Pigs Cost'!$L$175 -> #REF! | M75: =SUM(C75:L75) -> #REF! | N75: =+M75/'Summary Total Pigs'!#REF! -> #REF! | O75: =N75*'Summary Total Pigs'!#REF! -> #REF! | P75: =N75*'Summary Total Pigs'!#REF! -> #REF! | Q75: ='Summary Total Pigs'!#REF!*'Pigs Cost'!N75 -> #REF! | R75: =N75*'Summary Total Pigs'!#REF! -> #REF! | S75: ='Summary Total Pigs'!#REF!*'Pigs Cost'!N75 -> #REF! | T75: =M75+O75+P75+R75+S75+Q75 -> #REF! | V75: =C75/$B$178 -> 8.543703e-07
A76: WEANERS | B76: WEANER | C76: =[16]USD!$T76 -> 35951.326 | E76: =+'Summary Total Pigs'!#REF!*N75 -> #REF! | J76: =('Summary Total Pigs'!#REF!)/'Summary Total Pigs'!#REF!*$L$174 -> #REF! | K76: =('Summary Total Pigs'!#REF!/'Summary Total Pigs'!#REF!)*'Pigs Cost'!$L$175 -> #REF! | M76: =SUM(C76:L76) -> #REF! | N76: =+M76/'Summary Total Pigs'!#REF! -> #REF! | O76: =N76*'Summary Total Pigs'!#REF! -> #REF! | P76: =N76*'Summary Total Pigs'!#REF! -> #REF! | Q76: ='Summary Total Pigs'!#REF!*N76 -> #REF! | R76: =N76*'Summary Total Pigs'!#REF! -> #REF! | S76: ='Summary Total Pigs'!#REF!*'Pigs Cost'!N76 -> #REF! | T76: =M76+O76+P76+R76+S76+Q76 -> #REF! | V76: =C76/$B$178 -> 3.5951326e-06
A77: GROWERS | B77: GROWER | C77: =[16]USD!$T77 -> 10195.535 | E77: =+'Summary Total Pigs'!#REF!*N76 -> #REF! | J77: =('Summary Total Pigs'!#REF!)/'Summary Total Pigs'!#REF!*$L$174 -> #REF! | K77: =('Summary Total Pigs'!#REF!/'Summary Total Pigs'!#REF!)*'Pigs Cost'!$L$175 -> #REF! | M77: =SUM(C77:L77) -> #REF! | N77: =+M77/'Summary Total Pigs'!#REF! -> #REF! | O77: =N77*'Summary Total Pigs'!#REF! -> #REF! | P77: =N77*'Summary Total Pigs'!#REF! -> #REF! | Q77: ='Summary Total Pigs'!#REF!*N77 -> #REF! | R77: =N77*'Summary Total Pigs'!#REF! -> #REF! | S77: ='Summary Total Pigs'!#REF!*N77 -> #REF! | T77: =M77+O77+P77+R77+S77+Q77 -> #REF! | V77: =C77/$B$178 -> 1.0195535e-06
A78: GILTS | B78: MAIN | C78: =[16]USD!$T78 -> 0 | E78: =+'Summary Total Pigs'!#REF!*N77 -> #REF! | J78: 0 | K78: =('Summary Total Pigs'!#REF!/'Summary Total Pigs'!#REF!)*'Pigs Cost'!$L$175 -> #REF! | M78: =SUM(C78:L78) -> #REF! | O78: =N78*'Summary Total Pigs'!#REF! -> #REF! | P78: =N78*'Summary Total Pigs'!#REF! -> #REF! | Q78: ='Summary Total Pigs'!#REF!*'Pigs Cost'!N78 -> #REF! | R78: =N78*'Summary Total Pigs'!#REF! -> #REF! | S78: ='Summary Total Pigs'!#REF!*'Pigs Cost'!N78 -> #REF! | T78: =M78+O78+P78+R78+S78+Q78 -> #REF! | V78: =C78/$B$178 -> 0
A79: SOWS | B79: MAIN | C79: =[16]USD!$T79 -> 31106.308 | E79: =+'Summary Total Pigs'!#REF!*N56 -> #REF! | J79: 0 | K79: =('Summary Total Pigs'!#REF!/'Summary Total Pigs'!#REF!)*'Pigs Cost'!$L$175 -> #REF! | M79: =SUM(C79:L79) -> #REF! | N79: =+M79/'Summary Total Pigs'!#REF! -> #REF! | O79: =N79*'Summary Total Pigs'!#REF! -> #REF! | P79: =N79*'Summary Total Pigs'!#REF! -> #REF! | Q79: ='Summary Total Pigs'!#REF!*N79 -> #REF! | R79: =N79*'Summary Total Pigs'!#REF! -> #REF! | S79: ='Summary Total Pigs'!#REF!*'Pigs Cost'!N79 -> #REF! | T79: =M79+O79+P79+R79+S79+Q79 -> #REF! | V79: =C79/$B$178 -> 3.1106308e-06
A80: BOARS | C80: =[16]USD!$T80 -> 911.4516 | J80: 0 | K80: =('Summary Total Pigs'!#REF!/'Summary Total Pigs'!#REF!)*'Pigs Cost'!$L$175 -> #REF! | M80: =SUM(C80:L80) -> #REF! | N80: =+M80/'Summary Total Pigs'!#REF! -> #REF! | O80: =N80*'Summary Total Pigs'!#REF! -> #REF! | P80: =N80*'Summary Total Pigs'!#REF! -> #REF! | Q80: ='Summary Total Pigs'!#REF!*'Pigs Cost'!N80 -> #REF! | R80: =N80*'Summary Total Pigs'!#REF! -> #REF! | S80: ='Summary Total Pigs'!#REF!*'Pigs Cost'!N80 -> #REF! | T80: =M80+O80+P80+R80+S80+Q80 -> #REF! | V80: =C80/$B$178 -> 9.114516e-08
A81: TOTAL | C81: =SUM(C75:C80) -> 86708.324 | D81: =SUM(D75:D80) -> 0 | E81: =SUM(E75:E80) -> #REF! | F81: =SUM(F75:F80) -> 0 | G81: =SUM(G75:G80) -> 0 | H81: =SUM(H75:H80) -> 0 | I81: =SUM(I75:I80) -> 0 | J81: =SUM(J75:J80) -> #REF! | ... T81: =SUM(T75:T80) -> #REF! | V81: =C81/$B$178 -> 8.6708324e-06
J82: =J81-L174 -> #REF! | K82: =K81-L175 -> #REF! | V82: =C82/$B$178 -> 0
V83: =C83/$B$178 -> 0
A84: SITE: | B84: UMFULI BANKS | D84: =240*N100 -> #REF! | L84: =+(G82+H82+I82+K82+L82+J82)-K202 -> #REF! | O84: =O89/N89 -> #REF! | V84: =C84/$B$178 -> 0
V85: =C85/$B$178 -> 0
A86: DESCRIPTION | B86: SITE | C86: =+C74 -> OPENING | D86: PIG PURCHASES | E86: TRANSFER IN | F86: A I CONSUMMABLES | G86: BEDDING AND CONSUMMABLES | H86: CONSULTANCY FEES | I86: DIRECT STAFF COSTS | J86: STOCK FEED | K86: SUNDRY TOOLS | L86: VETERINARY | M86: TOTAL COST | N86: AVERAGE COST | O86: TRANSFER OUT | P86: SALES | Q86: =Q74 -> Deaths | R86: =R74 -> CULLS | S86: =+S74 -> STOCK ADJMNT | T86: CLOSING | V86: =C86/$B$178 -> #VALUE!
A87: PIGLETS | B87: MAIN | C87: =[16]USD!$T87 -> 0 | J87: =('Summary Total Pigs'!#REF!)/'Summary Total Pigs'!#REF!*'Pigs Cost'!$O$174 -> #REF! | M87: =SUM(C87:L87) -> #REF! | N87: 0 | O87: =N87*'Summary Total Pigs'!#REF! -> #REF! | P87: =N87*'Summary Total Pigs'!#REF! -> #REF! | Q87: ='Summary Total Pigs'!#REF!*N87 -> #REF! | R87: =N87*'Summary Total Pigs'!#REF! -> #REF! | S87: ='Summary Total Pigs'!#REF!*N87 -> #REF! | T87: =M87+O87+P87+R87+S87+Q87 -> #REF! | V87: =C87/$B$178 -> 0
A88: WEANERS | B88: WEANER | C88: =[16]USD!$T88 -> 0 | J88: =('Summary Total Pigs'!#REF!)/'Summary Total Pigs'!#REF!*'Pigs Cost'!$O$174 -> #REF! | M88: =SUM(C88:L88) -> #REF! | N88: 0 | O88: =N88*'Summary Total Pigs'!#REF! -> #REF! | P88: =N88*'Summary Total Pigs'!#REF! -> #REF! | Q88: ='Summary Total Pigs'!#REF!*N88 -> #REF! | R88: =N88*'Summary Total Pigs'!#REF! -> #REF! | S88: ='Summary Total Pigs'!#REF!*N88 -> #REF! | T88: =M88+O88+P88+R88+S88+Q88 -> #REF! | V88: =C88/$B$178 -> 0
A89: GROWERS | B89: GROWER | C89: =[16]USD!$T89 -> 34065.565 | E89: ='Summary Total Pigs'!#REF!*N101 -> #REF! | J89: =('Summary Total Pigs'!#REF!)/'Summary Total Pigs'!#REF!*$O$174 -> #REF! | M89: =SUM(C89:L89) -> #REF! | N89: =M89/'Summary Total Pigs'!#REF! -> #REF! | O89: =N89*'Summary Total Pigs'!#REF! -> #REF! | P89: =N89*'Summary Total Pigs'!#REF! -> #REF! | Q89: ='Summary Total Pigs'!#REF!*N89 -> #REF! | R89: =N89*'Summary Total Pigs'!#REF! -> #REF! | S89: ='Summary Total Pigs'!#REF!*N89 -> #REF! | T89: =M89+O89+P89+R89+S89+Q89 -> #REF! | V89: =C89/$B$178 -> 3.4065565e-06
A90: GILTS | B90: MAIN | C90: =[16]USD!$T90 -> 0 | J90: =('Summary Total Pigs'!#REF!)/'Summary Total Pigs'!#REF!*'Pigs Cost'!$O$174 -> #REF! | M90: =SUM(C90:L90) -> #REF! | O90: =N90*'Summary Total Pigs'!#REF! -> #REF! | P90: =N90*'Summary Total Pigs'!#REF! -> #REF! | Q90: ='Summary Total Pigs'!#REF!*N90 -> #REF! | R90: =N90*'Summary Total Pigs'!#REF! -> #REF! | S90: ='Summary Total Pigs'!#REF!*N90 -> #REF! | T90: =M90+O90+P90+R90+S90+Q90 -> #REF! | V90: =C90/$B$178 -> 0
A91: SOWS | B91: MAIN | C91: =[16]USD!$T91 -> 0 | J91: =('Summary Total Pigs'!#REF!)/'Summary Total Pigs'!#REF!*'Pigs Cost'!$O$174 -> #REF! | M91: =SUM(C91:L91) -> #REF! | O91: =N91*'Summary Total Pigs'!#REF! -> #REF! | P91: =N91*'Summary Total Pigs'!#REF! -> #REF! | Q91: ='Summary Total Pigs'!#REF!*N91 -> #REF! | R91: =N91*'Summary Total Pigs'!#REF! -> #REF! | S91: ='Summary Total Pigs'!#REF!*N91 -> #REF! | T91: =M91+O91+P91+R91+S91+Q91 -> #REF! | V91: =C91/$B$178 -> 0
A92: BOARS | C92: =[16]USD!$T92 -> 0 | J92: =('Summary Total Pigs'!#REF!)/'Summary Total Pigs'!#REF!*'Pigs Cost'!$O$174 -> #REF! | M92: =SUM(C92:L92) -> #REF! | O92: =N92*'Summary Total Pigs'!#REF! -> #REF! | P92: =N92*'Summary Total Pigs'!#REF! -> #REF! | Q92: ='Summary Total Pigs'!#REF!*N92 -> #REF! | R92: =N92*'Summary Total Pigs'!#REF! -> #REF! | S92: ='Summary Total Pigs'!#REF!*N92 -> #REF! | T92: =M92+O92+P92+R92+S92+Q92 -> #REF! | V92: =C92/$B$178 -> 0
A93: TOTAL | C93: =SUM(C87:C92) -> 34065.565 | D93: =SUM(D87:D92) -> 0 | E93: =SUM(E87:E92) -> #REF! | F93: =SUM(F87:F92) -> 0 | G93: =SUM(G87:G92) -> 0 | H93: =SUM(H87:H92) -> 0 | I93: =SUM(I87:I92) -> 0 | J93: =SUM(J87:J92) -> #REF! | ... P93: =SUM(P87:P92) -> #REF! | R93: =SUM(R87:R92) -> #REF! | S93: =SUM(S87:S92) -> #REF! | T93: =SUM(T87:T92) -> #REF! | V93: =C93/$B$178 -> 3.4065565e-06
J94: =J93-O174 -> #REF! | V94: =C94/$B$178 -> 0
S95: =+S93+'IAS 41 Mvmnt Pigs'!K93 -> #REF! | V95: =C95/$B$178 -> 0
A96: SITE: | B96: SEAFORTH FARM | L96: =+(G94+H94+I94+K94+L94+J94)-K214 -> #REF! | V96: =C96/$B$178 -> 0
V97: =C97/$B$178 -> 0
A98: DESCRIPTION | B98: SITE | C98: =+C86 -> OPENING | D98: PIG PURCHASES | E98: TRANSFER IN | F98: A I CONSUMMABLES | G98: BEDDING AND CONSUMMABLES | H98: CONSULTANCY FEES | I98: DIRECT STAFF COSTS | J98: STOCK FEED | K98: SUNDRY TOOLS | L98: VETERINARY | M98: TOTAL COST | N98: AVERAGE COST | O98: TRANSFER OUT | P98: SALES | Q98: =Q86 -> Deaths | R98: =R86 -> CULLS | S98: =+S86 -> STOCK ADJMNT | T98: CLOSING | V98: =C98/$B$178 -> #VALUE!
A99: PIGLETS | B99: MAIN | C99: =[16]USD!$T99 -> 0 | E99: ='Summary Total Pigs'!#REF!*N37 -> #REF! | J99: =('Summary Total Pigs'!#REF!/'Summary Total Pigs'!#REF!)*'Pigs Cost'!$P$174 -> #REF! | M99: =SUM(C99:L99) -> #REF! | O99: =N99*'Summary Total Pigs'!#REF! -> #REF! | P99: =N99*'Summary Total Pigs'!#REF! -> #REF! | Q99: =N99*'Summary Total Pigs'!#REF! -> #REF! | R99: 0 | S99: 0 | T99: =M99+O99+P99+R99+S99+Q99 -> #REF! | V99: =C99/$B$178 -> 0
A100: WEANERS | B100: WEANER | C100: =[16]USD!$T100 -> 21769.16 | E100: =(603*N37)+(489*N53) -> #REF! | J100: =('Summary Total Pigs'!#REF!/'Summary Total Pigs'!#REF!)*$P$174 -> #REF! | M100: =SUM(C100:L100) -> #REF! | N100: =M100/'Summary Total Pigs'!#REF! -> #REF! | O100: =N100*'Summary Total Pigs'!#REF! -> #REF! | P100: =N100*'Summary Total Pigs'!#REF! -> #REF! | Q100: =N100*'Summary Total Pigs'!#REF! -> #REF! | R100: 0 | S100: 0 | T100: =M100+O100+P100+R100+S100+Q100 -> #REF! | V100: =C100/$B$178 -> 2.176916e-06
A101: GROWERS | B101: GROWER | C101: =[16]USD!$T101 -> 1695.5031 | E101: ='Summary Total Pigs'!#REF!*N100 -> #REF! | J101: =('Summary Total Pigs'!#REF!/'Summary Total Pigs'!#REF!)*$P$174 -> #REF! | M101: =SUM(C101:L101) -> #REF! | N101: =M101/'Summary Total Pigs'!#REF! -> #REF! | O101: =N101*'Summary Total Pigs'!#REF! -> #REF! | P101: =N101*'Summary Total Pigs'!#REF! -> #REF! | Q101: =N101*'Summary Total Pigs'!#REF! -> #REF! | R101: =N101*'Summary Total Pigs'!#REF! -> #REF! | S101: ='Summary Total Pigs'!#REF!*N101 -> #REF! | T101: =M101+O101+P101+R101+S101+Q101 -> #REF! | V101: =C101/$B$178 -> 1.6955031e-07
A102: GILTS | B102: MAIN | C102: =[16]USD!$T102 -> 0 | J102: =('Summary Total Pigs'!#REF!/'Summary Total Pigs'!#REF!)*'Pigs Cost'!$P$174 -> #REF! | M102: =SUM(C102:L102) -> #REF! | N102: 0 | O102: =N102*'Summary Total Pigs'!#REF! -> #REF! | P102: =N102*'Summary Total Pigs'!#REF! -> #REF! | Q102: =N102*'Summary Total Pigs'!#REF! -> #REF! | R102: =N102*'Summary Total Pigs'!#REF! -> #REF! | S102: ='Summary Total Pigs'!#REF!*N102 -> #REF! | T102: =M102+O102+P102+R102+S102+Q102 -> #REF! | V102: =C102/$B$178 -> 0
A103: SOWS | B103: MAIN | C103: =[16]USD!$T103 -> 0 | J103: =('Summary Total Pigs'!#REF!/'Summary Total Pigs'!#REF!)*'Pigs Cost'!$P$174 -> #REF! | M103: =SUM(C103:L103) -> #REF! | N103: 0 | O103: =N103*'Summary Total Pigs'!#REF! -> #REF! | P103: =N103*'Summary Total Pigs'!#REF! -> #REF! | Q103: =N103*'Summary Total Pigs'!#REF! -> #REF! | R103: =N103*'Summary Total Pigs'!#REF! -> #REF! | S103: ='Summary Total Pigs'!#REF!*N103 -> #REF! | T103: =M103+O103+P103+R103+S103+Q103 -> #REF! | V103: =C103/$B$178 -> 0
A104: BOARS | C104: =[16]USD!$T104 -> 0 | J104: =('Summary Total Pigs'!#REF!/'Summary Total Pigs'!#REF!)*'Pigs Cost'!$P$174 -> #REF! | M104: =SUM(C104:L104) -> #REF! | N104: 0 | O104: =N104*'Summary Total Pigs'!#REF! -> #REF! | Q104: =N104*'Summary Total Pigs'!#REF! -> #REF! | R104: =N104*'Summary Total Pigs'!#REF! -> #REF! | S104: ='Summary Total Pigs'!#REF!*N104 -> #REF! | T104: =M104+O104+P104+R104+S104+Q104 -> #REF! | V104: =C104/$B$178 -> 0
A105: TOTAL | C105: =SUM(C99:C104) -> 23464.663 | D105: =SUM(D99:D104) -> 0 | E105: =SUM(E99:E104) -> #REF! | F105: =SUM(F99:F104) -> 0 | G105: =SUM(G99:G104) -> 0 | H105: =SUM(H99:H104) -> 0 | I105: =SUM(I99:I104) -> 0 | J105: =SUM(J99:J104) -> #REF! | ... T105: =SUM(T99:T104) -> #REF! | V105: =C105/$B$178 -> 2.3464663e-06
...

Sheet Sheet18
C1: In | D1: Out | E1: Mortality
B2: 2947

Sheet Sheet24
D1: mortaliy | E1: Cull hse | F1: DS4 | I1: Stock
B2: Fw | C2: 2 | H2: =SUM(C2:F2) -> 2 | I2: 2
B3: DS3 | C3: 1 | H3: =SUM(C3:F3) -> 1 | I3: 1
B4: DS4 | C4: 1 | D4: -1 | E4: 1 | H4: =SUM(C4:F4) -> 1 | I4: 1
B5: DS5 | C5: 1 | H5: =SUM(C5:F5) -> 1 | I5: 1
B6: FH6 | C6: 3 | E6: -1 | F6: -1 | H6: =SUM(C6:F6) -> 1 | I6: 1
B7: Qua | C7: 3 | D7: -1 | H7: =SUM(C7:F7) -> 2 | I7: 0
B8: Cull hse | E8: 1 | H8: =SUM(C8:F8) -> 1 | I8: 1
C11: =SUM(C2:C8) -> 11 | D11: =SUM(D2:D8) -> -2 | E11: =SUM(E2:E8) -> 1 | F11: =SUM(F2:F8) -> -1 | H11: =SUM(H2:H8) -> 9 | I11: =SUM(I2:I10) -> 7 | J11: =+H11-I11 -> 2

Sheet Sheet26

Sheet SUMMARY 
A2: Pre Farrowing | B2: # Pigs | C2: CDM | D2: Ave. | E2: Value | K2: Previous Month NOP | L2: Diff
A3: Grasmere | E3: =SUM('Grasmere Valuation '!H9) -> 435825.55
A4: Villa | E4: =SUM('Villa Valuation'!H9) -> 78870.422
A5: Lionshead | E5: =SUM('Lionhead Valuation'!H9) -> 216111.5
A6: Lionshead Ext. | E6: =SUM('Lionhead Ext. Valuation'!H9) -> 0
A7: Richlands | E7: =SUM('Richlands Valuation'!H9) -> 198132.14
A8: Learig | E8: =SUM('Learig Valuation'!H9) -> 0
A9: Porta | E9: ='Porta Valuation'!H9 -> 184576.22 | M9: =+B22+B34 -> 84288 | N9: =+SUM('Summary Total Pigs'!AF186:AF188) -> 84288
A10: Multiplier | E10: ='Multiplier Valuation'!H9 -> 90223.637 | M10: =+B45+B56 -> 8105 | N10: =+SUM('Summary Total Pigs'!AF189:AF191) -> 8105 | O10: =+N10-M10 -> 0
A11: Total | C11: =SUM(C3:C8) -> 0 | E11: =SUM(E3:I10) -> 1203739.5
A13: 1-17 Weeks | B13: =+B2 -> # Pigs | C13: =+C2 -> CDM | D13: =+D2 -> Ave. | E13: =+E2 -> Value
A14: =+A3 -> Grasmere | B14: =SUM('Grasmere Valuation '!E10:E26) -> 18979 | C14: =SUM('Grasmere Valuation '!F10:F26) -> 322518.85 | D14: =+E14/C14 -> 6.4886202 | E14: =SUM('Grasmere Valuation '!H10:H26) -> 2092702.3 | F14: =+B14-'Summary Total Pigs'!AF12 -> 13783 | K14: ='SUMMARY '!B14 -> 18979 | L14: =B14-K14 -> 0
A15: =+A4 -> Villa | B15: =SUM('Villa Valuation'!E10:E26) -> 3281 | C15: =SUM('Villa Valuation'!F10:F26) -> 66891.851 | D15: =+E15/C15 -> 5.1262314 | E15: =SUM('Villa Valuation'!H10:H26) -> 342903.11 | F15: =+B15-'Summary Total Pigs'!AF89 -> 2264 | K15: ='SUMMARY '!B15 -> 3281 | L15: =B15-K15 -> 0
A16: =+A5 -> Lionshead | B16: =SUM('Lionhead Valuation'!E10:E26) -> 10458 | C16: =SUM('Lionhead Valuation'!F10:F26) -> 189248.59 | D16: =+E16/C16 -> 6.6479937 | E16: =SUM('Lionhead Valuation'!H10:H26) -> 1258123.4 | F16: =+B16-'Summary Total Pigs'!AF50 -> 8123 | K16: ='SUMMARY '!B16 -> 10458 | L16: =B16-K16 -> 0
A17: Lionhead Ext. | B17: =SUM('Lionhead Ext. Valuation'!E10:E26) -> 2147 | C17: =SUM('Lionhead Ext. Valuation'!F10:F26) -> 53797.767 | D17: =+E17/C17 -> 5.8789453 | E17: =SUM('Lionhead Ext. Valuation'!H10:H26) -> 316274.13 | K17: ='SUMMARY '!B17 -> 2147 | L17: =B17-K17 -> 0
A18: =+A7 -> Richlands | B18: =SUM('Richlands Valuation'!E10:E26) -> 9586 | C18: =SUM('Richlands Valuation'!F10:F26) -> 176726.28 | D18: =+E18/C18 -> 6.5300821 | E18: =SUM('Richlands Valuation'!H10:H26) -> 1154037.1 | F18: =+B18-'Summary Total Pigs'!AF108 -> 7470 | K18: ='SUMMARY '!B18 -> 9586 | L18: =B18-K18 -> 0
A19: =+A8 -> Learig | B19: =SUM('Learig Valuation'!E10:E26) -> 5009 | C19: =SUM('Learig Valuation'!F10:F26) -> 118239.66 | D19: =+E19/C19 -> 6.1369979 | E19: =SUM('Learig Valuation'!H10:H26) -> 725636.56 | F19: =+B19-'Summary Total Pigs'!AF31 -> 5009 | K19: ='SUMMARY '!B19 -> 5009 | L19: =B19-K19 -> 0
A20: Porta | B20: =SUM('Porta Valuation'!E10:E26) -> 11034 | C20: =SUM('Porta Valuation'!F10:F26) -> 207625.03 | D20: =+E20/C20 -> 5.8980414 | E20: =SUM('Porta Valuation'!H10:H26) -> 1224581 | K20: ='SUMMARY '!B20 -> 11034 | L20: =B20-K20 -> 0
A21: Multiplier | B21: =SUM('Multiplier Valuation'!E10:E26) -> 3819 | C21: =SUM('Multiplier Valuation'!F10:F26) -> 69998.187 | D21: =+IFERROR(E21/C21,0) -> 6.2491611 | E21: =SUM('Multiplier Valuation'!H10:H26) -> 437429.95 | K21: ='SUMMARY '!B21 -> 3819 | L21: =B21-K21 -> 0
A22: =+A11 -> Total | B22: =SUM(B14:B21) -> 64313 | C22: =SUM(C14:C21) -> 1205046.2 | D22: =E22/C22 -> 6.2667203 | E22: =SUM(E14:E21) -> 7551687.6
A25: >=18 Weeks | B25: # Pigs | C25: CDM | D25: =+D2 -> Ave. | E25: Value
A26: =+A3 -> Grasmere | B26: =SUM('Grasmere Valuation '!E27:E40) -> 5920 | C26: =SUM('Grasmere Valuation '!F27:F40) -> 489108.45 | D26: =+E26/C26 -> 2.5156473 | E26: =SUM('Grasmere Valuation '!H27:H40) -> 1230424.3 | F26: =SUM('Summary Total Pigs'!AF13:AF14)-B26 -> 13783 | K26: ='SUMMARY '!B26 -> 5920 | L26: =B26-K26 -> 0
A27: =+A4 -> Villa | B27: =SUM('Villa Valuation'!E27:E41) -> 896 | C27: =SUM('Villa Valuation'!F27:F41) -> 74935.298 | D27: =+E27/C27 -> 2.505768 | E27: =SUM('Villa Valuation'!H27:H41) -> 187770.47 | F27: =SUM('Summary Total Pigs'!AF90:AF91)-B27 -> 2264 | K27: ='SUMMARY '!B27 -> 896 | L27: =B27-K27 -> 0
A28: =+A5 -> Lionshead | B28: =SUM('Lionhead Valuation'!E27:E41) -> 3096 | C28: =SUM('Lionhead Valuation'!F27:F41) -> 233685.86 | D28: =+E28/C28 -> 2.5124801 | E28: =SUM('Lionhead Valuation'!H27:H41) -> 587131.06 | F28: =SUM('Summary Total Pigs'!AF51:AF52)-B28 -> 8123 | G28: =+I28/H28 -> 2.5124552 | H28: =+C28+C29 -> 317133.92 | I28: =+E28+E29 -> 796784.79 | K28: ='SUMMARY '!B28 -> 3096 | L28: =B28-K28 -> 0
A29: Lionhead Ext. | B29: =SUM('Lionhead Ext. Valuation'!E27:E41) -> 1123 | C29: =SUM('Lionhead Ext. Valuation'!F27:F41) -> 83448.065 | D29: =+E29/C29 -> 2.5123858 | E29: =SUM('Lionhead Ext. Valuation'!H27:H41) -> 209653.73 | F29: =SUM('Summary Total Pigs'!AE69:AE71)-B29 -> 2147 | K29: ='SUMMARY '!B29 -> 1123 | L29: =B29-K29 -> 0
A30: =+A7 -> Richlands | B30: =SUM('Richlands Valuation'!E27:E41) -> 2159 | C30: =SUM('Richlands Valuation'!F27:F41) -> 174040.44 | D30: =+E30/C30 -> 2.5075585 | E30: =SUM('Richlands Valuation'!H27:H41) -> 436416.59 | F30: =SUM('Summary Total Pigs'!AF109:AF110)-B30 -> 7470 | K30: ='SUMMARY '!B30 -> 2159 | L30: =B30-K30 -> 0
A31: =+A8 -> Learig | B31: =SUM('Learig Valuation'!E27:E40) -> 2254 | C31: =SUM('Learig Valuation'!F27:F40) -> 188714.76 | D31: =+E31/C31 -> 2.4991804 | E31: =SUM('Learig Valuation'!H27:H40) -> 471632.21 | F31: =SUM('Summary Total Pigs'!AF32:AF33)-B31 -> 5009 | K31: ='SUMMARY '!B31 -> 2254 | L31: =B31-K31 -> 0
A32: Porta | B32: =SUM('Porta Valuation'!E27:E40) -> 3205 | C32: =SUM('Porta Valuation'!F27:F40) -> 267874.93 | D32: =+IFERROR(E32/C32,0) -> 2.5173289 | E32: =SUM('Porta Valuation'!H27:H40) -> 674329.3 | K32: ='SUMMARY '!B32 -> 3205 | L32: =B32-K32 -> 0
A33: Multiplier | B33: =SUM('Multiplier Valuation'!E27:E40) -> 1322 | C33: =SUM('Multiplier Valuation'!F27:F40) -> 114148.46 | D33: =+IFERROR(E33/C33,0) -> 2.5146002 | E33: =SUM('Multiplier Valuation'!H27:H40) -> 287037.74 | K33: ='SUMMARY '!B33 -> 1322 | L33: =B33-K33 -> 0 | N33: =+B34+B22-SUM('Summary Total Pigs'!AE186:AE188) -> 0
A34: =+A11 -> Total | B34: =SUM(B26:B33) -> 19975 | C34: =SUM(C26:C33) -> 1625956.3 | D34: =+E34/C34 -> 2.5119959 | E34: =SUM(E26:E33) -> 4084395.4 | F34: ='[26]Selling Price Working'!$K$19 -> 2.2478369 | G34: =C34*F34 -> 3654884.5 | H34: =E34-G34 -> 429510.96
A36: Local Non- Current | B36: =+B25 -> # Pigs | C36: =+C25 -> CDM | D36: Ave/Pig | E36: =+E25 -> Value
A37: =+A26 -> Grasmere | B37: =SUM('Grasmere Valuation '!E41:E44) -> 2794 | C37: =(B37*150) -> 419100 | D37: ='Grasmere Valuation '!G41 -> 2.05 | E37: =(C37*D37) -> 859155 | K37: ='SUMMARY '!B37 -> 2794 | L37: =B37-K37 -> 0 | N37: =+'Grasmere Batch Mvnt'!J121 -> 2820 | O37: =+B37+B48 -> 2822 | P37: =+O37-N37 -> 2
A38: =+A27 -> Villa | B38: =SUM('Villa Valuation'!E44:E48) -> 576 | C38: =SUM('Villa Valuation'!F44:F49) -> 86400 | D38: =D37 -> 2.05 | E38: =C38*D38 -> 177120 | K38: ='SUMMARY '!B38 -> 576 | L38: =B38-K38 -> 0 | N38: =+'Villa Batch Mvnt'!I7 -> 576 | O38: =+B38+B49 -> 576 | P38: =+O38-N38 -> 0
A39: =+A28 -> Lionshead | B39: =SUM('Lionhead Valuation'!E55:E59) -> 1412 | C39: =SUM('Lionhead Valuation'!F55:F59) -> 211800 | D39: =D38 -> 2.05 | E39: =C39*D39 -> 434190 | K39: ='SUMMARY '!B39 -> 1412 | L39: =B39-K39 -> 0 | N39: =+'Lionheads Batch Mvnt'!I7 -> 1418 | O39: =+B39+B50 -> 1412 | P39: =+O39-N39 -> -6
A40: Lionhead Ext. | B40: =SUM('Lionhead Ext. Valuation'!E44:E48) -> 0 | C40: =SUM('Lionhead Ext. Valuation'!F44:F48) -> 0 | D40: =D39 -> 2.05 | E40: =C40*D40 -> 0 | K40: ='SUMMARY '!B40 -> 0 | L40: =B40-K40 -> 0 | N40: =+'Lionheads Ext. Batch Mvnt'!I7 -> 0 | O40: =+B40+B51 -> 0 | P40: =+O40-N40 -> 0
A41: =+A30 -> Richlands | B41: =SUM('Richlands Valuation'!E82:E86) -> 1262 | C41: =SUM('Richlands Valuation'!F82:F86) -> 189300 | D41: =D40 -> 2.05 | E41: =C41*D41 -> 388065 | K41: ='SUMMARY '!B41 -> 1262 | L41: =B41-K41 -> 0 | N41: =+'Richlands Batch Mvnt'!I7 -> 1272 | O41: =+B41+B52 -> 1266 | P41: =+O41-N41 -> -6
A42: =+A31 -> Learig | B42: =SUM('Learig Valuation'!E41:E44) -> 0 | C42: =SUM('Learig Valuation'!F41:F44) -> 0 | D42: =D41 -> 2.05 | E42: =C42*D42 -> 0 | K42: ='SUMMARY '!B42 -> 0 | L42: =B42-K42 -> 0 | N42: =+'Learig Batch Mvnt'!J6 -> 0 | O42: =+B42+B53 -> 0 | P42: =+O42-N42 -> 0
A43: Porta | B43: =SUM('Porta Valuation'!E82:E86) -> 775 | C43: =SUM('Porta Valuation'!F82:F86) -> 116250 | D43: =D42 -> 2.05 | E43: =C43*D43 -> 238312.5 | K43: ='SUMMARY '!B43 -> 775 | L43: =B43-K43 -> 0 | N43: =+'Porta Batch Mvnt'!I7 -> 1326 | O43: =+B43+B54 -> 1337 | P43: =+O43-N43 -> 11
A44: Multiplier | B44: =SUM('Multiplier Valuation'!E86:E90) -> 194 | C44: =SUM('Multiplier Valuation'!F86:F90) -> 29100 | D44: =D43 -> 2.05 | E44: =C44*D44 -> 59655 | K44: ='SUMMARY '!B44 -> 194 | L44: =B44-K44 -> 0 | N44: =+'Multiplier Batch Mvnt'!I7 -> 693 | O44: =+B44+B55 -> 692 | P44: =+O44-N44 -> -1
A45: =+A34 -> Total | B45: =SUM(B37:B44) -> 7013 | C45: =SUM(C37:C44) -> 1051950 | D45: =+E45/C45 -> 2.05 | E45: =SUM(E37:E44) -> 2156497.5 | F45: ='[27]Pig Costing December 2023'!$BB$68-E45 -> -547783.5
F46: =SUM('Summary Total Pigs'!AE189:AE191) -> 8105 | G46: =SUM('Summary Total Pigs'!C189:C191) -> 8028
A47: Imported Non-Current | B47: =+B36 -> # Pigs | C47: Cost | D47: Acc. Amort. | E47: =+E36 -> Value | F47: =F46-B56 -> 7013 | G47: =G46-'[28]SUMMARY '!$B$46 -> 7608
A48: AI | B48: =+'Grasmere Imported Boars'!D31+'Grasmere Imported Boars'!D30+'Grasmere Imported Boars'!D35+'Grasmere Imported Boars'!D34 -> 28 | F48: ='Summary Total Pigs'!AE189 -> 1890 | G48: ='Summary Total Pigs'!C189 -> 1841 | K48: ='SUMMARY '!B48 -> 28 | L48: =B48-K48 -> 0
A49: =+A4 -> Villa | E49: =+C49+D49 -> 0 | F49: =F47-F48 -> 5123 | G49: =G47-G48 -> 5767 | K49: ='SUMMARY '!B49 -> 0 | L49: =B49-K49 -> 0
A50: =+A5 -> Lionshead | B50: 0 | C50: 0 | D50: =SUM('Summary Valuation'!C86:C94) -> 0 | E50: =+C50+D50 -> 0 | K50: ='SUMMARY '!B50 -> 0 | L50: =B50-K50 -> 0
A51: Liohead Ext | K51: ='SUMMARY '!B51 -> 0 | L51: =B51-K51 -> 0
A52: =+A7 -> Richlands | B52: =+'Grasmere Imported Boars'!D34 -> 4 | C52: =B52/(B52+B48)*(SUM('Total Pigs'!R333)-C54) -> 272957.41 | D52: 0 | E52: 0 | G52: =C54-E54 -> 27223.631 | K52: ='SUMMARY '!B52 -> 4 | L52: =B52-K52 -> 0
A53: =+A8 -> Learig | E53: =+C53+D53 -> 0 | K53: ='SUMMARY '!B53 -> 0 | L53: =B53-K53 -> 0
A54: Porta | B54: ='Porta Imported Valuation'!Z8 -> 562 | C54: =SUM('[29]Imported Pigs Costing 0726'!$AX$102:$AX$359) -> 227545.78 | D54: =E54-C54 -> -27223.631 | E54: =+'[29]Imported Pigs Costing 0726'!$BN$360 -> 200322.15 | F54: 339410.14 | K54: ='SUMMARY '!B54 -> 562 | L54: =B54-K54 -> 0
A55: Multiplier | B55: ='Multiplier Imported Valuation'!BO9+'Grasmere Valuation '!E94+'Quarantine Sows'!B89+'Quarantine Boars'!B11 -> 498 | C55: =$B$48/($B$48+$B$52)*(SUM('Total Pigs'!$R$333)-$C$54) -> 1910701.9 | D55: ='Total Pigs'!$R$334-$D$54 -> -1152921.9 | E55: =SUM('[29]Imported Pigs Costing 0726'!$BS$360,'[29]Imported Pigs Costing 0726'!$CS$360) -> 1029114.5 | K55: ='SUMMARY '!B55 -> 498 | L55: =B55-K55 -> 0
A56: =+A11 -> Total | B56: =SUM(B48:B55) -> 1092 | C56: =SUM(C48:C55) -> 2411205 | D56: =SUM(D48:D55) -> -1180145.5 | E56: =SUM(E48:E55) -> 1229436.7 | G56: ='Total Pigs'!R333+'Total Pigs'!R334 -> 1231059.5
G57: =E56-G56 -> -1622.8699
A58: Cattle | B58: # Cattle | C58: =+C47 -> Cost | D58: =+D47 -> Acc. Amort. | E58: =+E47 -> Value
A59: Grasmere | B59: =+'Cattle Valuation'!D21 -> 123 | E59: =SUM('Cattle Valuation'!G21) -> 48511.464
A61: Grand Total | B61: =+B47 -> # Pigs | C61: CDM | D61: Ave | E61: =+E47 -> Value
A62: =+A48 -> AI | B62: =+B3+B14+B26+B37+B48 -> 27721 | E62: =+E3+E14+E26+E37+E48 -> 4618107.2 | F62: =SUM('Summary Total Pigs'!AF18,'Summary Total Pigs'!AF130:AF132) -> 27821 | G62: =+B62-F62 -> -100 | L62: =SUM('Summary Total Pigs'!AF12:AF17) -> 27719 | M62: =B62-L62 -> 2
A63: =+A49 -> Villa | B63: =+B4+B15+B27+B38+B49 -> 4753 | E63: =+E4+E15+E27+E38+E49 -> 786664 | F63: =SUM('Summary Total Pigs'!AE95) -> 4753 | G63: =+B63-F63 -> 0 | L63: =SUM('Summary Total Pigs'!AF89:AF94) -> 4753 | M63: =B63-L63 -> 0
A64: =+A50 -> Lionshead | B64: =+B5+B16+B28+B39+B50 -> 14966 | E64: =+E5+E16+E28+E39+E50 -> 2495556 | F64: =SUM('Summary Total Pigs'!AE56) -> 14972 | G64: =+B64-F64 -> -6 | L64: =SUM('Summary Total Pigs'!AF50:AF55) -> 14972 | M64: =B64-L64 -> -6
A65: Lionhead Ext | B65: =+B6+B17+B29+B40+B51 -> 3270 | E65: =+E6+E17+E29+E40+E51 -> 525927.87 | F65: =SUM('Summary Total Pigs'!AE75) -> 3270 | G65: =+B65-F65 -> 0 | L65: =SUM('Summary Total Pigs'!AF69:AF74) -> 3270 | M65: =B65-L65 -> 0
A66: =+A52 -> Richlands | B66: =+B7+B18+B30+B41+B52 -> 13011 | E66: =+E7+E18+E30+E41+E52 -> 2176650.9 | F66: =SUM('Summary Total Pigs'!AE114) -> 13017 | G66: =+B66-F66 -> -6 | L66: =SUM('Summary Total Pigs'!AF108:AF113) -> 13017 | M66: =B66-L66 -> -6
A67: =+A53 -> Learig | B67: =+B8+B19+B31+B42+B53 -> 7263 | E67: =+E8+E19+E31+E42+E53 -> 1197268.8 | F67: =SUM('Summary Total Pigs'!AE37) -> 7263 | G67: =+B67-F67 -> 0 | L67: =SUM('Summary Total Pigs'!AF31:AF36) -> 7263 | M67: =B67-L67 -> 0
A68: Porta | B68: =+B11+B20+B32+B43+B54 -> 15576 | E68: =E32+E43+E54+E9+E20 -> 2522121.2 | L68: =SUM('Summary Total Pigs'!AF146:AF151) -> 15565 | M68: =B68-L68 -> 11
A69: Multiplier | B69: =+B12+B21+B33+B44+B55 -> 5833 | E69: =E33+E44+E55+E10+E21 -> 1903460.8 | L69: =SUM('Summary Total Pigs'!AF165:AF170,'Summary Total Pigs'!AE133) -> 5834 | M69: =B69-L69 -> -1
A70: =+A56 -> Total | B70: =SUM(B62:B69) -> 92393 | C70: =SUM(C62:C67) -> 0 | D70: =SUM(D62:D67) -> 0 | E70: =SUM(E62:E69) -> 16225757 | F70: =SUM('Summary Total Pigs'!AF186:AF191)-B70 -> 0
A71: Cattle | E71: =+E59 -> 48511.464
A72: Grand Total | E72: =SUM(E70:E71) -> 16274268
E74: =+'Total Pigs'!D316 -> 11497804
A75: Check | B75: =B70-'Summary Total Pigs'!AE194 -> 0 | E75: =+E72-E74 -> 4776464.2
F83: 1 to 17 Weeks | G83: !8 to 23 Weeks Cost | H83: !8 to 23Faire Value
E84: Grasmere | G84: =SUM('Grasmere Pig Cost'!AJ62:AO62) -> 1796247.2 | H84: =I28-H28 -> 479650.87
E85: Richlands
E86: Lionshead
E87: Lionshead Ext
E88: Learig
E89: Villa

Sheet Sheet31

Sheet Mvnmt Recon
A1: Triple C Pigs
C3: Transfer In | L3: Transfer In | U3: Transfer In | AD3: Transfer In | AM3: Transfer In | AV3: Transfer In | BE3: Transfer In
C4: Grasmere | L4: Lionhead | U4: Villa | AD4: Richlands | AM4: Lionhead Ext. | AV4: Learig | BE4: Quarantine
C5: Lionhead | D5: Richlands | E5: Villa Franca | F5: Lionhead Ext | G5: Learig | H5: Quarantine | I5: Total | L5: Grasmere | M5: Richlands | N5: Villa Franca | O5: Lionhead Ext | P5: Learig | Q5: Quarantine | R5: Total | U5: Grasmere | V5: Richlands | W5: Lionhead | X5: Lionhead Ext | Y5: Learig | Z5: Quarantine | AA5: Total | AD5: Grasmere | AE5: Villa | AF5: Lionhead | AG5: Lionhead Ext | AH5: Learig | AI5: Quarantine | AJ5: Total | AM5: Grasmere | AN5: Villa | AO5: Lionhead | AP5: Richlands | AQ5: Learig | AR5: Quarantine | AS5: Total | AV5: Grasmere | AW5: Villa | AX5: Lionhead | AY5: Richlands | AZ5: Lionhead Ext. | BA5: Quarantine | BB5: Total | BE5: Grasmere | BF5: Villa | BG5: Lionhead | BH5: Richlands | BI5: Lionhead Ext. | BJ5: Learig | BK5: Total | BN5: Grand Total
A6: PIGLETS | C6: =+'Summary Total Pigs'!E12 -> 0 | D6: =+'Summary Total Pigs'!G12 -> 0 | E6: =+'Summary Total Pigs'!I12 -> 0 | F6: =+'Summary Total Pigs'!F12 -> 0 | G6: =+'Summary Total Pigs'!H12 -> 0 | H6: =+'Summary Total Pigs'!K12 -> 0 | I6: =SUM(C6:H6) -> 0 | L6: =+'Summary Total Pigs'!E50 -> 0 | M6: =+'Summary Total Pigs'!G50 -> 0 | N6: =+'Summary Total Pigs'!I50 -> 0 | O6: =+'Summary Total Pigs'!F50 -> 0 | P6: =+'Summary Total Pigs'!H50 -> 0 | Q6: =+'Summary Total Pigs'!K50 -> 0 | R6: =SUM(L6:Q6) -> 0 | U6: =+'Summary Total Pigs'!E89 -> 0 | V6: =+'Summary Total Pigs'!I89 -> 0 | W6: =+'Summary Total Pigs'!F89 -> 0 | X6: =+'Summary Total Pigs'!G89 -> 0 | Y6: =+'Summary Total Pigs'!H89 -> 0 | Z6: =+'Summary Total Pigs'!K89 -> 0 | AA6: =SUM(U6:Z6) -> 0 | AD6: =+'Summary Total Pigs'!E108 -> 0 | AE6: =+'Summary Total Pigs'!I108 -> 0 | AF6: =+'Summary Total Pigs'!F108 -> 0 | AG6: =+'Summary Total Pigs'!G108 -> 0 | AH6: =+'Summary Total Pigs'!H108 -> 0 | AI6: =+'Summary Total Pigs'!K108 -> 0 | AJ6: =SUM(AD6:AI6) -> 0 | AM6: =+'Summary Total Pigs'!E69 -> 0 | AN6: =+'Summary Total Pigs'!I69 -> 0 | AO6: =+'Summary Total Pigs'!F69 -> 0 | AP6: =+'Summary Total Pigs'!G69 -> 0 | AQ6: =+'Summary Total Pigs'!H69 -> 0 | AR6: =+'Summary Total Pigs'!K69 -> 0 | AS6: =SUM(AM6:AR6) -> 0 | AV6: =+'Summary Total Pigs'!H31 -> 0 | AW6: =+'Summary Total Pigs'!I31 -> 0 | AX6: =+'Summary Total Pigs'!E31 -> 0 | AY6: =+'Summary Total Pigs'!G31 -> 0 | AZ6: =+'Summary Total Pigs'!F31 -> 0 | BA6: =+'Summary Total Pigs'!K31 -> 0 | BB6: =SUM(AV6:BA6) -> 0 | BE6: =+'Summary Total Pigs'!K127 -> 0 | BF6: =+'Summary Total Pigs'!I127 -> 0 | BG6: =+'Summary Total Pigs'!F127 -> 0 | BH6: =+'Summary Total Pigs'!E127 -> 0 | BI6: =+'Summary Total Pigs'!G127 -> 0 | BJ6: =+'Summary Total Pigs'!H127 -> 0 | BK6: =SUM(BE6:BJ6) -> 0 | BN6: =SUM(C6:H6,L6:Q6,U6:Z6,AD6:AI6,AM6:AR6,AV6:BA6,BE6:BJ6) -> 0
A7: WEANER | C7: =+'Summary Total Pigs'!E13 -> 0 | D7: =+'Summary Total Pigs'!G13 -> 0 | E7: =+'Summary Total Pigs'!I13 -> 0 | F7: =+'Summary Total Pigs'!F13 -> 0 | G7: =+'Summary Total Pigs'!H13 -> 0 | H7: =+'Summary Total Pigs'!K13 -> 0 | I7: =SUM(C7:H7) -> 0 | J7: =+'Summary Total Pigs'!I200 -> 0 | K7: =+I6+I7+I8-J7 -> 0 | L7: =+'Summary Total Pigs'!E51 -> 0 | M7: =+'Summary Total Pigs'!G51 -> 0 | N7: =+'Summary Total Pigs'!I51 -> 0 | O7: =+'Summary Total Pigs'!F51 -> 0 | P7: =+'Summary Total Pigs'!H51 -> 0 | Q7: =+'Summary Total Pigs'!K51 -> 0 | R7: =SUM(L7:Q7) -> 0 | S7: =+'Summary Total Pigs'!I201 -> 0 | T7: =+R6+R7+R8-S7 -> 0 | U7: =+'Summary Total Pigs'!E90 -> 0 | V7: =+'Summary Total Pigs'!I90 -> 0 | W7: =+'Summary Total Pigs'!F90 -> 0 | X7: =+'Summary Total Pigs'!G90 -> 0 | Y7: =+'Summary Total Pigs'!H90 -> 0 | Z7: =+'Summary Total Pigs'!K90 -> 0 | AA7: =SUM(U7:Z7) -> 0 | AB7: =+'Summary Total Pigs'!I202 -> 0 | AC7: =+AA6+AA7+AA8-AB7 -> 0 | AD7: =+'Summary Total Pigs'!E109 -> 0 | AE7: =+'Summary Total Pigs'!I109 -> 0 | AF7: =+'Summary Total Pigs'!F109 -> 0 | AG7: =+'Summary Total Pigs'!G109 -> 0 | AH7: =+'Summary Total Pigs'!H109 -> 0 | AI7: =+'Summary Total Pigs'!K109 -> 0 | AJ7: =SUM(AD7:AI7) -> 0 | AK7: =+'Summary Total Pigs'!I203 -> 0 | AL7: =+AJ6+AJ7+AJ8-AK7 -> 0 | AM7: =+'Summary Total Pigs'!E70 -> 0 | AN7: =+'Summary Total Pigs'!I70 -> 250 | AO7: =+'Summary Total Pigs'!F70 -> 119 | AP7: =+'Summary Total Pigs'!G70 -> 380 | AQ7: =+'Summary Total Pigs'!H70 -> 0 | AR7: =+'Summary Total Pigs'!K70 -> 140 | AS7: =SUM(AM7:AR7) -> 889 | AT7: =+'Summary Total Pigs'!I205 -> 889 | AU7: =+AS6+AS7+AS8-AT7 -> 0 | AV7: =+'Summary Total Pigs'!H32 -> 1203 | AW7: =+'Summary Total Pigs'!I32 -> 190 | AX7: =+'Summary Total Pigs'!E32 -> 0 | AY7: =+'Summary Total Pigs'!G32 -> 0 | AZ7: =+'Summary Total Pigs'!F32 -> 0 | BA7: =+'Summary Total Pigs'!K32 -> 108 | BB7: =SUM(AV7:BA7) -> 1501 | BC7: =+'Summary Total Pigs'!I204 -> 1501 | BD7: =+BB6+BB7+BB8-BC7 -> 0 | BE7: =+'Summary Total Pigs'!K128 -> 0 | BF7: =+'Summary Total Pigs'!I128 -> 0 | BG7: =+'Summary Total Pigs'!F128 -> 0 | BH7: =+'Summary Total Pigs'!E128 -> 0 | BI7: =+'Summary Total Pigs'!G128 -> 0 | BJ7: =+'Summary Total Pigs'!H128 -> 0 | BK7: =SUM(BE7:BJ7) -> 0 | BL7: =+'Summary Total Pigs'!I206 -> 0 | BM7: =+BK6+BK7+BK8-BL7 -> 0 | BN7: =SUM(C7:H7,L7:Q7,U7:Z7,AD7:AI7,AM7:AR7,AV7:BA7,BE7:BJ7) -> 2390
A8: GROWERS | C8: =+'Summary Total Pigs'!E14 -> 0 | D8: =+'Summary Total Pigs'!G14 -> 0 | E8: =+'Summary Total Pigs'!I14 -> 0 | F8: =+'Summary Total Pigs'!F14 -> 0 | G8: =+'Summary Total Pigs'!H14 -> 0 | H8: =+'Summary Total Pigs'!K14 -> 0 | I8: =SUM(C8:H8) -> 0 | L8: =+'Summary Total Pigs'!E52 -> 0 | M8: =+'Summary Total Pigs'!G52 -> 0 | N8: =+'Summary Total Pigs'!I52 -> 0 | O8: =+'Summary Total Pigs'!F52 -> 0 | P8: =+'Summary Total Pigs'!H52 -> 0 | Q8: =+'Summary Total Pigs'!K52 -> 0 | R8: =SUM(L8:Q8) -> 0 | U8: =+'Summary Total Pigs'!E91 -> 0 | V8: =+'Summary Total Pigs'!I91 -> 0 | W8: =+'Summary Total Pigs'!F91 -> 0 | X8: =+'Summary Total Pigs'!G91 -> 0 | Y8: =+'Summary Total Pigs'!H91 -> 0 | Z8: =+'Summary Total Pigs'!K91 -> 0 | AA8: =SUM(U8:Z8) -> 0 | AD8: =+'Summary Total Pigs'!E110 -> 0 | AE8: =+'Summary Total Pigs'!I110 -> 0 | AF8: =+'Summary Total Pigs'!F110 -> 0 | AG8: =+'Summary Total Pigs'!G110 -> 0 | AH8: =+'Summary Total Pigs'!H110 -> 0 | AI8: =+'Summary Total Pigs'!K110 -> 0 | AJ8: =SUM(AD8:AI8) -> 0 | AM8: =+'Summary Total Pigs'!E71 -> 0 | AN8: =+'Summary Total Pigs'!I71 -> 0 | AO8: =+'Summary Total Pigs'!F71 -> 0 | AP8: =+'Summary Total Pigs'!G71 -> 0 | AQ8: =+'Summary Total Pigs'!H71 -> 0 | AR8: =+'Summary Total Pigs'!K71 -> 0 | AS8: =SUM(AM8:AR8) -> 0 | AV8: =+'Summary Total Pigs'!H33 -> 0 | AW8: =+'Summary Total Pigs'!I33 -> 0 | AX8: =+'Summary Total Pigs'!E33 -> 0 | AY8: =+'Summary Total Pigs'!G33 -> 0 | AZ8: =+'Summary Total Pigs'!F33 -> 0 | BA8: =+'Summary Total Pigs'!K33 -> 0 | BB8: =SUM(AV8:BA8) -> 0 | BE8: =+'Summary Total Pigs'!K129 -> 0 | BF8: =+'Summary Total Pigs'!I129 -> 0 | BG8: =+'Summary Total Pigs'!F129 -> 0 | BH8: =+'Summary Total Pigs'!E129 -> 0 | BI8: =+'Summary Total Pigs'!G129 -> 0 | BJ8: =+'Summary Total Pigs'!H129 -> 0 | BK8: =SUM(BE8:BJ8) -> 0 | BN8: =SUM(C8:H8,L8:Q8,U8:Z8,AD8:AI8,AM8:AR8,AV8:BA8,BE8:BJ8) -> 0
A9: GILTS | C9: =+'Summary Total Pigs'!E15 -> 0 | D9: =+'Summary Total Pigs'!G15 -> 0 | E9: =+'Summary Total Pigs'!I15 -> 0 | F9: =+'Summary Total Pigs'!F15 -> 0 | G9: =+'Summary Total Pigs'!H15 -> 0 | H9: =+'Summary Total Pigs'!K15 -> 0 | I9: =SUM(C9:H9) -> 0 | J9: =+'Summary Total Pigs'!E200 -> 95 | K9: =+I9-J9 -> -95 | L9: =+'Summary Total Pigs'!E53 -> 0 | M9: =+'Summary Total Pigs'!G53 -> 0 | N9: =+'Summary Total Pigs'!I53 -> 0 | O9: =+'Summary Total Pigs'!F53 -> 0 | P9: =+'Summary Total Pigs'!H53 -> 0 | Q9: =+'Summary Total Pigs'!K53 -> 0 | R9: =SUM(L9:Q9) -> 0 | S9: =+'Summary Total Pigs'!E201 -> 43 | T9: =+R9-S9 -> -43 | U9: =+'Summary Total Pigs'!E92 -> 0 | V9: =+'Summary Total Pigs'!I92 -> 0 | W9: =+'Summary Total Pigs'!F92 -> 0 | X9: =+'Summary Total Pigs'!G92 -> 0 | Y9: =+'Summary Total Pigs'!H92 -> 0 | Z9: =+'Summary Total Pigs'!K92 -> 0 | AA9: =SUM(U9:Z9) -> 0 | AB9: =+'Summary Total Pigs'!E202 -> 17 | AC9: =+AA9-AB9 -> -17 | AD9: =+'Summary Total Pigs'!E111 -> 0 | AE9: =+'Summary Total Pigs'!I111 -> 0 | AF9: =+'Summary Total Pigs'!F111 -> 0 | AG9: =+'Summary Total Pigs'!G111 -> 0 | AH9: =+'Summary Total Pigs'!H111 -> 0 | AI9: =+'Summary Total Pigs'!K111 -> 0 | AJ9: =SUM(AD9:AI9) -> 0 | AK9: =+'Summary Total Pigs'!E203 -> 0 | AL9: =+AJ9-AK9 -> 0 | AM9: =+'Summary Total Pigs'!E72 -> 0 | AN9: =+'Summary Total Pigs'!I72 -> 0 | AO9: =+'Summary Total Pigs'!F72 -> 0 | AP9: =+'Summary Total Pigs'!G72 -> 0 | AQ9: =+'Summary Total Pigs'!H72 -> 0 | AR9: =+'Summary Total Pigs'!K72 -> 0 | AS9: =SUM(AM9:AR9) -> 0 | AT9: =+'Summary Total Pigs'!E205 -> 0 | AU9: =+AS9-AT9 -> 0 | AV9: =+'Summary Total Pigs'!H34 -> 0 | AW9: =+'Summary Total Pigs'!I34 -> 0 | AX9: =+'Summary Total Pigs'!E34 -> 0 | AY9: =+'Summary Total Pigs'!G34 -> 0 | AZ9: =+'Summary Total Pigs'!F34 -> 0 | BA9: =+'Summary Total Pigs'!K34 -> 0 | BB9: =SUM(AV9:BA9) -> 0 | BC9: =+'Summary Total Pigs'!E204 -> 0 | BD9: =+BB9-BC9 -> 0 | BE9: =+'Summary Total Pigs'!K130 -> 0 | BF9: =+'Summary Total Pigs'!I130 -> 0 | BG9: =+'Summary Total Pigs'!F130 -> 0 | BH9: =+'Summary Total Pigs'!E130 -> 0 | BI9: =+'Summary Total Pigs'!G130 -> 0 | BJ9: =+'Summary Total Pigs'!H130 -> 0 | BK9: =SUM(BE9:BJ9) -> 0 | BL9: =+'Summary Total Pigs'!E206 -> 11 | BM9: =+BK9-BL9 -> -11 | BN9: =SUM(C9:H9,L9:Q9,U9:Z9,AD9:AI9,AM9:AR9,AV9:BA9,BE9:BJ9) -> 0
A10: SOWS | C10: =+'Summary Total Pigs'!E16 -> 0 | D10: =+'Summary Total Pigs'!G16 -> 0 | E10: =+'Summary Total Pigs'!I16 -> 0 | F10: =+'Summary Total Pigs'!F16 -> 0 | G10: =+'Summary Total Pigs'!H16 -> 0 | H10: =+'Summary Total Pigs'!K16 -> 0 | I10: =SUM(C10:H10) -> 0 | J10: =+'Summary Total Pigs'!G200 -> 0 | K10: =+I10+I11-J10 -> 0 | L10: =+'Summary Total Pigs'!E54 -> 0 | M10: =+'Summary Total Pigs'!G54 -> 0 | N10: =+'Summary Total Pigs'!I54 -> 0 | O10: =+'Summary Total Pigs'!F54 -> 0 | P10: =+'Summary Total Pigs'!H54 -> 0 | Q10: =+'Summary Total Pigs'!K54 -> 0 | R10: =SUM(L10:Q10) -> 0 | S10: =+'Summary Total Pigs'!G201 -> 0 | T10: =+R10+R11-S10 -> 0 | U10: =+'Summary Total Pigs'!E93 -> 0 | V10: =+'Summary Total Pigs'!I93 -> 0 | W10: =+'Summary Total Pigs'!F93 -> 0 | X10: =+'Summary Total Pigs'!G93 -> 0 | Y10: =+'Summary Total Pigs'!H93 -> 0 | Z10: =+'Summary Total Pigs'!K93 -> 0 | AA10: =SUM(U10:Z10) -> 0 | AB10: =+'Summary Total Pigs'!G202 -> 0 | AC10: =+AA10+AA11-AB10 -> 0 | AD10: =+'Summary Total Pigs'!E112 -> 0 | AE10: =+'Summary Total Pigs'!I112 -> 0 | AF10: =+'Summary Total Pigs'!F112 -> 0 | AG10: =+'Summary Total Pigs'!G112 -> 0 | AH10: =+'Summary Total Pigs'!H112 -> 0 | AI10: =+'Summary Total Pigs'!K112 -> 0 | AJ10: =SUM(AD10:AI10) -> 0 | AK10: =+'Summary Total Pigs'!G203 -> 0 | AL10: =+AJ10+AJ11-AK10 -> 0 | AM10: =+'Summary Total Pigs'!E73 -> 0 | AN10: =+'Summary Total Pigs'!I73 -> 0 | AO10: =+'Summary Total Pigs'!F73 -> 0 | AP10: =+'Summary Total Pigs'!G73 -> 0 | AQ10: =+'Summary Total Pigs'!H73 -> 0 | AR10: =+'Summary Total Pigs'!K73 -> 0 | AS10: =SUM(AM10:AR10) -> 0 | AT10: =+'Summary Total Pigs'!G205 -> 0 | AU10: =+AS10+AS11-AT10 -> 0 | AV10: =+'Summary Total Pigs'!H35 -> 0 | AW10: =+'Summary Total Pigs'!I35 -> 0 | AX10: =+'Summary Total Pigs'!E35 -> 0 | AY10: =+'Summary Total Pigs'!G35 -> 0 | AZ10: =+'Summary Total Pigs'!F35 -> 0 | BA10: =+'Summary Total Pigs'!K35 -> 0 | BB10: =SUM(AV10:BA10) -> 0 | BC10: =+'Summary Total Pigs'!G204 -> 0 | BD10: =+BB10+BB11-BC10 -> 0 | BE10: =+'Summary Total Pigs'!K131 -> 0 | BF10: =+'Summary Total Pigs'!I131 -> 0 | BG10: =+'Summary Total Pigs'!F131 -> 0 | BH10: =+'Summary Total Pigs'!E131 -> 0 | BI10: =+'Summary Total Pigs'!G131 -> 0 | BJ10: =+'Summary Total Pigs'!H131 -> 0 | BK10: =SUM(BE10:BJ10) -> 0 | BL10: =+'Summary Total Pigs'!G206 -> 1 | BM10: =+BK10+BK11-BL10 -> 0 | BN10: =SUM(C10:H10,L10:Q10,U10:Z10,AD10:AI10,AM10:AR10,AV10:BA10,BE10:BJ10) -> 0
A11: BOARS | C11: =+'Summary Total Pigs'!E17 -> 0 | D11: =+'Summary Total Pigs'!G17 -> 0 | E11: =+'Summary Total Pigs'!I17 -> 0 | F11: =+'Summary Total Pigs'!F17 -> 0 | G11: =+'Summary Total Pigs'!H17 -> 0 | H11: =+'Summary Total Pigs'!K17 -> 0 | I11: =SUM(C11:H11) -> 0 | L11: =+'Summary Total Pigs'!E55 -> 0 | M11: =+'Summary Total Pigs'!G55 -> 0 | N11: =+'Summary Total Pigs'!I55 -> 0 | O11: =+'Summary Total Pigs'!F55 -> 0 | P11: =+'Summary Total Pigs'!H55 -> 0 | Q11: =+'Summary Total Pigs'!K55 -> 0 | R11: =SUM(L11:Q11) -> 0 | U11: =+'Summary Total Pigs'!E94 -> 0 | V11: =+'Summary Total Pigs'!I94 -> 0 | W11: =+'Summary Total Pigs'!F94 -> 0 | X11: =+'Summary Total Pigs'!G94 -> 0 | Y11: =+'Summary Total Pigs'!H94 -> 0 | Z11: =+'Summary Total Pigs'!K94 -> 0 | AA11: =SUM(U11:Z11) -> 0 | AD11: =+'Summary Total Pigs'!E113 -> 0 | AE11: =+'Summary Total Pigs'!I113 -> 0 | AF11: =+'Summary Total Pigs'!F113 -> 0 | AG11: =+'Summary Total Pigs'!G113 -> 0 | AH11: =+'Summary Total Pigs'!H113 -> 0 | AI11: =+'Summary Total Pigs'!K113 -> 0 | AJ11: =SUM(AD11:AI11) -> 0 | AM11: =+'Summary Total Pigs'!E74 -> 0 | AN11: =+'Summary Total Pigs'!I74 -> 0 | AO11: =+'Summary Total Pigs'!F74 -> 0 | AP11: =+'Summary Total Pigs'!G74 -> 0 | AQ11: =+'Summary Total Pigs'!H74 -> 0 | AR11: =+'Summary Total Pigs'!K74 -> 0 | AS11: =SUM(AM11:AR11) -> 0 | AV11: =+'Summary Total Pigs'!H36 -> 0 | AW11: =+'Summary Total Pigs'!I36 -> 0 | AX11: =+'Summary Total Pigs'!E36 -> 0 | AY11: =+'Summary Total Pigs'!G36 -> 0 | AZ11: =+'Summary Total Pigs'!F36 -> 0 | BA11: =+'Summary Total Pigs'!K36 -> 0 | BB11: =SUM(AV11:BA11) -> 0 | BE11: =+'Summary Total Pigs'!K132 -> 1 | BF11: =+'Summary Total Pigs'!I132 -> 0 | BG11: =+'Summary Total Pigs'!F132 -> 0 | BH11: =+'Summary Total Pigs'!E132 -> 0 | BI11: =+'Summary Total Pigs'!G132 -> 0 | BJ11: =+'Summary Total Pigs'!H132 -> 0 | BK11: =SUM(BE11:BJ11) -> 1 | BN11: =SUM(C11:H11,L11:Q11,U11:Z11,AD11:AI11,AM11:AR11,AV11:BA11,BE11:BJ11) -> 1
C12: =SUM(C6:C11) -> 0 | D12: =SUM(D6:D11) -> 0 | E12: =SUM(E6:E11) -> 0 | F12: =SUM(F6:F11) -> 0 | G12: =SUM(G6:G11) -> 0 | H12: =SUM(H6:H11) -> 0 | I12: =SUM(I6:I11) -> 0 | J12: =SUM(J6:J11) -> 95 | K12: =+I12-J12 -> -95 | L12: =SUM(L6:L11) -> 0 | M12: =SUM(M6:M11) -> 0 | N12: =SUM(N6:N11) -> 0 | O12: =SUM(O6:O11) -> 0 | P12: =SUM(P6:P11) -> 0 | Q12: =SUM(Q6:Q11) -> 0 | R12: =SUM(R6:R11) -> 0 | S12: =SUM(S6:S11) -> 43 | U12: =SUM(U6:U11) -> 0 | V12: =SUM(V6:V11) -> 0 | W12: =SUM(W6:W11) -> 0 | X12: =SUM(X6:X11) -> 0 | Y12: =SUM(Y6:Y11) -> 0 | Z12: =SUM(Z6:Z11) -> 0 | AA12: =SUM(AA6:AA11) -> 0 | AB12: =SUM(AB6:AB11) -> 17 | AD12: =SUM(AD6:AD11) -> 0 | AE12: =SUM(AE6:AE11) -> 0 | AF12: =SUM(AF6:AF11) -> 0 | AG12: =SUM(AG6:AG11) -> 0 | AH12: =SUM(AH6:AH11) -> 0 | AI12: =SUM(AI6:AI11) -> 0 | AJ12: =SUM(AJ6:AJ11) -> 0 | AK12: =SUM(AK6:AK11) -> 0 | AM12: =SUM(AM6:AM11) -> 0 | AN12: =SUM(AN6:AN11) -> 250 | AO12: =SUM(AO6:AO11) -> 119 | AP12: =SUM(AP6:AP11) -> 380 | AQ12: =SUM(AQ6:AQ11) -> 0 | AR12: =SUM(AR6:AR11) -> 140 | AS12: =SUM(AS6:AS11) -> 889 | AT12: =SUM(AT6:AT11) -> 889 | AV12: =SUM(AV6:AV11) -> 1203 | AW12: =SUM(AW6:AW11) -> 190 | AX12: =SUM(AX6:AX11) -> 0 | AY12: =SUM(AY6:AY11) -> 0 | AZ12: =SUM(AZ6:AZ11) -> 0 | BA12: =SUM(BA6:BA11) -> 108 | BB12: =SUM(BB6:BB11) -> 1501 | BC12: =SUM(BC6:BC11) -> 1501 | BE12: =SUM(BE6:BE11) -> 1 | BF12: =SUM(BF6:BF11) -> 0 | BG12: =SUM(BG6:BG11) -> 0 | BH12: =SUM(BH6:BH11) -> 0 | BI12: =SUM(BI6:BI11) -> 0 | BJ12: =SUM(BJ6:BJ11) -> 0 | BK12: =SUM(BK6:BK11) -> 1 | BL12: =SUM(BL6:BL11) -> 12 | BN12: =SUM(BN6:BN11) -> 2391
C14: Transfer Out | L14: Transfer Out | U14: Transfer Out | AD14: Transfer Out | AM14: Transfer Out | AV14: Transfer Out | BE14: Transfer Out
C15: Grasmere | L15: Lionhead | U15: Villa | AD15: Richlands | AM15: Lionhead Ext | AV15: Learig | BE15: Quarantine
C16: Lionhead | D16: Richlands | E16: Villa Franca | F16: Lionhead Ext | G16: Learig | H16: Quarantine | I16: Total | L16: Grasmere | M16: Richlands | N16: Villa Franca | O16: Lionhead Ext | P16: Learig | Q16: Quarantine | R16: Total | U16: Grasmere | V16: Richlands | W16: Lionhead | X16: Lionhead Ext | Y16: Learig | Z16: Quarantine | AA16: Total | AD16: Grasmere | AE16: Villa | AF16: Lionhead | AG16: Lionhead Ext | AH16: Learig | AI16: Quarantine | AJ16: Total | AM16: Grasmere | AN16: Villa | AO16: Lionhead | AP16: Richlands | AQ16: Learig | AR16: Quarantine | AS16: Total | AV16: Grasmere | AW16: Villa | AX16: Lionhead | AY16: Richlands | AZ16: Lionhead Ext. | BA16: Quarantine | BB16: Total | BE16: Grasmere | BF16: Villa | BG16: Lionhead | BH16: Richlands | BI16: Lionhead Ext. | BJ16: Learig | BK16: Total
A17: =+A6 -> PIGLETS | C17: =+'Summary Total Pigs'!O12 -> 0 | D17: =+'Summary Total Pigs'!Q12 -> 0 | E17: =+'Summary Total Pigs'!S12 -> 0 | F17: =+'Summary Total Pigs'!P12 -> 0 | G17: =+'Summary Total Pigs'!R12 -> -1203 | H17: =+'Summary Total Pigs'!T12 -> 0 | I17: =SUM(C17:H17) -> -1203 | L17: =+'Summary Total Pigs'!O50 -> 0 | M17: =+'Summary Total Pigs'!Q50 -> 0 | N17: =+'Summary Total Pigs'!S50 -> 0 | O17: =+'Summary Total Pigs'!P50 -> -84 | P17: =+'Summary Total Pigs'!R50 -> 0 | Q17: =+'Summary Total Pigs'!T50 -> 0 | R17: =SUM(L17:Q17) -> -84 | U17: =+'Summary Total Pigs'!O89 -> 0 | V17: =+'Summary Total Pigs'!S89 -> 0 | W17: =+'Summary Total Pigs'!P89 -> 0 | X17: =+'Summary Total Pigs'!Q89 -> -250 | Y17: =+'Summary Total Pigs'!R89 -> -190 | Z17: =+'Summary Total Pigs'!T89 -> 0 | AA17: =SUM(U17:Z17) -> -440 | AD17: =+'Summary Total Pigs'!O108 -> 0 | AE17: =+'Summary Total Pigs'!S108 -> 0 | AF17: =+'Summary Total Pigs'!P108 -> 0 | AG17: =+'Summary Total Pigs'!Q108 -> 0 | AH17: =+'Summary Total Pigs'!R108 -> 0 | AI17: =+'Summary Total Pigs'!T108 -> 0 | AJ17: =SUM(AD17:AI17) -> 0 | AM17: =+'Summary Total Pigs'!O69 -> 0 | AN17: =+'Summary Total Pigs'!Q69 -> 0 | AO17: =+'Summary Total Pigs'!P69 -> 0 | AP17: =+'Summary Total Pigs'!S69 -> 0 | AQ17: =+'Summary Total Pigs'!R69 -> 0 | AR17: =+'Summary Total Pigs'!T69 -> 0 | AS17: =SUM(AM17:AR17) -> 0 | AV17: =+'Summary Total Pigs'!R31 -> 0 | AW17: =+'Summary Total Pigs'!S31 -> 0 | AX17: =+'Summary Total Pigs'!O31 -> 0 | AY17: =+'Summary Total Pigs'!Q31 -> 0 | AZ17: =+'Summary Total Pigs'!P31 -> 0 | BA17: =+'Summary Total Pigs'!T31 -> 0 | BB17: =SUM(AV17:BA17) -> 0 | BE17: =+'Summary Total Pigs'!T127 -> 0 | BF17: =+'Summary Total Pigs'!S127 -> 0 | BG17: =+'Summary Total Pigs'!P127 -> 0 | BH17: =+'Summary Total Pigs'!O127 -> 0 | BI17: =+'Summary Total Pigs'!Q127 -> 0 | BJ17: =+'Summary Total Pigs'!R127 -> 0 | BK17: =SUM(BE17:BJ17) -> 0 | BN17: =SUM(C17:H17,L17:Q17,U17:Z17,AD17:AI17,AM17:AR17,AV17:BA17,BE17:BJ17) -> -1727
A18: =+A7 -> WEANER | C18: =+'Summary Total Pigs'!O13 -> 0 | D18: =+'Summary Total Pigs'!Q13 -> 0 | E18: =+'Summary Total Pigs'!S13 -> 0 | F18: =+'Summary Total Pigs'!P13 -> 0 | G18: =+'Summary Total Pigs'!R13 -> 0 | H18: =+'Summary Total Pigs'!T13 -> 0 | I18: =SUM(C18:H18) -> 0 | J18: =+'Summary Total Pigs'!J200 -> -1203 | K18: =+I17+I18+I19-J18 -> 0 | L18: =+'Summary Total Pigs'!O51 -> 0 | M18: =+'Summary Total Pigs'!Q51 -> 0 | N18: =+'Summary Total Pigs'!S51 -> 0 | O18: =+'Summary Total Pigs'!P51 -> -36 | P18: =+'Summary Total Pigs'!R51 -> 0 | Q18: =+'Summary Total Pigs'!T51 -> 0 | R18: =SUM(L18:Q18) -> -36 | S18: =+'Summary Total Pigs'!J201 -> -120 | T18: =+R17+R18+R19-S18 -> 0 | U18: =+'Summary Total Pigs'!O90 -> 0 | V18: =+'Summary Total Pigs'!S90 -> 0 | W18: =+'Summary Total Pigs'!P90 -> 0 | X18: =+'Summary Total Pigs'!Q90 -> 0 | Y18: =+'Summary Total Pigs'!R90 -> 0 | Z18: =+'Summary Total Pigs'!T90 -> 0 | AA18: =SUM(U18:Z18) -> 0 | AB18: =+'Summary Total Pigs'!J202 -> -440 | AC18: =+AA17+AA18+AA19-AB18 -> 0 | AD18: =+'Summary Total Pigs'!O109 -> 0 | AE18: =+'Summary Total Pigs'!S109 -> 0 | AF18: =+'Summary Total Pigs'!P109 -> 0 | AG18: =+'Summary Total Pigs'!Q109 -> -380 | AH18: =+'Summary Total Pigs'!R109 -> 0 | AI18: =+'Summary Total Pigs'!T109 -> 0 | AJ18: =SUM(AD18:AI18) -> -380 | AK18: =+'Summary Total Pigs'!J203 -> -380 | AL18: =+AJ17+AJ18+AJ19-AK18 -> 0 | AM18: =+'Summary Total Pigs'!O70 -> 0 | AN18: =+'Summary Total Pigs'!Q70 -> 0 | AO18: =+'Summary Total Pigs'!P70 -> 0 | AP18: =+'Summary Total Pigs'!S70 -> 0 | AQ18: =+'Summary Total Pigs'!R70 -> 0 | AR18: =+'Summary Total Pigs'!T70 -> 0 | AS18: =SUM(AM18:AR18) -> 0 | AT18: =+'Summary Total Pigs'!J205 -> 0 | AU18: =+AS17+AS18+AS19-AT18 -> 0 | AV18: =+'Summary Total Pigs'!R32 -> 0 | AW18: =+'Summary Total Pigs'!S32 -> 0 | AX18: =+'Summary Total Pigs'!O32 -> 0 | AY18: =+'Summary Total Pigs'!Q32 -> 0 | AZ18: =+'Summary Total Pigs'!P32 -> 0 | BA18: =+'Summary Total Pigs'!T32 -> 0 | BB18: =SUM(AV18:BA18) -> 0 | BC18: =+'Summary Total Pigs'!J204 -> 0 | BD18: =+BB17+BB18+BB19-BC18 -> 0 | BE18: =+'Summary Total Pigs'!T128 -> 0 | BF18: =+'Summary Total Pigs'!S128 -> 0 | BG18: =+'Summary Total Pigs'!P128 -> 0 | BH18: =+'Summary Total Pigs'!O128 -> 0 | BI18: =+'Summary Total Pigs'!Q128 -> 0 | BJ18: =+'Summary Total Pigs'!R128 -> 0 | BK18: =SUM(BE18:BJ18) -> 0 | BL18: =+'Summary Total Pigs'!J206 -> 0 | BM18: =+BK17+BK18+BK19-BL18 -> 0 | BN18: =SUM(C18:H18,L18:Q18,U18:Z18,AD18:AI18,AM18:AR18,AV18:BA18,BE18:BJ18) -> -416
A19: =+A8 -> GROWERS | C19: =+'Summary Total Pigs'!O14 -> 0 | D19: =+'Summary Total Pigs'!Q14 -> 0 | E19: =+'Summary Total Pigs'!S14 -> 0 | F19: =+'Summary Total Pigs'!P14 -> 0 | G19: =+'Summary Total Pigs'!R14 -> 0 | H19: =+'Summary Total Pigs'!T14 -> 0 | I19: =SUM(C19:H19) -> 0 | L19: =+'Summary Total Pigs'!O52 -> 0 | M19: =+'Summary Total Pigs'!Q52 -> 0 | N19: =+'Summary Total Pigs'!S52 -> 0 | O19: =+'Summary Total Pigs'!P52 -> 0 | P19: =+'Summary Total Pigs'!R52 -> 0 | Q19: =+'Summary Total Pigs'!T52 -> 0 | R19: =SUM(L19:Q19) -> 0 | U19: =+'Summary Total Pigs'!O91 -> 0 | V19: =+'Summary Total Pigs'!S91 -> 0 | W19: =+'Summary Total Pigs'!P91 -> 0 | X19: =+'Summary Total Pigs'!Q91 -> 0 | Y19: =+'Summary Total Pigs'!R91 -> 0 | Z19: =+'Summary Total Pigs'!T91 -> 0 | AA19: =SUM(U19:Z19) -> 0 | AD19: =+'Summary Total Pigs'!O110 -> 0 | AE19: =+'Summary Total Pigs'!S110 -> 0 | AF19: =+'Summary Total Pigs'!P110 -> 0 | AG19: =+'Summary Total Pigs'!Q110 -> 0 | AH19: =+'Summary Total Pigs'!R110 -> 0 | AI19: =+'Summary Total Pigs'!T110 -> 0 | AJ19: =SUM(AD19:AI19) -> 0 | AM19: =+'Summary Total Pigs'!O71 -> 0 | AN19: =+'Summary Total Pigs'!Q71 -> 0 | AO19: =+'Summary Total Pigs'!P71 -> 0 | AP19: =+'Summary Total Pigs'!S71 -> 0 | AQ19: =+'Summary Total Pigs'!R71 -> 0 | AR19: =+'Summary Total Pigs'!T71 -> 0 | AS19: =SUM(AM19:AR19) -> 0 | AV19: =+'Summary Total Pigs'!R33 -> 0 | AW19: =+'Summary Total Pigs'!S33 -> 0 | AX19: =+'Summary Total Pigs'!O33 -> 0 | AY19: =+'Summary Total Pigs'!Q33 -> 0 | AZ19: =+'Summary Total Pigs'!P33 -> 0 | BA19: =+'Summary Total Pigs'!T33 -> 0 | BB19: =SUM(AV19:BA19) -> 0 | BE19: =+'Summary Total Pigs'!T129 -> 0 | BF19: =+'Summary Total Pigs'!S129 -> 0 | BG19: =+'Summary Total Pigs'!P129 -> 0 | BH19: =+'Summary Total Pigs'!O129 -> 0 | BI19: =+'Summary Total Pigs'!Q129 -> 0 | BJ19: =+'Summary Total Pigs'!R129 -> 0 | BK19: =SUM(BE19:BJ19) -> 0 | BN19: =SUM(C19:H19,L19:Q19,U19:Z19,AD19:AI19,AM19:AR19,AV19:BA19,BE19:BJ19) -> 0
